Workbook
Name ActiveList: _xlfn.ANCHORARRAY(Assumptions!$B$16)
Name asset_renewal: Assets!$E$21:$E$29
Name asset_sentence: Assets!$B$31
Name assets_table: Assets!$B$6
Name BaseYear: Assumptions!$E$12
Name checks_status: Checks!$G$5:$G$21
Name checks_summary: Checks!$B$2
Name dash_commentary: Dashboard!$B$18:$B$22
Name dash_tiles: Dashboard!$B$6:$M$6,Dashboard!$B$12:$M$12
Name debt_amount: Debt!$F$16
Name debt_capacity: Debt!$F$8
Name debt_capacity_after: Debt!$F$18
Name debt_history: Debt!$B$25:$E$30
Name debt_limit: Debt!$F$6
Name debt_limit_used: Debt!$F$9
Name debt_max_borrowing: Debt!$F$19
Name debt_outstanding: Debt!$F$10
Name debt_payment: Debt!$F$17
Name debt_rate: Debt!$F$14
Name debt_revenue_for_limit: Debt!$F$5
Name debt_sentence: Debt!$B$21
Name debt_servicing: Debt!$F$7
Name debt_term: Debt!$F$15
Name LatestYear: Assumptions!$E$11
Name peer_benchmark: Peers!$B$6:$I$18
Name peer_metric_input: Peers!$D$22
Name peer_ranking: Peers!$B$24
Name plan_avg_increase: Plan!$E$32
Name plan_base_capital: Plan!$J$9
Name plan_base_year: Plan!$J$5
Name plan_closure: Plan!$E$8
Name plan_cost_growth: Plan!$J$7
Name plan_cpi: Plan!$E$5
Name plan_debt: Plan!$E$9
Name plan_gap: Plan!$J$10
Name plan_grid: Plan!$D$37:$H$41
Name plan_pop_growth: Plan!$J$6
Name plan_rate: Plan!$E$11
Name plan_reserve: Plan!$E$10
Name plan_rev_growth: Plan!$J$8
Name plan_sentence: Plan!$B$33
Name plan_table: Plan!$D$16:$I$30
Name plan_term: Plan!$E$12
Name plan_wage: Plan!$E$6
Name plan_wage_share: Plan!$E$7
Name plan_year1_increase: Plan!$E$26
Name profile_block: Profile!$D$6:$I$35
Name profile_keys: Profile!$C$6:$C$35
Name profile_years: Profile!$D$5:$I$5
Name prov_amp_full: Province!$H$19
Name prov_below: Province!$H$16
Name prov_missing: Province!$H$20
Name prov_not_reported: Province!$H$18
Name prov_reinvestment: Province!$H$17
Name prov_screened: Province!$H$15
Name prov_vancouver_rate: Province!$H$21
Name province_sentence: Province!$B$23
Name province_trend: Province!$B$6:$J$11
Name Selected: Dashboard!$C$3
Name SelId: Assumptions!$E$5

Sheet Cover
B2: BC local government finance model
B3: ="Every municipality in British Columbia, 2019-"&LatestYear&": benchmarks, infrastructure renewal, a five-year financial plan, property tax by class and borrowing room. Now showing: "&Selected&"." -> Every municipality in British Columbia, 2019-2024: benchmarks, infrastructure renewal, a five-year financial plan, property tax by class and borrowing room. Now showing: Fernie.
B5: Independent analysis of the Province of British Columbia's Local Government Statistics. Not affiliated with or endorsed by any municipality or by the Province.
B7: How to use it
B8: 1. Pick a municipality in the yellow cell on the Dashboard. Every sheet follows.
B9: 2. Change the plan drivers on Plan: inflation, wages, how much of the renewal gap to close, and how much of it to borrow.
B10: 3. Test a levy change on Tax, and a borrowing amount on Debt.
B11: 4. Rank a municipality's tier on any metric on Peers.
B12: 5. Checks proves the numbers; Province shows how far the asset data can be trusted.
B14: Sheets
B15: Dashboard | C15: Eight tiles against the peer tier, five sentences written by formulas, two charts
B16: Profile | C16: Six years of revenue, expenses, position, debt, assets and tax
B17: Peers | C17: Thirteen metrics with tier and province percentiles; the tier ranked on any of them
B18: Assets | C18: Schedule 503 by category; renewal need and the reinvestment ratio
B19: Plan | C19: A five-year financial plan and a what-if data table over its two big choices
B20: Tax | C20: Assessment, rates and multiples by class; a levy-to-rates calculator
B21: Debt | C21: The legal servicing limit, the room left, and what it would borrow
B22: Province | C22: Totals by year and the asset data-quality screen
B23: Checks | C23: 17 controls, each with a tolerance
B25: Sources
B26: Province of British Columbia, Ministry of Municipal Affairs: Local Government Statistics, schedules 201-707, 2019-2024. Open Government Licence – British Columbia.
B27: Pipeline: pipeline/ (bronze and silver, held to contracts), dbt/ (gold marts and 31 data tests). data/sources.json records every file's URL and SHA-256.

Sheet Dashboard
B1: ="BC local government finance: "&Selected -> BC local government finance: Fernie
B3: Municipality | C3: Fernie | G3: {=SelType&" in the "&SelRD&" regional district · population "&TEXT(YV(tbl_Year[population],LatestYear),"#,##0")&" · peer tier "&SelTierLabel&" ("&SelTierCount&" municipalities) · statements through "&BaseYear} -> City in the EKO regional district · population 6,000 · peer tier 2,500 to 9,999 residents (47 municipalities) · statements through 2024
B5: Own-source share of revenue | E5: Share of the legal debt-servicing limit used | H5: Reserves against a year of cash spending | K5: Share of asset life used up
B6: {=_xlfn.LET(_xlpm.v,_xlfn.XLOOKUP(SelId,tbl_Peers[municipality_id],_xlfn.XLOOKUP("own_source_share",tbl_Peers[#Headers],tbl_Peers[]),""),IF(_xlpm.v="","not reported",_xlpm.v))} -> 0.89259257 | E6: {=_xlfn.LET(_xlpm.v,_xlfn.XLOOKUP(SelId,tbl_Peers[municipality_id],_xlfn.XLOOKUP("limit_used",tbl_Peers[#Headers],tbl_Peers[]),""),IF(_xlpm.v="","not reported",_xlpm.v))} -> 0.15192215 | H6: {=_xlfn.LET(_xlpm.v,_xlfn.XLOOKUP(SelId,tbl_Peers[municipality_id],_xlfn.XLOOKUP("reserves_to_cash_expenses",tbl_Peers[#Headers],tbl_Peers[]),""),IF(_xlpm.v="","not reported",_xlpm.v))} -> 0.75543501 | K6: {=_xlfn.LET(_xlpm.v,_xlfn.XLOOKUP(SelId,tbl_Peers[municipality_id],_xlfn.XLOOKUP("asset_consumption_ratio",tbl_Peers[#Headers],tbl_Peers[]),""),IF(_xlpm.v="","not reported",_xlpm.v))} -> 0.41173021
B7: {="tier median "&TEXT(_xlfn.XLOOKUP(SelId,tbl_Peers[municipality_id],_xlfn.XLOOKUP("own_source_share_tier_median",tbl_Peers[#Headers],tbl_Peers[])),"0.0%")} -> tier median 77.3% | E7: {="tier median "&TEXT(_xlfn.XLOOKUP(SelId,tbl_Peers[municipality_id],_xlfn.XLOOKUP("limit_used_tier_median",tbl_Peers[#Headers],tbl_Peers[])),"0.0%")} -> tier median 15.4% | H7: {="tier median "&TEXT(_xlfn.XLOOKUP(SelId,tbl_Peers[municipality_id],_xlfn.XLOOKUP("reserves_to_cash_expenses_tier_median",tbl_Peers[#Headers],tbl_Peers[])),"0.00""x""")} -> tier median 1.83x | K7: {="tier median "&TEXT(_xlfn.XLOOKUP(SelId,tbl_Peers[municipality_id],_xlfn.XLOOKUP("asset_consumption_ratio_tier_median",tbl_Peers[#Headers],tbl_Peers[])),"0.0%")} -> tier median 42.6%
B8: =_xlfn.XLOOKUP("own_source_share",Peers!$C$6:$C$18,Peers!$I$6:$I$18) -> better than the tier median | E8: =_xlfn.XLOOKUP("limit_used",Peers!$C$6:$C$18,Peers!$I$6:$I$18) -> better than the tier median | H8: =_xlfn.XLOOKUP("reserves_to_cash_expenses",Peers!$C$6:$C$18,Peers!$I$6:$I$18) -> weaker than the tier median | K8: =_xlfn.XLOOKUP("asset_consumption_ratio",Peers!$C$6:$C$18,Peers!$I$6:$I$18) -> better than the tier median
B9: =IFERROR("percentile in tier: "&TEXT(_xlfn.XLOOKUP("own_source_share",Peers!$C$6:$C$18,Peers!$F$6:$F$18),"0%"),"") -> percentile in tier: 98% | E9: =IFERROR("percentile in tier: "&TEXT(_xlfn.XLOOKUP("limit_used",Peers!$C$6:$C$18,Peers!$F$6:$F$18),"0%"),"") -> percentile in tier: 49% | H9: =IFERROR("percentile in tier: "&TEXT(_xlfn.XLOOKUP("reserves_to_cash_expenses",Peers!$C$6:$C$18,Peers!$F$6:$F$18),"0%"),"") -> percentile in tier: 2% | K9: =IFERROR("percentile in tier: "&TEXT(_xlfn.XLOOKUP("asset_consumption_ratio",Peers!$C$6:$C$18,Peers!$F$6:$F$18),"0%"),"") -> percentile in tier: 40%
B11: Capital reinvestment against renewal need | E11: Taxes and charges on a representative house | H11: Municipal property tax per resident | K11: Long-term debt per resident
B12: {=_xlfn.LET(_xlpm.v,_xlfn.XLOOKUP(SelId,tbl_Peers[municipality_id],_xlfn.XLOOKUP("reinvestment_ratio",tbl_Peers[#Headers],tbl_Peers[]),""),IF(_xlpm.v="","not reported",_xlpm.v))} -> 0.95779831 | E12: {=_xlfn.LET(_xlpm.v,_xlfn.XLOOKUP(SelId,tbl_Peers[municipality_id],_xlfn.XLOOKUP("house_total_charges",tbl_Peers[#Headers],tbl_Peers[]),""),IF(_xlpm.v="","not reported",_xlpm.v))} -> 6264 | H12: {=_xlfn.LET(_xlpm.v,_xlfn.XLOOKUP(SelId,tbl_Peers[municipality_id],_xlfn.XLOOKUP("municipal_tax_per_capita",tbl_Peers[#Headers],tbl_Peers[]),""),IF(_xlpm.v="","not reported",_xlpm.v))} -> 2326.3268 | K12: {=_xlfn.LET(_xlpm.v,_xlfn.XLOOKUP(SelId,tbl_Peers[municipality_id],_xlfn.XLOOKUP("debt_per_capita",tbl_Peers[#Headers],tbl_Peers[]),""),IF(_xlpm.v="","not reported",_xlpm.v))} -> 427.6825
B13: {="tier median "&TEXT(_xlfn.XLOOKUP(SelId,tbl_Peers[municipality_id],_xlfn.XLOOKUP("reinvestment_ratio_tier_median",tbl_Peers[#Headers],tbl_Peers[])),"0.00""x""")} -> tier median 1.06x | E13: {="tier median "&TEXT(_xlfn.XLOOKUP(SelId,tbl_Peers[municipality_id],_xlfn.XLOOKUP("house_total_charges_tier_median",tbl_Peers[#Headers],tbl_Peers[])),"$#,##0")} -> tier median $4,507 | H13: {="tier median "&TEXT(_xlfn.XLOOKUP(SelId,tbl_Peers[municipality_id],_xlfn.XLOOKUP("municipal_tax_per_capita_tier_median",tbl_Peers[#Headers],tbl_Peers[])),"$#,##0")} -> tier median $1,246 | K13: {="tier median "&TEXT(_xlfn.XLOOKUP(SelId,tbl_Peers[municipality_id],_xlfn.XLOOKUP("debt_per_capita_tier_median",tbl_Peers[#Headers],tbl_Peers[])),"$#,##0")} -> tier median $950
B14: =_xlfn.XLOOKUP("reinvestment_ratio",Peers!$C$6:$C$18,Peers!$I$6:$I$18) -> weaker than the tier median | E14: =_xlfn.XLOOKUP("house_total_charges",Peers!$C$6:$C$18,Peers!$I$6:$I$18) -> weaker than the tier median | H14: =_xlfn.XLOOKUP("municipal_tax_per_capita",Peers!$C$6:$C$18,Peers!$I$6:$I$18) -> above the tier median | K14: =_xlfn.XLOOKUP("debt_per_capita",Peers!$C$6:$C$18,Peers!$I$6:$I$18) -> better than the tier median
B15: =IFERROR("percentile in tier: "&TEXT(_xlfn.XLOOKUP("reinvestment_ratio",Peers!$C$6:$C$18,Peers!$F$6:$F$18),"0%"),"") -> percentile in tier: 44% | E15: =IFERROR("percentile in tier: "&TEXT(_xlfn.XLOOKUP("house_total_charges",Peers!$C$6:$C$18,Peers!$F$6:$F$18),"0%"),"") -> percentile in tier: 87% | H15: =IFERROR("percentile in tier: "&TEXT(_xlfn.XLOOKUP("municipal_tax_per_capita",Peers!$C$6:$C$18,Peers!$F$6:$F$18),"0%"),"") -> percentile in tier: 96% | K15: =IFERROR("percentile in tier: "&TEXT(_xlfn.XLOOKUP("debt_per_capita",Peers!$C$6:$C$18,Peers!$F$6:$F$18),"0%"),"") -> percentile in tier: 27%
B17: What the numbers say
B18: {=Selected&", "&LatestYear&": revenue "&MONEY(YV(tbl_Year[total_revenue],BaseYear))&", expenses "&MONEY(YV(tbl_Year[total_expenses],BaseYear))&", a surplus of "&MONEY(YV(tbl_Year[annual_surplus],BaseYear))&" ("&TEXT(YV(tbl_Year[surplus_ratio],BaseYear),"0.0%")&" of revenue); "&TEXT(YV(tbl_Year[own_source_share],BaseYear),"0%")&" of revenue is its own."} -> Fernie, 2024: revenue $24.5M, expenses $22.0M, a surplus of $2.5M (10.1% of revenue); 89% of revenue is its own.
B19: =debt_sentence -> Fernie uses 15% of its legal servicing limit. The $4.8M a year still available would service about $62.9M of new borrowing at 4.3% over 20 years.
B20: =asset_sentence -> Capital additions cover 96% of the renewal need: $348K a year short of keeping pace with wear.
B21: =plan_sentence -> Closing 100% of the renewal gap by year 5, borrowing 30% of the new capital, needs municipal tax increases averaging 3.7% a year. The representative house's municipal tax goes from $2,842 to $3,406, and debt servicing reaches 14% of the legal limit.
B22: {="A representative "&TEXT(YV(tbl_Year[house_value],LatestYear),"$#,##0")&" house pays "&TEXT(YV(tbl_Year[house_total_charges],LatestYear),"$#,##0")&" in property taxes and charges, against a tier median of "&TEXT(_xlfn.XLOOKUP(SelId,tbl_Peers[municipality_id],tbl_Peers[house_total_charges_tier_median]),"$#,##0")&"; "&TEXT(YV(tbl_Year[house_municipal_share],LatestYear),"0%")&" of it is the municipal share."} -> A representative $907,932 house pays $6,264 in property taxes and charges, against a tier median of $4,507; 45% of it is the municipal share.
B42: Independent analysis of the Province of British Columbia's Local Government Statistics (Open Government Licence – British Columbia). Not affiliated with or endorsed by any municipality or the Province. Built in Excel by Kush Patel.

Sheet Profile
B1: ="Six-year profile: "&Selected -> Six-year profile: Fernie
B2: Every line is the Province's schedule for that year, looked up for the selected municipality. A dash means the Province published nothing for that year.
B5: Line | C5: Column | D5: 2019 | E5: 2020 | F5: 2021 | G5: 2022 | H5: 2023 | I5: 2024 | J5: Change, first to last
B6: Revenue
B7: Taxation and grants in lieu | C7: taxation | D7: {=YV(_xlfn.XLOOKUP($C7,tbl_Year[#Headers],tbl_Year[]),D$5)} -> 11679941 | E7: {=YV(_xlfn.XLOOKUP($C7,tbl_Year[#Headers],tbl_Year[]),E$5)} -> 11847977 | F7: {=YV(_xlfn.XLOOKUP($C7,tbl_Year[#Headers],tbl_Year[]),F$5)} -> 12126305 | G7: {=YV(_xlfn.XLOOKUP($C7,tbl_Year[#Headers],tbl_Year[]),G$5)} -> 13369957 | H7: {=YV(_xlfn.XLOOKUP($C7,tbl_Year[#Headers],tbl_Year[]),H$5)} -> 14194174 | I7: {=YV(_xlfn.XLOOKUP($C7,tbl_Year[#Headers],tbl_Year[]),I$5)} -> 15074622 | J7: =IFERROR(I7/D7-1,"") -> 0.29064196
B8: Sale of services | C8: sale_of_services | D8: {=YV(_xlfn.XLOOKUP($C8,tbl_Year[#Headers],tbl_Year[]),D$5)} -> 4630558 | E8: {=YV(_xlfn.XLOOKUP($C8,tbl_Year[#Headers],tbl_Year[]),E$5)} -> 4796932 | F8: {=YV(_xlfn.XLOOKUP($C8,tbl_Year[#Headers],tbl_Year[]),F$5)} -> 5212081 | G8: {=YV(_xlfn.XLOOKUP($C8,tbl_Year[#Headers],tbl_Year[]),G$5)} -> 4985343 | H8: {=YV(_xlfn.XLOOKUP($C8,tbl_Year[#Headers],tbl_Year[]),H$5)} -> 5465696 | I8: {=YV(_xlfn.XLOOKUP($C8,tbl_Year[#Headers],tbl_Year[]),I$5)} -> 5910458 | J8: =IFERROR(I8/D8-1,"") -> 0.27640297
B9: Government transfers | C9: government_transfers | D9: {=YV(_xlfn.XLOOKUP($C9,tbl_Year[#Headers],tbl_Year[]),D$5)} -> 3063142 | E9: {=YV(_xlfn.XLOOKUP($C9,tbl_Year[#Headers],tbl_Year[]),E$5)} -> 3861857 | F9: {=YV(_xlfn.XLOOKUP($C9,tbl_Year[#Headers],tbl_Year[]),F$5)} -> 2132053 | G9: {=YV(_xlfn.XLOOKUP($C9,tbl_Year[#Headers],tbl_Year[]),G$5)} -> 9031310 | H9: {=YV(_xlfn.XLOOKUP($C9,tbl_Year[#Headers],tbl_Year[]),H$5)} -> 6032744 | I9: {=YV(_xlfn.XLOOKUP($C9,tbl_Year[#Headers],tbl_Year[]),I$5)} -> 2633114 | J9: =IFERROR(I9/D9-1,"") -> -0.14038788
B10: Investment income | C10: investment_income | D10: {=YV(_xlfn.XLOOKUP($C10,tbl_Year[#Headers],tbl_Year[]),D$5)} -> 297439 | E10: {=YV(_xlfn.XLOOKUP($C10,tbl_Year[#Headers],tbl_Year[]),E$5)} -> 99811 | F10: {=YV(_xlfn.XLOOKUP($C10,tbl_Year[#Headers],tbl_Year[]),F$5)} -> 116551 | G10: {=YV(_xlfn.XLOOKUP($C10,tbl_Year[#Headers],tbl_Year[]),G$5)} -> 448469 | H10: {=YV(_xlfn.XLOOKUP($C10,tbl_Year[#Headers],tbl_Year[]),H$5)} -> 839539 | I10: {=YV(_xlfn.XLOOKUP($C10,tbl_Year[#Headers],tbl_Year[]),I$5)} -> 897000 | J10: =IFERROR(I10/D10-1,"") -> 2.0157444
B11: Developer contributions | C11: developer_contributions | D11: {=YV(_xlfn.XLOOKUP($C11,tbl_Year[#Headers],tbl_Year[]),D$5)} -> 206600 | E11: {=YV(_xlfn.XLOOKUP($C11,tbl_Year[#Headers],tbl_Year[]),E$5)} -> -144741 | F11: {=YV(_xlfn.XLOOKUP($C11,tbl_Year[#Headers],tbl_Year[]),F$5)} -> 80000 | G11: {=YV(_xlfn.XLOOKUP($C11,tbl_Year[#Headers],tbl_Year[]),G$5)} -> 0 | H11: {=YV(_xlfn.XLOOKUP($C11,tbl_Year[#Headers],tbl_Year[]),H$5)} -> 0 | I11: {=YV(_xlfn.XLOOKUP($C11,tbl_Year[#Headers],tbl_Year[]),I$5)} -> 0 | J11: =IFERROR(I11/D11-1,"") -> -1
B12: Total revenue | C12: total_revenue | D12: {=YV(_xlfn.XLOOKUP($C12,tbl_Year[#Headers],tbl_Year[]),D$5)} -> 19992680 | E12: {=YV(_xlfn.XLOOKUP($C12,tbl_Year[#Headers],tbl_Year[]),E$5)} -> 20461836 | F12: {=YV(_xlfn.XLOOKUP($C12,tbl_Year[#Headers],tbl_Year[]),F$5)} -> 19666990 | G12: {=YV(_xlfn.XLOOKUP($C12,tbl_Year[#Headers],tbl_Year[]),G$5)} -> 27835079 | H12: {=YV(_xlfn.XLOOKUP($C12,tbl_Year[#Headers],tbl_Year[]),H$5)} -> 26532153 | I12: {=YV(_xlfn.XLOOKUP($C12,tbl_Year[#Headers],tbl_Year[]),I$5)} -> 24515194 | J12: =IFERROR(I12/D12-1,"") -> 0.22620849
B13: Expenses
B14: Cash expenses | C14: cash_expenses | D14: {=YV(_xlfn.XLOOKUP($C14,tbl_Year[#Headers],tbl_Year[]),D$5)} -> 13684373 | E14: {=YV(_xlfn.XLOOKUP($C14,tbl_Year[#Headers],tbl_Year[]),E$5)} -> 12791061 | F14: {=YV(_xlfn.XLOOKUP($C14,tbl_Year[#Headers],tbl_Year[]),F$5)} -> 13650961 | G14: {=YV(_xlfn.XLOOKUP($C14,tbl_Year[#Headers],tbl_Year[]),G$5)} -> 16539897 | H14: {=YV(_xlfn.XLOOKUP($C14,tbl_Year[#Headers],tbl_Year[]),H$5)} -> 17129644 | I14: {=YV(_xlfn.XLOOKUP($C14,tbl_Year[#Headers],tbl_Year[]),I$5)} -> 17764865 | J14: =IFERROR(I14/D14-1,"") -> 0.29818626
B15: Amortization | C15: amortization | D15: {=YV(_xlfn.XLOOKUP($C15,tbl_Year[#Headers],tbl_Year[]),D$5)} -> 3256048 | E15: {=YV(_xlfn.XLOOKUP($C15,tbl_Year[#Headers],tbl_Year[]),E$5)} -> 3471292 | F15: {=YV(_xlfn.XLOOKUP($C15,tbl_Year[#Headers],tbl_Year[]),F$5)} -> 3476738 | G15: {=YV(_xlfn.XLOOKUP($C15,tbl_Year[#Headers],tbl_Year[]),G$5)} -> 3644440 | H15: {=YV(_xlfn.XLOOKUP($C15,tbl_Year[#Headers],tbl_Year[]),H$5)} -> 4162923 | I15: {=YV(_xlfn.XLOOKUP($C15,tbl_Year[#Headers],tbl_Year[]),I$5)} -> 4268555 | J15: =IFERROR(I15/D15-1,"") -> 0.31096194
B16: Total expenses | C16: total_expenses | D16: {=YV(_xlfn.XLOOKUP($C16,tbl_Year[#Headers],tbl_Year[]),D$5)} -> 16940421 | E16: {=YV(_xlfn.XLOOKUP($C16,tbl_Year[#Headers],tbl_Year[]),E$5)} -> 16262353 | F16: {=YV(_xlfn.XLOOKUP($C16,tbl_Year[#Headers],tbl_Year[]),F$5)} -> 17127699 | G16: {=YV(_xlfn.XLOOKUP($C16,tbl_Year[#Headers],tbl_Year[]),G$5)} -> 20184337 | H16: {=YV(_xlfn.XLOOKUP($C16,tbl_Year[#Headers],tbl_Year[]),H$5)} -> 21292567 | I16: {=YV(_xlfn.XLOOKUP($C16,tbl_Year[#Headers],tbl_Year[]),I$5)} -> 22033420 | J16: =IFERROR(I16/D16-1,"") -> 0.30064182
B17: Annual surplus | C17: annual_surplus | D17: {=YV(_xlfn.XLOOKUP($C17,tbl_Year[#Headers],tbl_Year[]),D$5)} -> 3052259 | E17: {=YV(_xlfn.XLOOKUP($C17,tbl_Year[#Headers],tbl_Year[]),E$5)} -> 4199483 | F17: {=YV(_xlfn.XLOOKUP($C17,tbl_Year[#Headers],tbl_Year[]),F$5)} -> 2539291 | G17: {=YV(_xlfn.XLOOKUP($C17,tbl_Year[#Headers],tbl_Year[]),G$5)} -> 7650742 | H17: {=YV(_xlfn.XLOOKUP($C17,tbl_Year[#Headers],tbl_Year[]),H$5)} -> 5239586 | I17: {=YV(_xlfn.XLOOKUP($C17,tbl_Year[#Headers],tbl_Year[]),I$5)} -> 2481774 | J17: =IFERROR(I17/D17-1,"") -> -0.18690583
B18: Financial position
B19: Financial assets | C19: total_financial_assets | D19: {=YV(_xlfn.XLOOKUP($C19,tbl_Year[#Headers],tbl_Year[]),D$5)} -> 10154160 | E19: {=YV(_xlfn.XLOOKUP($C19,tbl_Year[#Headers],tbl_Year[]),E$5)} -> 16113500 | F19: {=YV(_xlfn.XLOOKUP($C19,tbl_Year[#Headers],tbl_Year[]),F$5)} -> 20138489 | G19: {=YV(_xlfn.XLOOKUP($C19,tbl_Year[#Headers],tbl_Year[]),G$5)} -> 21079484 | H19: {=YV(_xlfn.XLOOKUP($C19,tbl_Year[#Headers],tbl_Year[]),H$5)} -> 28409540 | I19: {=YV(_xlfn.XLOOKUP($C19,tbl_Year[#Headers],tbl_Year[]),I$5)} -> 24816939 | J19: =IFERROR(I19/D19-1,"") -> 1.4440169
B20: Liabilities | C20: total_liabilities | D20: {=YV(_xlfn.XLOOKUP($C20,tbl_Year[#Headers],tbl_Year[]),D$5)} -> 11339782 | E20: {=YV(_xlfn.XLOOKUP($C20,tbl_Year[#Headers],tbl_Year[]),E$5)} -> 13813880 | F20: {=YV(_xlfn.XLOOKUP($C20,tbl_Year[#Headers],tbl_Year[]),F$5)} -> 14367534 | G20: {=YV(_xlfn.XLOOKUP($C20,tbl_Year[#Headers],tbl_Year[]),G$5)} -> 15411959 | H20: {=YV(_xlfn.XLOOKUP($C20,tbl_Year[#Headers],tbl_Year[]),H$5)} -> 21941329 | I20: {=YV(_xlfn.XLOOKUP($C20,tbl_Year[#Headers],tbl_Year[]),I$5)} -> 16880536 | J20: =IFERROR(I20/D20-1,"") -> 0.48861204
B21: Net financial assets | C21: net_financial_assets | D21: {=YV(_xlfn.XLOOKUP($C21,tbl_Year[#Headers],tbl_Year[]),D$5)} -> -1185622 | E21: {=YV(_xlfn.XLOOKUP($C21,tbl_Year[#Headers],tbl_Year[]),E$5)} -> 2299620 | F21: {=YV(_xlfn.XLOOKUP($C21,tbl_Year[#Headers],tbl_Year[]),F$5)} -> 5770955 | G21: {=YV(_xlfn.XLOOKUP($C21,tbl_Year[#Headers],tbl_Year[]),G$5)} -> 5667525 | H21: {=YV(_xlfn.XLOOKUP($C21,tbl_Year[#Headers],tbl_Year[]),H$5)} -> 6468211 | I21: {=YV(_xlfn.XLOOKUP($C21,tbl_Year[#Headers],tbl_Year[]),I$5)} -> 7936403 | J21: =IFERROR(I21/D21-1,"") -> -7.6938729
B22: Reserves and operating/capital surplus | C22: financial_reserves | D22: {=YV(_xlfn.XLOOKUP($C22,tbl_Year[#Headers],tbl_Year[]),D$5)} -> 1525280 | E22: {=YV(_xlfn.XLOOKUP($C22,tbl_Year[#Headers],tbl_Year[]),E$5)} -> 7852727 | F22: {=YV(_xlfn.XLOOKUP($C22,tbl_Year[#Headers],tbl_Year[]),F$5)} -> 11185508 | G22: {=YV(_xlfn.XLOOKUP($C22,tbl_Year[#Headers],tbl_Year[]),G$5)} -> 9738321 | H22: {=YV(_xlfn.XLOOKUP($C22,tbl_Year[#Headers],tbl_Year[]),H$5)} -> 10859555 | I22: {=YV(_xlfn.XLOOKUP($C22,tbl_Year[#Headers],tbl_Year[]),I$5)} -> 13420201 | J22: =IFERROR(I22/D22-1,"") -> 7.7985163
B23: Long-term debt | C23: long_term_debt | D23: {=YV(_xlfn.XLOOKUP($C23,tbl_Year[#Headers],tbl_Year[]),D$5)} -> 2686653 | E23: {=YV(_xlfn.XLOOKUP($C23,tbl_Year[#Headers],tbl_Year[]),E$5)} -> 5553107 | F23: {=YV(_xlfn.XLOOKUP($C23,tbl_Year[#Headers],tbl_Year[]),F$5)} -> 4814554 | G23: {=YV(_xlfn.XLOOKUP($C23,tbl_Year[#Headers],tbl_Year[]),G$5)} -> 4070796 | H23: {=YV(_xlfn.XLOOKUP($C23,tbl_Year[#Headers],tbl_Year[]),H$5)} -> 3321143 | I23: {=YV(_xlfn.XLOOKUP($C23,tbl_Year[#Headers],tbl_Year[]),I$5)} -> 2566095 | J23: =IFERROR(I23/D23-1,"") -> -0.044872933
B24: Debt capacity
B25: Revenue for the liability limit | C25: revenue_for_limit | D25: {=YV(_xlfn.XLOOKUP($C25,tbl_Year[#Headers],tbl_Year[]),D$5)} -> 16741329 | E25: {=YV(_xlfn.XLOOKUP($C25,tbl_Year[#Headers],tbl_Year[]),E$5)} -> 16801219 | F25: {=YV(_xlfn.XLOOKUP($C25,tbl_Year[#Headers],tbl_Year[]),F$5)} -> 17578972 | G25: {=YV(_xlfn.XLOOKUP($C25,tbl_Year[#Headers],tbl_Year[]),G$5)} -> 18739359 | H25: {=YV(_xlfn.XLOOKUP($C25,tbl_Year[#Headers],tbl_Year[]),H$5)} -> 20973687 | I25: {=YV(_xlfn.XLOOKUP($C25,tbl_Year[#Headers],tbl_Year[]),I$5)} -> 22410266 | J25: =IFERROR(I25/D25-1,"") -> 0.33861929
B26: Liability servicing limit (25%) | C26: liability_servicing_limit | D26: {=YV(_xlfn.XLOOKUP($C26,tbl_Year[#Headers],tbl_Year[]),D$5)} -> 4185332 | E26: {=YV(_xlfn.XLOOKUP($C26,tbl_Year[#Headers],tbl_Year[]),E$5)} -> 4200305 | F26: {=YV(_xlfn.XLOOKUP($C26,tbl_Year[#Headers],tbl_Year[]),F$5)} -> 4394743 | G26: {=YV(_xlfn.XLOOKUP($C26,tbl_Year[#Headers],tbl_Year[]),G$5)} -> 4684840 | H26: {=YV(_xlfn.XLOOKUP($C26,tbl_Year[#Headers],tbl_Year[]),H$5)} -> 5243422 | I26: {=YV(_xlfn.XLOOKUP($C26,tbl_Year[#Headers],tbl_Year[]),I$5)} -> 5602567 | J26: =IFERROR(I26/D26-1,"") -> 0.33861949
B27: Actual debt servicing | C27: debt_servicing_cost | D27: {=YV(_xlfn.XLOOKUP($C27,tbl_Year[#Headers],tbl_Year[]),D$5)} -> 243269 | E27: {=YV(_xlfn.XLOOKUP($C27,tbl_Year[#Headers],tbl_Year[]),E$5)} -> 200042 | F27: {=YV(_xlfn.XLOOKUP($C27,tbl_Year[#Headers],tbl_Year[]),F$5)} -> 824208 | G27: {=YV(_xlfn.XLOOKUP($C27,tbl_Year[#Headers],tbl_Year[]),G$5)} -> 851682 | H27: {=YV(_xlfn.XLOOKUP($C27,tbl_Year[#Headers],tbl_Year[]),H$5)} -> 885711 | I27: {=YV(_xlfn.XLOOKUP($C27,tbl_Year[#Headers],tbl_Year[]),I$5)} -> 851154 | J27: =IFERROR(I27/D27-1,"") -> 2.4988182
B28: Share of the limit used | C28: limit_used | D28: {=YV(_xlfn.XLOOKUP($C28,tbl_Year[#Headers],tbl_Year[]),D$5)} -> 0.058124182 | E28: {=YV(_xlfn.XLOOKUP($C28,tbl_Year[#Headers],tbl_Year[]),E$5)} -> 0.047625589 | F28: {=YV(_xlfn.XLOOKUP($C28,tbl_Year[#Headers],tbl_Year[]),F$5)} -> 0.18754407 | G28: {=YV(_xlfn.XLOOKUP($C28,tbl_Year[#Headers],tbl_Year[]),G$5)} -> 0.18179532 | H28: {=YV(_xlfn.XLOOKUP($C28,tbl_Year[#Headers],tbl_Year[]),H$5)} -> 0.1689185 | I28: {=YV(_xlfn.XLOOKUP($C28,tbl_Year[#Headers],tbl_Year[]),I$5)} -> 0.15192215 | J28: =IFERROR(I28-D28,"") -> 0.093797963
B29: Assets and tax
B30: Capital additions | C30: tca_additions | D30: {=YV(_xlfn.XLOOKUP($C30,tbl_Year[#Headers],tbl_Year[]),D$5)} -> 13873447 | E30: {=YV(_xlfn.XLOOKUP($C30,tbl_Year[#Headers],tbl_Year[]),E$5)} -> 4209779 | F30: {=YV(_xlfn.XLOOKUP($C30,tbl_Year[#Headers],tbl_Year[]),F$5)} -> 2544694 | G30: {=YV(_xlfn.XLOOKUP($C30,tbl_Year[#Headers],tbl_Year[]),G$5)} -> 10814019 | H30: {=YV(_xlfn.XLOOKUP($C30,tbl_Year[#Headers],tbl_Year[]),H$5)} -> 7572883 | I30: {=YV(_xlfn.XLOOKUP($C30,tbl_Year[#Headers],tbl_Year[]),I$5)} -> 5282136 | J30: =IFERROR(I30/D30-1,"") -> -0.6192629
B31: Replacement value | C31: replacement_value | D31: {=YV(_xlfn.XLOOKUP($C31,tbl_Year[#Headers],tbl_Year[]),D$5)} -> 287234599 | E31: {=YV(_xlfn.XLOOKUP($C31,tbl_Year[#Headers],tbl_Year[]),E$5)} -> 296225505 | F31: {=YV(_xlfn.XLOOKUP($C31,tbl_Year[#Headers],tbl_Year[]),F$5)} -> 299497019 | G31: {=YV(_xlfn.XLOOKUP($C31,tbl_Year[#Headers],tbl_Year[]),G$5)} -> 313485667 | H31: {=YV(_xlfn.XLOOKUP($C31,tbl_Year[#Headers],tbl_Year[]),H$5)} -> 322621947 | I31: {=YV(_xlfn.XLOOKUP($C31,tbl_Year[#Headers],tbl_Year[]),I$5)} -> 365516873 | J31: =IFERROR(I31/D31-1,"") -> 0.27253776
B32: Municipal property tax | C32: municipal_property_tax | D32: {=YV(_xlfn.XLOOKUP($C32,tbl_Year[#Headers],tbl_Year[]),D$5)} -> 10743925 | E32: {=YV(_xlfn.XLOOKUP($C32,tbl_Year[#Headers],tbl_Year[]),E$5)} -> 10997472 | F32: {=YV(_xlfn.XLOOKUP($C32,tbl_Year[#Headers],tbl_Year[]),F$5)} -> 11502422 | G32: {=YV(_xlfn.XLOOKUP($C32,tbl_Year[#Headers],tbl_Year[]),G$5)} -> 12425297 | H32: {=YV(_xlfn.XLOOKUP($C32,tbl_Year[#Headers],tbl_Year[]),H$5)} -> 13139811 | I32: {=YV(_xlfn.XLOOKUP($C32,tbl_Year[#Headers],tbl_Year[]),I$5)} -> 13957961 | J32: =IFERROR(I32/D32-1,"") -> 0.29914912
B33: Representative house value | C33: house_value | D33: {=YV(_xlfn.XLOOKUP($C33,tbl_Year[#Headers],tbl_Year[]),D$5)} -> 527027 | E33: {=YV(_xlfn.XLOOKUP($C33,tbl_Year[#Headers],tbl_Year[]),E$5)} -> 569308 | F33: {=YV(_xlfn.XLOOKUP($C33,tbl_Year[#Headers],tbl_Year[]),F$5)} -> 619538 | G33: {=YV(_xlfn.XLOOKUP($C33,tbl_Year[#Headers],tbl_Year[]),G$5)} -> 736170 | H33: {=YV(_xlfn.XLOOKUP($C33,tbl_Year[#Headers],tbl_Year[]),H$5)} -> 876753 | I33: {=YV(_xlfn.XLOOKUP($C33,tbl_Year[#Headers],tbl_Year[]),I$5)} -> 907932 | J33: =IFERROR(I33/D33-1,"") -> 0.72274286
B34: Taxes and charges, representative house | C34: house_total_charges | D34: {=YV(_xlfn.XLOOKUP($C34,tbl_Year[#Headers],tbl_Year[]),D$5)} -> 4761.0779 | E34: {=YV(_xlfn.XLOOKUP($C34,tbl_Year[#Headers],tbl_Year[]),E$5)} -> 4954 | F34: {=YV(_xlfn.XLOOKUP($C34,tbl_Year[#Headers],tbl_Year[]),F$5)} -> 5203 | G34: {=YV(_xlfn.XLOOKUP($C34,tbl_Year[#Headers],tbl_Year[]),G$5)} -> 5491 | H34: {=YV(_xlfn.XLOOKUP($C34,tbl_Year[#Headers],tbl_Year[]),H$5)} -> 5937 | I34: {=YV(_xlfn.XLOOKUP($C34,tbl_Year[#Headers],tbl_Year[]),I$5)} -> 6264 | J34: =IFERROR(I34/D34-1,"") -> 0.31566845
B35: Population (BC Stats estimate) | C35: population | D35: {=YV(_xlfn.XLOOKUP($C35,tbl_Year[#Headers],tbl_Year[]),D$5)} -> 5744 | E35: {=YV(_xlfn.XLOOKUP($C35,tbl_Year[#Headers],tbl_Year[]),E$5)} -> 5668 | F35: {=YV(_xlfn.XLOOKUP($C35,tbl_Year[#Headers],tbl_Year[]),F$5)} -> 5739 | G35: {=YV(_xlfn.XLOOKUP($C35,tbl_Year[#Headers],tbl_Year[]),G$5)} -> 5869.5 | H35: {=YV(_xlfn.XLOOKUP($C35,tbl_Year[#Headers],tbl_Year[]),H$5)} -> 6000 | I35: {=YV(_xlfn.XLOOKUP($C35,tbl_Year[#Headers],tbl_Year[]),I$5)} -> 6000 | J35: =IFERROR(I35/D35-1,"") -> 0.044568245

Sheet Peers
B1: ="Peers: "&Selected&" against "&SelTierLabel -> Peers: Fernie against 2,500 to 9,999 residents
B2: Every active municipality in the same population tier, from the latest year. Percentiles count only municipalities that report the metric; 100% is the highest value, which is the best only where the direction says so.
B4: The selected municipality on every metric
B5: Metric | C5: Key | D5: Value | E5: Tier median | F5: Tier percentile | G5: Province percentile | H5: Direction | I5: Reading
B6: Revenue per resident | C6: revenue_per_capita | D6: {=_xlfn.XLOOKUP(SelId,tbl_Peers[municipality_id],_xlfn.XLOOKUP("revenue_per_capita",tbl_Peers[#Headers],tbl_Peers[]),"")} -> 4085.8657 | E6: {=_xlfn.XLOOKUP(SelId,tbl_Peers[municipality_id],_xlfn.XLOOKUP("revenue_per_capita_tier_median",tbl_Peers[#Headers],tbl_Peers[]),"")} -> 3327.878 | F6: {=_xlfn.LET(_xlpm.c,_xlfn.XLOOKUP("revenue_per_capita",tbl_Peers[#Headers],tbl_Peers[]),_xlpm.v,D6,_xlpm.t,tbl_Peers[size_tier]=SelTier,IF(_xlpm.v="","",SUM(_xlpm.t*(_xlpm.c<>"")*(_xlpm.c<_xlpm.v))/(SUM(_xlpm.t*(_xlpm.c<>""))-1)))} -> 0.66666667 | G6: {=_xlfn.LET(_xlpm.c,_xlfn.XLOOKUP("revenue_per_capita",tbl_Peers[#Headers],tbl_Peers[]),_xlpm.v,D6,IF(_xlpm.v="","",SUM((_xlpm.c<>"")*(_xlpm.c<_xlpm.v))/(SUM(--(_xlpm.c<>""))-1)))} -> 0.62580645 | H6: context | I6: =IF(D6="","not reported",IF(H6="context",IF(D6>E6,"above","below")&" the tier median",IF((D6>E6)=(H6="higher"),"better","weaker")&" than the tier median")) -> above the tier median
B7: Spending per resident | C7: expenses_per_capita | D7: {=_xlfn.XLOOKUP(SelId,tbl_Peers[municipality_id],_xlfn.XLOOKUP("expenses_per_capita",tbl_Peers[#Headers],tbl_Peers[]),"")} -> 3672.2367 | E7: {=_xlfn.XLOOKUP(SelId,tbl_Peers[municipality_id],_xlfn.XLOOKUP("expenses_per_capita_tier_median",tbl_Peers[#Headers],tbl_Peers[]),"")} -> 2783.6651 | F7: {=_xlfn.LET(_xlpm.c,_xlfn.XLOOKUP("expenses_per_capita",tbl_Peers[#Headers],tbl_Peers[]),_xlpm.v,D7,_xlpm.t,tbl_Peers[size_tier]=SelTier,IF(_xlpm.v="","",SUM(_xlpm.t*(_xlpm.c<>"")*(_xlpm.c<_xlpm.v))/(SUM(_xlpm.t*(_xlpm.c<>""))-1)))} -> 0.88888889 | G7: {=_xlfn.LET(_xlpm.c,_xlfn.XLOOKUP("expenses_per_capita",tbl_Peers[#Headers],tbl_Peers[]),_xlpm.v,D7,IF(_xlpm.v="","",SUM((_xlpm.c<>"")*(_xlpm.c<_xlpm.v))/(SUM(--(_xlpm.c<>""))-1)))} -> 0.77419355 | H7: context | I7: =IF(D7="","not reported",IF(H7="context",IF(D7>E7,"above","below")&" the tier median",IF((D7>E7)=(H7="higher"),"better","weaker")&" than the tier median")) -> above the tier median
B8: Municipal property tax per resident | C8: municipal_tax_per_capita | D8: {=_xlfn.XLOOKUP(SelId,tbl_Peers[municipality_id],_xlfn.XLOOKUP("municipal_tax_per_capita",tbl_Peers[#Headers],tbl_Peers[]),"")} -> 2326.3268 | E8: {=_xlfn.XLOOKUP(SelId,tbl_Peers[municipality_id],_xlfn.XLOOKUP("municipal_tax_per_capita_tier_median",tbl_Peers[#Headers],tbl_Peers[]),"")} -> 1246.362 | F8: {=_xlfn.LET(_xlpm.c,_xlfn.XLOOKUP("municipal_tax_per_capita",tbl_Peers[#Headers],tbl_Peers[]),_xlpm.v,D8,_xlpm.t,tbl_Peers[size_tier]=SelTier,IF(_xlpm.v="","",SUM(_xlpm.t*(_xlpm.c<>"")*(_xlpm.c<_xlpm.v))/(SUM(_xlpm.t*(_xlpm.c<>""))-1)))} -> 0.95555556 | G8: {=_xlfn.LET(_xlpm.c,_xlfn.XLOOKUP("municipal_tax_per_capita",tbl_Peers[#Headers],tbl_Peers[]),_xlpm.v,D8,IF(_xlpm.v="","",SUM((_xlpm.c<>"")*(_xlpm.c<_xlpm.v))/(SUM(--(_xlpm.c<>""))-1)))} -> 0.92405063 | H8: context | I8: =IF(D8="","not reported",IF(H8="context",IF(D8>E8,"above","below")&" the tier median",IF((D8>E8)=(H8="higher"),"better","weaker")&" than the tier median")) -> above the tier median
B9: Own-source share of revenue | C9: own_source_share | D9: {=_xlfn.XLOOKUP(SelId,tbl_Peers[municipality_id],_xlfn.XLOOKUP("own_source_share",tbl_Peers[#Headers],tbl_Peers[]),"")} -> 0.89259257 | E9: {=_xlfn.XLOOKUP(SelId,tbl_Peers[municipality_id],_xlfn.XLOOKUP("own_source_share_tier_median",tbl_Peers[#Headers],tbl_Peers[]),"")} -> 0.77321957 | F9: {=_xlfn.LET(_xlpm.c,_xlfn.XLOOKUP("own_source_share",tbl_Peers[#Headers],tbl_Peers[]),_xlpm.v,D9,_xlpm.t,tbl_Peers[size_tier]=SelTier,IF(_xlpm.v="","",SUM(_xlpm.t*(_xlpm.c<>"")*(_xlpm.c<_xlpm.v))/(SUM(_xlpm.t*(_xlpm.c<>""))-1)))} -> 0.97777778 | G9: {=_xlfn.LET(_xlpm.c,_xlfn.XLOOKUP("own_source_share",tbl_Peers[#Headers],tbl_Peers[]),_xlpm.v,D9,IF(_xlpm.v="","",SUM((_xlpm.c<>"")*(_xlpm.c<_xlpm.v))/(SUM(--(_xlpm.c<>""))-1)))} -> 0.85806452 | H9: higher | I9: =IF(D9="","not reported",IF(H9="context",IF(D9>E9,"above","below")&" the tier median",IF((D9>E9)=(H9="higher"),"better","weaker")&" than the tier median")) -> better than the tier median
B10: Annual surplus as a share of revenue | C10: surplus_ratio | D10: {=_xlfn.XLOOKUP(SelId,tbl_Peers[municipality_id],_xlfn.XLOOKUP("surplus_ratio",tbl_Peers[#Headers],tbl_Peers[]),"")} -> 0.10123412 | E10: {=_xlfn.XLOOKUP(SelId,tbl_Peers[municipality_id],_xlfn.XLOOKUP("surplus_ratio_tier_median",tbl_Peers[#Headers],tbl_Peers[]),"")} -> 0.21663632 | F10: {=_xlfn.LET(_xlpm.c,_xlfn.XLOOKUP("surplus_ratio",tbl_Peers[#Headers],tbl_Peers[]),_xlpm.v,D10,_xlpm.t,tbl_Peers[size_tier]=SelTier,IF(_xlpm.v="","",SUM(_xlpm.t*(_xlpm.c<>"")*(_xlpm.c<_xlpm.v))/(SUM(_xlpm.t*(_xlpm.c<>""))-1)))} -> 0.17777778 | G10: {=_xlfn.LET(_xlpm.c,_xlfn.XLOOKUP("surplus_ratio",tbl_Peers[#Headers],tbl_Peers[]),_xlpm.v,D10,IF(_xlpm.v="","",SUM((_xlpm.c<>"")*(_xlpm.c<_xlpm.v))/(SUM(--(_xlpm.c<>""))-1)))} -> 0.17419355 | H10: higher | I10: =IF(D10="","not reported",IF(H10="context",IF(D10>E10,"above","below")&" the tier median",IF((D10>E10)=(H10="higher"),"better","weaker")&" than the tier median")) -> weaker than the tier median
B11: Share of the legal debt-servicing limit used | C11: limit_used | D11: {=_xlfn.XLOOKUP(SelId,tbl_Peers[municipality_id],_xlfn.XLOOKUP("limit_used",tbl_Peers[#Headers],tbl_Peers[]),"")} -> 0.15192215 | E11: {=_xlfn.XLOOKUP(SelId,tbl_Peers[municipality_id],_xlfn.XLOOKUP("limit_used_tier_median",tbl_Peers[#Headers],tbl_Peers[]),"")} -> 0.15427955 | F11: {=_xlfn.LET(_xlpm.c,_xlfn.XLOOKUP("limit_used",tbl_Peers[#Headers],tbl_Peers[]),_xlpm.v,D11,_xlpm.t,tbl_Peers[size_tier]=SelTier,IF(_xlpm.v="","",SUM(_xlpm.t*(_xlpm.c<>"")*(_xlpm.c<_xlpm.v))/(SUM(_xlpm.t*(_xlpm.c<>""))-1)))} -> 0.48888889 | G11: {=_xlfn.LET(_xlpm.c,_xlfn.XLOOKUP("limit_used",tbl_Peers[#Headers],tbl_Peers[]),_xlpm.v,D11,IF(_xlpm.v="","",SUM((_xlpm.c<>"")*(_xlpm.c<_xlpm.v))/(SUM(--(_xlpm.c<>""))-1)))} -> 0.62580645 | H11: lower | I11: =IF(D11="","not reported",IF(H11="context",IF(D11>E11,"above","below")&" the tier median",IF((D11>E11)=(H11="higher"),"better","weaker")&" than the tier median")) -> better than the tier median
B12: Long-term debt per resident | C12: debt_per_capita | D12: {=_xlfn.XLOOKUP(SelId,tbl_Peers[municipality_id],_xlfn.XLOOKUP("debt_per_capita",tbl_Peers[#Headers],tbl_Peers[]),"")} -> 427.6825 | E12: {=_xlfn.XLOOKUP(SelId,tbl_Peers[municipality_id],_xlfn.XLOOKUP("debt_per_capita_tier_median",tbl_Peers[#Headers],tbl_Peers[]),"")} -> 950.36657 | F12: {=_xlfn.LET(_xlpm.c,_xlfn.XLOOKUP("debt_per_capita",tbl_Peers[#Headers],tbl_Peers[]),_xlpm.v,D12,_xlpm.t,tbl_Peers[size_tier]=SelTier,IF(_xlpm.v="","",SUM(_xlpm.t*(_xlpm.c<>"")*(_xlpm.c<_xlpm.v))/(SUM(_xlpm.t*(_xlpm.c<>""))-1)))} -> 0.26666667 | G12: {=_xlfn.LET(_xlpm.c,_xlfn.XLOOKUP("debt_per_capita",tbl_Peers[#Headers],tbl_Peers[]),_xlpm.v,D12,IF(_xlpm.v="","",SUM((_xlpm.c<>"")*(_xlpm.c<_xlpm.v))/(SUM(--(_xlpm.c<>""))-1)))} -> 0.43870968 | H12: lower | I12: =IF(D12="","not reported",IF(H12="context",IF(D12>E12,"above","below")&" the tier median",IF((D12>E12)=(H12="higher"),"better","weaker")&" than the tier median")) -> better than the tier median
B13: Reserves and surplus per resident | C13: reserves_per_capita | D13: {=_xlfn.XLOOKUP(SelId,tbl_Peers[municipality_id],_xlfn.XLOOKUP("reserves_per_capita",tbl_Peers[#Headers],tbl_Peers[]),"")} -> 2236.7002 | E13: {=_xlfn.XLOOKUP(SelId,tbl_Peers[municipality_id],_xlfn.XLOOKUP("reserves_per_capita_tier_median",tbl_Peers[#Headers],tbl_Peers[]),"")} -> 4022.5271 | F13: {=_xlfn.LET(_xlpm.c,_xlfn.XLOOKUP("reserves_per_capita",tbl_Peers[#Headers],tbl_Peers[]),_xlpm.v,D13,_xlpm.t,tbl_Peers[size_tier]=SelTier,IF(_xlpm.v="","",SUM(_xlpm.t*(_xlpm.c<>"")*(_xlpm.c<_xlpm.v))/(SUM(_xlpm.t*(_xlpm.c<>""))-1)))} -> 0.088888889 | G13: {=_xlfn.LET(_xlpm.c,_xlfn.XLOOKUP("reserves_per_capita",tbl_Peers[#Headers],tbl_Peers[]),_xlpm.v,D13,IF(_xlpm.v="","",SUM((_xlpm.c<>"")*(_xlpm.c<_xlpm.v))/(SUM(--(_xlpm.c<>""))-1)))} -> 0.18064516 | H13: higher | I13: =IF(D13="","not reported",IF(H13="context",IF(D13>E13,"above","below")&" the tier median",IF((D13>E13)=(H13="higher"),"better","weaker")&" than the tier median")) -> weaker than the tier median
B14: Reserves against a year of cash spending | C14: reserves_to_cash_expenses | D14: {=_xlfn.XLOOKUP(SelId,tbl_Peers[municipality_id],_xlfn.XLOOKUP("reserves_to_cash_expenses",tbl_Peers[#Headers],tbl_Peers[]),"")} -> 0.75543501 | E14: {=_xlfn.XLOOKUP(SelId,tbl_Peers[municipality_id],_xlfn.XLOOKUP("reserves_to_cash_expenses_tier_median",tbl_Peers[#Headers],tbl_Peers[]),"")} -> 1.8328982 | F14: {=_xlfn.LET(_xlpm.c,_xlfn.XLOOKUP("reserves_to_cash_expenses",tbl_Peers[#Headers],tbl_Peers[]),_xlpm.v,D14,_xlpm.t,tbl_Peers[size_tier]=SelTier,IF(_xlpm.v="","",SUM(_xlpm.t*(_xlpm.c<>"")*(_xlpm.c<_xlpm.v))/(SUM(_xlpm.t*(_xlpm.c<>""))-1)))} -> 0.022222222 | G14: {=_xlfn.LET(_xlpm.c,_xlfn.XLOOKUP("reserves_to_cash_expenses",tbl_Peers[#Headers],tbl_Peers[]),_xlpm.v,D14,IF(_xlpm.v="","",SUM((_xlpm.c<>"")*(_xlpm.c<_xlpm.v))/(SUM(--(_xlpm.c<>""))-1)))} -> 0.058064516 | H14: higher | I14: =IF(D14="","not reported",IF(H14="context",IF(D14>E14,"above","below")&" the tier median",IF((D14>E14)=(H14="higher"),"better","weaker")&" than the tier median")) -> weaker than the tier median
B15: Share of asset life used up | C15: asset_consumption_ratio | D15: {=_xlfn.XLOOKUP(SelId,tbl_Peers[municipality_id],_xlfn.XLOOKUP("asset_consumption_ratio",tbl_Peers[#Headers],tbl_Peers[]),"")} -> 0.41173021 | E15: {=_xlfn.XLOOKUP(SelId,tbl_Peers[municipality_id],_xlfn.XLOOKUP("asset_consumption_ratio_tier_median",tbl_Peers[#Headers],tbl_Peers[]),"")} -> 0.42596276 | F15: {=_xlfn.LET(_xlpm.c,_xlfn.XLOOKUP("asset_consumption_ratio",tbl_Peers[#Headers],tbl_Peers[]),_xlpm.v,D15,_xlpm.t,tbl_Peers[size_tier]=SelTier,IF(_xlpm.v="","",SUM(_xlpm.t*(_xlpm.c<>"")*(_xlpm.c<_xlpm.v))/(SUM(_xlpm.t*(_xlpm.c<>""))-1)))} -> 0.4 | G15: {=_xlfn.LET(_xlpm.c,_xlfn.XLOOKUP("asset_consumption_ratio",tbl_Peers[#Headers],tbl_Peers[]),_xlpm.v,D15,IF(_xlpm.v="","",SUM((_xlpm.c<>"")*(_xlpm.c<_xlpm.v))/(SUM(--(_xlpm.c<>""))-1)))} -> 0.38064516 | H15: lower | I15: =IF(D15="","not reported",IF(H15="context",IF(D15>E15,"above","below")&" the tier median",IF((D15>E15)=(H15="higher"),"better","weaker")&" than the tier median")) -> better than the tier median
B16: Capital reinvestment against renewal need | C16: reinvestment_ratio | D16: {=_xlfn.XLOOKUP(SelId,tbl_Peers[municipality_id],_xlfn.XLOOKUP("reinvestment_ratio",tbl_Peers[#Headers],tbl_Peers[]),"")} -> 0.95779831 | E16: {=_xlfn.XLOOKUP(SelId,tbl_Peers[municipality_id],_xlfn.XLOOKUP("reinvestment_ratio_tier_median",tbl_Peers[#Headers],tbl_Peers[]),"")} -> 1.0599919 | F16: {=_xlfn.LET(_xlpm.c,_xlfn.XLOOKUP("reinvestment_ratio",tbl_Peers[#Headers],tbl_Peers[]),_xlpm.v,D16,_xlpm.t,tbl_Peers[size_tier]=SelTier,IF(_xlpm.v="","",SUM(_xlpm.t*(_xlpm.c<>"")*(_xlpm.c<_xlpm.v))/(SUM(_xlpm.t*(_xlpm.c<>""))-1)))} -> 0.43589744 | G16: {=_xlfn.LET(_xlpm.c,_xlfn.XLOOKUP("reinvestment_ratio",tbl_Peers[#Headers],tbl_Peers[]),_xlpm.v,D16,IF(_xlpm.v="","",SUM((_xlpm.c<>"")*(_xlpm.c<_xlpm.v))/(SUM(--(_xlpm.c<>""))-1)))} -> 0.49230769 | H16: higher | I16: =IF(D16="","not reported",IF(H16="context",IF(D16>E16,"above","below")&" the tier median",IF((D16>E16)=(H16="higher"),"better","weaker")&" than the tier median")) -> weaker than the tier median
B17: Taxes and charges on a representative house | C17: house_total_charges | D17: {=_xlfn.XLOOKUP(SelId,tbl_Peers[municipality_id],_xlfn.XLOOKUP("house_total_charges",tbl_Peers[#Headers],tbl_Peers[]),"")} -> 6264 | E17: {=_xlfn.XLOOKUP(SelId,tbl_Peers[municipality_id],_xlfn.XLOOKUP("house_total_charges_tier_median",tbl_Peers[#Headers],tbl_Peers[]),"")} -> 4506.5 | F17: {=_xlfn.LET(_xlpm.c,_xlfn.XLOOKUP("house_total_charges",tbl_Peers[#Headers],tbl_Peers[]),_xlpm.v,D17,_xlpm.t,tbl_Peers[size_tier]=SelTier,IF(_xlpm.v="","",SUM(_xlpm.t*(_xlpm.c<>"")*(_xlpm.c<_xlpm.v))/(SUM(_xlpm.t*(_xlpm.c<>""))-1)))} -> 0.86666667 | G17: {=_xlfn.LET(_xlpm.c,_xlfn.XLOOKUP("house_total_charges",tbl_Peers[#Headers],tbl_Peers[]),_xlpm.v,D17,IF(_xlpm.v="","",SUM((_xlpm.c<>"")*(_xlpm.c<_xlpm.v))/(SUM(--(_xlpm.c<>""))-1)))} -> 0.79746835 | H17: lower | I17: =IF(D17="","not reported",IF(H17="context",IF(D17>E17,"above","below")&" the tier median",IF((D17>E17)=(H17="higher"),"better","weaker")&" than the tier median")) -> weaker than the tier median
B18: Municipal tax per $1,000 of assessment | C18: effective_municipal_rate | D18: {=_xlfn.XLOOKUP(SelId,tbl_Peers[municipality_id],_xlfn.XLOOKUP("effective_municipal_rate",tbl_Peers[#Headers],tbl_Peers[]),"")} -> 4.8324159 | E18: {=_xlfn.XLOOKUP(SelId,tbl_Peers[municipality_id],_xlfn.XLOOKUP("effective_municipal_rate_tier_median",tbl_Peers[#Headers],tbl_Peers[]),"")} -> 4.3304406 | F18: {=_xlfn.LET(_xlpm.c,_xlfn.XLOOKUP("effective_municipal_rate",tbl_Peers[#Headers],tbl_Peers[]),_xlpm.v,D18,_xlpm.t,tbl_Peers[size_tier]=SelTier,IF(_xlpm.v="","",SUM(_xlpm.t*(_xlpm.c<>"")*(_xlpm.c<_xlpm.v))/(SUM(_xlpm.t*(_xlpm.c<>""))-1)))} -> 0.62222222 | G18: {=_xlfn.LET(_xlpm.c,_xlfn.XLOOKUP("effective_municipal_rate",tbl_Peers[#Headers],tbl_Peers[]),_xlpm.v,D18,IF(_xlpm.v="","",SUM((_xlpm.c<>"")*(_xlpm.c<_xlpm.v))/(SUM(--(_xlpm.c<>""))-1)))} -> 0.63291139 | H18: lower | I18: =IF(D18="","not reported",IF(H18="context",IF(D18>E18,"above","below")&" the tier median",IF((D18>E18)=(H18="higher"),"better","weaker")&" than the tier median")) -> weaker than the tier median
B21: The tier, ranked
B22: Rank the tier by | D22: Share of the legal debt-servicing limit used | G22: =_xlfn.XLOOKUP(D22,B6:B18,C6:C18) -> limit_used
B23: Municipality | C23: Population | D23: Value | E23: Regional district
B24: {=_xlfn.LET(_xlpm.c,_xlfn.XLOOKUP(G22,tbl_Peers[#Headers],tbl_Peers[]),_xlpm.keep,(tbl_Peers[size_tier]=SelTier)*(_xlpm.c<>""),_xlfn.SORTBY(_xlfn._xlws.FILTER(_xlfn.HSTACK(tbl_Peers[display_name],tbl_Peers[population],_xlpm.c,tbl_Peers[regional_district]&""),_xlpm.keep),_xlfn._xlws.FILTER(_xlpm.c,_xlpm.keep),-1))} -> Golden | C24: 4455 | D24: 0.87420592 | E24: COL
B25: Peachland | C25: 6382 | D25: 0.33175721 | E25: COK
B26: Gibsons | C26: 5098 | D26: 0.29353887 | E26: SUN
B27: Invermere | C27: 3910 | D27: 0.28976738 | E27: EKO
B28: Trail | C28: 8480 | D28: 0.28348561 | E28: KOO
B29: Oliver | C29: 5824 | D29: 0.27823678 | E29: OKS
B30: Revelstoke | C30: 8617 | D30: 0.26897539 | E30: COL
B31: Cumberland | C31: 4901 | D31: 0.26443686 | E31: COM
B32: Bowen Island | C32: 4181 | D32: 0.26111081 | E32: MVRD
B33: Merritt | C33: 7809 | D33: 0.25012126 | E33: TNR
B34: Ladysmith | C34: 9690 | D34: 0.24631014 | E34: COW
B35: Princeton | C35: 3333 | D35: 0.23400777 | E35: OKS
B36: Elkford | C36: 2805 | D36: 0.23079681 | E36: EKO
... B38: Rossland | C38: 4390 | D38: 0.22244766 | E38: KOO
B39: Northern Rockies | C39: 4400 | D39: 0.192659
B40: Pemberton | C40: 3678 | D40: 0.18407837 | E40: SQL
B41: Tofino | C41: 2653 | D41: 0.18188387 | E41: ALB
B42: Sicamous | C42: 3005 | D42: 0.17717121 | E42: COL
B43: Osoyoos | C43: 5730 | D43: 0.16173193 | E43: OKS
B44: Vanderhoof | C44: 4839 | D44: 0.16071929 | E44: BUL
B45: Port McNeill | C45: 2591 | D45: 0.15673478 | E45: MW
B46: Port Hardy | C46: 4552 | D46: 0.15663695 | E46: MW
B47: Fernie | C47: 6000 | D47: 0.15192215 | E47: EKO
B48: Castlegar | C48: 9042 | D48: 0.14530838 | E48: CKO
B49: Armstrong | C49: 5899 | D49: 0.14107284 | E49: NOK
B50: Chase | C50: 2639 | D50: 0.1386845 | E50: TNR
B51: Sparwood | C51: 4265 | D51: 0.1330574 | E51: EKO
... B69: Metchosin | C69: 5271 | D69: 0 | E69: CAP

Sheet Assets
B1: ="Infrastructure: "&Selected&", "&LatestYear -> Infrastructure: Fernie, 2024
B2: Schedule 503: what the municipality owns, what it would cost to replace, and whether capital spending keeps up with wear. The renewal need is re-derived, because the Province's own field is not usable as published (see Province).
B4: Assets by category, latest year
B5: Category | C5: Historical cost | D5: Accumulated amortization | E5: Net book value | F5: Additions | G5: Replacement value | H5: Life used up | I5: Asset management plan | J5: Replacement value share
B6: {=_xlfn.LET(_xlpm.k,(tbl_Assets[municipality_id]=SelId)*(tbl_Assets[year]=LatestYear),_xlpm.d,_xlfn._xlws.FILTER(_xlfn.HSTACK(tbl_Assets[asset_category],tbl_Assets[historical_cost],tbl_Assets[accumulated_amortization],tbl_Assets[net_book_value],tbl_Assets[additions],tbl_Assets[replacement_value],tbl_Assets[consumption_ratio],SUBSTITUTE(tbl_Assets[amp_status]&"","_"," ")),_xlpm.k,""),_xlfn.SORTBY(_xlpm.d,_xlfn.CHOOSECOLS(_xlpm.d,6),-1))} -> Buildings | C6: 27847711 | D6: 11018999 | E6: 16828712 | F6: 478157 | G6: 94976440 | H6: 0.39568778 | I6: In Progress | J6: {=IFERROR(_xlfn.CHOOSECOLS(_xlfn.ANCHORARRAY(B6),6)/SUM(_xlfn.CHOOSECOLS(_xlfn.ANCHORARRAY(B6),6)),"")} -> 0.25984147
B7: Transportation System | C7: 46235209 | D7: 23998201 | E7: 22237008 | F7: 1692305 | G7: 88140126 | H7: 0.51904602 | I7: In Progress | J7: 0.24113832
B8: Water System | C8: 38989296 | D8: 11183684 | E8: 27805612 | F8: 383797 | G8: 58886174 | H8: 0.28683985 | I8: In Progress | J8: 0.16110385
B9: Sewer System | C9: 28934056 | D9: 12195448 | E9: 16738608 | F9: 103877 | G9: 41426092 | H9: 0.42149113 | I9: In Progress | J9: 0.11333565
B10: Drainage System | C10: 12295932 | D10: 6120208 | E10: 6175724 | F10: 92948 | G10: 30242160 | H10: 0.49774251 | I10: In Progress | J10: 0.082738068
B11: Parks and Recreation | C11: 15035272 | D11: 1922661 | E11: 13112611 | F11: 2548597 | G11: 25456198 | H11: 0.1278767 | I11: In Progress | J11: 0.069644385
B12: Fleet | C12: 14478454 | D12: 9243371 | E12: 5235083 | F12: 1181386 | G12: 15594339 | H12: 0.63842251 | I12: In Progress | J12: 0.042663801
B13: Work In Progress | C13: 6381384 | D13: 0 | E13: 6381384 | F13: -1198931 | G13: 6381384 | H13: 0 | I13: Not applicable | J13: 0.017458521
B14: Land | C14: 4413960 | D14: 0 | E14: 4413960 | F14: 0 | G14: 4413960 | H14: 0 | I14: Not applicable | J14: 0.01207594
B15: Other Engineering Systems | C15: 0 | D15: 0 | E15: 0 | F15: 0 | G15: 0 | H15: 0 | J15: 0
B16: Other Tangible Capital Assets | C16: 0 | D16: 0 | E16: 0 | F16: 0 | G16: 0 | H16: 0 | I16: Not applicable | J16: 0
B20: Renewal: is capital spending keeping up with wear?
B21: Data quality of the replacement values | E21: {=YV(tbl_Year[asset_data_quality],LatestYear)} -> plausible
B22: Replacement value against historical cost | E22: {=YV(tbl_Year[replacement_to_cost],LatestYear)} -> 1.9297649
B23: Amortization this year | E23: {=YV(tbl_Year[amortization],LatestYear)} -> 4268555
B24: Renewal need (amortization at replacement cost) | E24: {=YV(tbl_Year[renewal_need],LatestYear)} -> 8237307.6
B25: Capital additions, three-year average | E25: {=YV(tbl_Year[tca_additions_3yr],LatestYear)} -> 7889679.3
B26: Reinvestment ratio | E26: {=YV(tbl_Year[reinvestment_ratio],LatestYear)} -> 0.95779831
B27: Annual renewal gap | E27: {=YV(tbl_Year[annual_renewal_gap],LatestYear)} -> 347628.26
B28: Share of replacement value under an asset management plan | E28: {=YV(tbl_Year[amp_coverage],LatestYear)} -> 0
B29: Share of asset life used up (depreciable assets) | E29: {=YV(tbl_Year[asset_consumption_ratio],LatestYear)} -> 0.41173021
B31: {=IF(E21<>"plausible","The replacement values do not pass the screen ("&E21&"), so no renewal need is estimated for "&Selected&".",IF(E26<1,"Capital additions cover "&TEXT(E26,"0%")&" of the renewal need: "&MONEY(E27)&" a year short of keeping pace with wear.","Capital additions exceed the renewal need ("&TEXT(E26,"0.00")&"x). They include growth assets, so this is an upper bound on renewal."))} -> Capital additions cover 96% of the renewal need: $348K a year short of keeping pace with wear.

Sheet Plan
B1: ="Five-year financial plan: "&Selected -> Five-year financial plan: Fernie
B2: The plan the Community Charter (s.165) requires, built from the latest statements: costs grow with wages, prices and population; the renewal gap closes on a straight line to the target; new capital is funded from debt, reserves and taxation in the shares below. The output is the tax increase each year needs.
B4: Drivers (change the yellow cells)
B5: Inflation (CPI) | E5: 0.025 | G5: Base year (latest with statements) | J5: =BaseYear -> 2024
B6: Wage and contract growth | E6: 0.035 | G6: Population growth, two-year average | J6: {=IFERROR((YV(tbl_Year[population],BaseYear)/YV(tbl_Year[population],BaseYear-2))^(1/2)-1,0)} -> 0.011055676
B7: Wage-like share of cash costs | E7: 0.55 | G7: Cost growth (wages, prices, population) | J7: =plan_wage_share*plan_wage+(1-plan_wage_share)*plan_cpi+plan_pop_growth -> 0.041555676
B8: Share of the renewal gap closed by year 5 | E8: 1 | G8: Growth in revenue other than taxation | J8: =plan_cpi+plan_pop_growth -> 0.036055676
B9: Share of new capital borrowed | E9: 0.3 | G9: Base capital program (three-year average additions) | J9: {=_xlfn.LET(_xlpm.a,YV(tbl_Year[tca_additions_3yr],BaseYear),IF(_xlpm.a="",N(YV(tbl_Year[tca_additions],BaseYear)),_xlpm.a))} -> 7889679.3
B10: Share of new capital from reserves | E10: 0.2 | G10: Annual renewal gap at the base year | J10: {=N(YV(tbl_Year[annual_renewal_gap],BaseYear))} -> 347628.26
B11: MFA borrowing rate | E11: 0.043
B12: Borrowing term (years) | E12: 20
B14: The plan
D15: Year 0 | E15: Year 1 | F15: Year 2 | G15: Year 3 | H15: Year 4 | I15: Year 5
B16: Year | D16: =BaseYear+COLUMN()-COLUMN($D$16) -> 2024 | E16: =BaseYear+COLUMN()-COLUMN($D$16) -> 2025 | F16: =BaseYear+COLUMN()-COLUMN($D$16) -> 2026 | G16: =BaseYear+COLUMN()-COLUMN($D$16) -> 2027 | H16: =BaseYear+COLUMN()-COLUMN($D$16) -> 2028 | I16: =BaseYear+COLUMN()-COLUMN($D$16) -> 2029
B17: Cash operating expenses | D17: {=YV(tbl_Year[cash_expenses],BaseYear)*(1+plan_cost_growth)^(COLUMN()-COLUMN($D$1))} -> 17764865 | E17: {=YV(tbl_Year[cash_expenses],BaseYear)*(1+plan_cost_growth)^(COLUMN()-COLUMN($D$1))} -> 18503096 | F17: {=YV(tbl_Year[cash_expenses],BaseYear)*(1+plan_cost_growth)^(COLUMN()-COLUMN($D$1))} -> 19272005 | G17: {=YV(tbl_Year[cash_expenses],BaseYear)*(1+plan_cost_growth)^(COLUMN()-COLUMN($D$1))} -> 20072866 | H17: {=YV(tbl_Year[cash_expenses],BaseYear)*(1+plan_cost_growth)^(COLUMN()-COLUMN($D$1))} -> 20907007 | I17: {=YV(tbl_Year[cash_expenses],BaseYear)*(1+plan_cost_growth)^(COLUMN()-COLUMN($D$1))} -> 21775812
B18: Revenue other than taxation | D18: {=(YV(tbl_Year[total_revenue],BaseYear)-YV(tbl_Year[taxation],BaseYear))*(1+plan_rev_growth)^(COLUMN()-COLUMN($D$1))} -> 9440572 | E18: {=(YV(tbl_Year[total_revenue],BaseYear)-YV(tbl_Year[taxation],BaseYear))*(1+plan_rev_growth)^(COLUMN()-COLUMN($D$1))} -> 9780958.2 | F18: {=(YV(tbl_Year[total_revenue],BaseYear)-YV(tbl_Year[taxation],BaseYear))*(1+plan_rev_growth)^(COLUMN()-COLUMN($D$1))} -> 10133617 | G18: {=(YV(tbl_Year[total_revenue],BaseYear)-YV(tbl_Year[taxation],BaseYear))*(1+plan_rev_growth)^(COLUMN()-COLUMN($D$1))} -> 10498992 | H18: {=(YV(tbl_Year[total_revenue],BaseYear)-YV(tbl_Year[taxation],BaseYear))*(1+plan_rev_growth)^(COLUMN()-COLUMN($D$1))} -> 10877540 | I18: {=(YV(tbl_Year[total_revenue],BaseYear)-YV(tbl_Year[taxation],BaseYear))*(1+plan_rev_growth)^(COLUMN()-COLUMN($D$1))} -> 11269737
B19: Capital program | D19: =(plan_base_capital+plan_gap*plan_closure*(COLUMN()-COLUMN($D$1))/5)*(1+plan_cpi)^(COLUMN()-COLUMN($D$1)) -> 7889679.3 | E19: =(plan_base_capital+plan_gap*plan_closure*(COLUMN()-COLUMN($D$1))/5)*(1+plan_cpi)^(COLUMN()-COLUMN($D$1)) -> 8158185.1 | F19: =(plan_base_capital+plan_gap*plan_closure*(COLUMN()-COLUMN($D$1))/5)*(1+plan_cpi)^(COLUMN()-COLUMN($D$1)) -> 8435185.1 | G19: =(plan_base_capital+plan_gap*plan_closure*(COLUMN()-COLUMN($D$1))/5)*(1+plan_cpi)^(COLUMN()-COLUMN($D$1)) -> 8720936.3 | H19: =(plan_base_capital+plan_gap*plan_closure*(COLUMN()-COLUMN($D$1))/5)*(1+plan_cpi)^(COLUMN()-COLUMN($D$1)) -> 9015703 | I19: =(plan_base_capital+plan_gap*plan_closure*(COLUMN()-COLUMN($D$1))/5)*(1+plan_cpi)^(COLUMN()-COLUMN($D$1)) -> 9319757.5
B20: Capital above the base-year program | D20: =D19-plan_base_capital -> 0 | E20: =E19-plan_base_capital -> 268505.78 | F20: =F19-plan_base_capital -> 545505.79 | G20: =G19-plan_base_capital -> 831256.94 | H20: =H19-plan_base_capital -> 1126023.7 | I20: =I19-plan_base_capital -> 1430078.1
B21: New borrowing | D21: =plan_debt*D20 -> 0 | E21: =plan_debt*E20 -> 80551.733 | F21: =plan_debt*F20 -> 163651.74 | G21: =plan_debt*G20 -> 249377.08 | H21: =plan_debt*H20 -> 337807.1 | I21: =plan_debt*I20 -> 429023.44
B22: Servicing on new borrowing | D22: {=SUM(PMT(plan_rate,plan_term,-$D21:D21))} -> 0 | E22: {=SUM(PMT(plan_rate,plan_term,-$D21:E21))} -> 6085.6549 | F22: {=SUM(PMT(plan_rate,plan_term,-$D21:F21))} -> 18449.486 | G22: {=SUM(PMT(plan_rate,plan_term,-$D21:G21))} -> 37289.836 | H22: {=SUM(PMT(plan_rate,plan_term,-$D21:H21))} -> 62811.042 | I22: {=SUM(PMT(plan_rate,plan_term,-$D21:I21))} -> 95223.611
B23: Drawn from reserves | D23: =plan_reserve*D20 -> 0 | E23: =plan_reserve*E20 -> 53701.155 | F23: =plan_reserve*F20 -> 109101.16 | G23: =plan_reserve*G20 -> 166251.39 | H23: =plan_reserve*H20 -> 225204.73 | I23: =plan_reserve*I20 -> 286015.63
B24: Capital funded from taxation | D24: =(1-plan_debt-plan_reserve)*D20 -> 0 | E24: =(1-plan_debt-plan_reserve)*E20 -> 134252.89 | F24: =(1-plan_debt-plan_reserve)*F20 -> 272752.9 | G24: =(1-plan_debt-plan_reserve)*G20 -> 415628.47 | H24: =(1-plan_debt-plan_reserve)*H20 -> 563011.83 | I24: =(1-plan_debt-plan_reserve)*I20 -> 715039.07
B25: Taxation required | D25: {=YV(tbl_Year[taxation],BaseYear)+(D17-$D17)+D22+D24-(D18-$D18)} -> 15074622 | E25: {=YV(tbl_Year[taxation],BaseYear)+(E17-$D17)+E22+E24-(E18-$D18)} -> 15612805 | F25: {=YV(tbl_Year[taxation],BaseYear)+(F17-$D17)+F22+F24-(F18-$D18)} -> 16179919 | G25: {=YV(tbl_Year[taxation],BaseYear)+(G17-$D17)+G22+G24-(G18-$D18)} -> 16777121 | H25: {=YV(tbl_Year[taxation],BaseYear)+(H17-$D17)+H22+H24-(H18-$D18)} -> 17405619 | I25: {=YV(tbl_Year[taxation],BaseYear)+(I17-$D17)+I22+I24-(I18-$D18)} -> 18066667
B26: Increase on the year before | E26: =E25/D25-1 -> 0.035701281 | F26: =F25/E25-1 -> 0.036323609 | G26: =G25/F25-1 -> 0.036910117 | H26: =H25/G25-1 -> 0.037461601 | I26: =I25/H25-1 -> 0.037978975
B27: Reserves and surplus, closing | D27: {=YV(tbl_Year[financial_reserves],BaseYear)-SUM($D23:D23)} -> 13420201 | E27: {=YV(tbl_Year[financial_reserves],BaseYear)-SUM($D23:E23)} -> 13366500 | F27: {=YV(tbl_Year[financial_reserves],BaseYear)-SUM($D23:F23)} -> 13257399 | G27: {=YV(tbl_Year[financial_reserves],BaseYear)-SUM($D23:G23)} -> 13091147 | H27: {=YV(tbl_Year[financial_reserves],BaseYear)-SUM($D23:H23)} -> 12865943 | I27: {=YV(tbl_Year[financial_reserves],BaseYear)-SUM($D23:I23)} -> 12579927
B28: Total debt servicing | D28: {=YV(tbl_Year[debt_servicing_cost],BaseYear)+D22} -> 851154 | E28: {=YV(tbl_Year[debt_servicing_cost],BaseYear)+E22} -> 857239.65 | F28: {=YV(tbl_Year[debt_servicing_cost],BaseYear)+F22} -> 869603.49 | G28: {=YV(tbl_Year[debt_servicing_cost],BaseYear)+G22} -> 888443.84 | H28: {=YV(tbl_Year[debt_servicing_cost],BaseYear)+H22} -> 913965.04 | I28: {=YV(tbl_Year[debt_servicing_cost],BaseYear)+I22} -> 946377.61
B29: Share of the legal limit used | D29: {=D28/(0.25*YV(tbl_Year[revenue_for_limit],BaseYear)*(D25+D18)/($D25+$D18))} -> 0.15192216 | E29: {=E28/(0.25*YV(tbl_Year[revenue_for_limit],BaseYear)*(E25+E18)/($D25+$D18))} -> 0.14771462 | F29: {=F28/(0.25*YV(tbl_Year[revenue_for_limit],BaseYear)*(F25+F18)/($D25+$D18))} -> 0.14460735 | G29: {=G28/(0.25*YV(tbl_Year[revenue_for_limit],BaseYear)*(G25+G18)/($D25+$D18))} -> 0.14252656 | H29: {=H28/(0.25*YV(tbl_Year[revenue_for_limit],BaseYear)*(H25+H18)/($D25+$D18))} -> 0.14140019 | I29: {=I28/(0.25*YV(tbl_Year[revenue_for_limit],BaseYear)*(I25+I18)/($D25+$D18))} -> 0.14115813
B30: Municipal tax on the representative house | D30: {=YV(tbl_Year[house_municipal_tax],BaseYear)*D25/$D25} -> 2842 | E30: {=YV(tbl_Year[house_municipal_tax],BaseYear)*E25/$D25} -> 2943.463 | F30: {=YV(tbl_Year[house_municipal_tax],BaseYear)*F25/$D25} -> 3050.3802 | G30: {=YV(tbl_Year[house_municipal_tax],BaseYear)*G25/$D25} -> 3162.9701 | H30: {=YV(tbl_Year[house_municipal_tax],BaseYear)*H25/$D25} -> 3281.4601 | I30: {=YV(tbl_Year[house_municipal_tax],BaseYear)*I25/$D25} -> 3406.0865
B32: Average tax increase a year, years 1 to 5 | E32: =(I25/D25)^(1/5)-1 -> 0.036874803
B33: ="Closing "&TEXT(plan_closure,"0%")&" of the renewal gap by year 5, borrowing "&TEXT(plan_debt,"0%")&" of the new capital, needs municipal tax increases averaging "&TEXT(E32,"0.0%")&" a year. The representative house's municipal tax goes from "&TEXT(D30,"$#,##0")&" to "&TEXT(I30,"$#,##0")&", and debt servicing reaches "&TEXT(I29,"0%")&" of the legal limit." -> Closing 100% of the renewal gap by year 5, borrowing 30% of the new capital, needs municipal tax increases averaging 3.7% a year. The representative house's municipal tax goes from $2,842 to $3,406, and debt servicing reaches 14% of the legal limit.
B35: What-if data table: average tax increase by gap closure and debt share
B36: Gap closed ↓ Debt share → | C36: =E32 -> 0.036874803 | D36: 0 | E36: 0.15 | F36: 0.3 | G36: 0.45 | H36: 0.6
C37: 0 | D37: 0.037094546 | E37: 0.03570487 | F37: 0.034307695 | G37: 0.03290293 | H37: 0.031490481
C38: 0.25 | D38: 0.037995122 | E38: 0.03647796 | F38: 0.034951863 | G38: 0.033416711 | H38: 0.031872383
C39: 0.5 | D39: 0.038892583 | E39: 0.037248751 | F39: 0.035594431 | G39: 0.033929473 | H39: 0.03225372
C40: 0.75 | D40: 0.039786954 | E40: 0.038017257 | F40: 0.036235408 | G40: 0.034441219 | H40: 0.032634495
C41: 1 | D41: 0.040678258 | E41: 0.038783494 | F41: 0.036874803 | G41: 0.034951955 | H41: 0.033014709

Sheet Tax
B1: ="Property tax by class: "&Selected&", "&LatestYear -> Property tax by class: Fernie, 2024
B2: Schedule 707. BC sets each class's rate as a multiple of the residential rate, so one number, the residential rate, sets them all. The calculator turns a levy change into the rates that raise it.
B4: The classes
B5: Property class | C5: Assessment | D5: Rate per $1,000 | E5: Class multiple | F5: Variable-rate taxes | G5: Flat and other taxes | H5: Municipal taxes | I5: Share of taxes | J5: Assessment × multiple
B6: {=_xlfn.LET(_xlpm.k,(tbl_Tax[municipality_id]=SelId)*(tbl_Tax[year]=LatestYear),_xlpm.d,_xlfn._xlws.FILTER(_xlfn.HSTACK(tbl_Tax[property_class],tbl_Tax[assessment],tbl_Tax[municipal_rate],tbl_Tax[class_multiple],tbl_Tax[variable_rate_taxes],tbl_Tax[flat_and_other_taxes],tbl_Tax[municipal_taxes]),_xlpm.k,""),_xlfn.SORTBY(_xlpm.d,_xlfn.CHOOSECOLS(_xlpm.d,7),-1))} -> Residential | C6: 2643674301 | D6: 3.13073 | E6: 1 | F6: 8276630 | G6: 0 | H6: 8276630 | I6: {=IFERROR(_xlfn.CHOOSECOLS(_xlfn.ANCHORARRAY(B6),7)/SUM(_xlfn.CHOOSECOLS(_xlfn.ANCHORARRAY(B6),7)),"")} -> 0.58805896 | J6: {=IFERROR(_xlfn.CHOOSECOLS(_xlfn.ANCHORARRAY(B6),2)*_xlfn.CHOOSECOLS(_xlfn.ANCHORARRAY(B6),4),"")} -> 2643674301
B7: Major Industry | C7: 0 | D7: 0 | E7: 0 | F7: 0 | G7: 3461569 | H7: 3461569 | I7: 0.24594632 | J7: 0
B8: Business/Other | C8: 238390989 | D8: 8.75733 | E8: 2.7972166 | F8: 2087669 | G8: 0 | H8: 2087669 | I8: 0.14832999 | J8: 6.6683124e+08
B9: Utilities | C9: 3182720 | D9: 33.83754 | E9: 10.808195 | F9: 107695 | G9: 116529 | H9: 224224 | I9: 0.015931234 | J9: 34399458
B10: Light Industry | C10: 1932800 | D10: 10.64449 | E10: 3.4000026 | F10: 20574 | G10: 0 | H10: 20574 | I10: 0.0014617936 | J10: 6571524.9
B11: Recreation | C11: 1207000 | D11: 3.13073 | E11: 1 | F11: 3779 | G11: 0 | H11: 3779 | I11: 0.00026849996 | J11: 1207000
B12: Farm | C12: 14438 | D12: 3.13073 | E12: 1 | F12: 45 | G12: 0 | H12: 45 | I12: 3.1972739e-06 | J12: 14438
B13: Managed Forest | C13: 0 | D13: 0 | E13: 0 | F13: 0 | G13: 0 | H13: 0 | I13: 0 | J13: 0
B14: Supportive Housing | C14: 2 | D14: 3.13073 | E14: 1 | F14: 0 | G14: 0 | H14: 0 | I14: 0 | J14: 2
B18: Levy to rates
B19: Variable-rate levy this year | F19: =SUM(_xlfn.CHOOSECOLS(_xlfn.ANCHORARRAY(B6),5)) -> 10496392
B20: Assessment weighted by class multiples | F20: =SUM(_xlfn.ANCHORARRAY(J6)) -> 3.352698e+09
B21: Residential rate the levy implies (per $1,000) | F21: =tax_variable_levy*1000/tax_weighted_base -> 3.13073
B22: Residential rate the Province publishes | F22: {=_xlfn.XLOOKUP("Residential",_xlfn.CHOOSECOLS(_xlfn.ANCHORARRAY(B6),1),_xlfn.CHOOSECOLS(_xlfn.ANCHORARRAY(B6),3),"")} -> 3.13073
B23: Levy change to test (defaults to plan year 1) | F23: =plan_year1_increase -> 0.035701281
B24: New residential rate | F24: =tax_res_rate_implied*(1+tax_levy_change) -> 3.242501
B25: Representative house value | F25: {=YV(tbl_Year[house_value],LatestYear)} -> 907932
B26: Municipal tax on it now | F26: {=YV(tbl_Year[house_municipal_tax],LatestYear)} -> 2842
B27: Municipal tax on it after the change | F27: =tax_house_now*(1+tax_levy_change) -> 2943.463
B29: ="The levy and the class multiples imply a residential rate of "&TEXT(tax_res_rate_implied,"0.0000")&" per $1,000; the Province publishes "&TEXT(tax_res_rate_published,"0.0000")&". A "&TEXT(tax_levy_change,"+0.0%;-0.0%")&" levy change moves it to "&TEXT(tax_res_rate_new,"0.0000")&", and the representative house's municipal tax from "&TEXT(tax_house_now,"$#,##0")&" to "&TEXT(tax_house_new,"$#,##0")&"." -> The levy and the class multiples imply a residential rate of 3.1307 per $1,000; the Province publishes 3.1307. A +3.6% levy change moves it to 3.2425, and the representative house's municipal tax from $2,842 to $2,943.

Sheet Debt
B1: ="Borrowing room: "&Selected&", "&BaseYear -> Borrowing room: Fernie, 2024
B2: The Community Charter caps annual liability servicing at 25% of revenue (B.C. Reg. 254/2004). Schedule 602.1 reports the limit and what is used; the calculator turns the room left into a borrowing amount.
B4: The limit
B5: Revenue for the purposes of the limit | F5: {=YV(tbl_Year[revenue_for_limit],BaseYear)} -> 22410266
B6: Liability servicing limit (25%) | F6: {=YV(tbl_Year[liability_servicing_limit],BaseYear)} -> 5602567
B7: Actual debt servicing | F7: {=YV(tbl_Year[debt_servicing_cost],BaseYear)} -> 851154
B8: Servicing capacity available | F8: {=YV(tbl_Year[servicing_capacity],BaseYear)} -> 4751413
B9: Share of the limit used | F9: =debt_servicing/debt_limit -> 0.15192215
B10: Long-term debt outstanding | F10: {=YV(tbl_Year[long_term_debt],BaseYear)} -> 2566095
B13: Borrowing calculator
B14: Borrowing rate | F14: =plan_rate -> 0.043
B15: Term (years) | F15: =plan_term -> 20
B16: Amount to borrow | F16: 10000000
B17: Annual servicing on it | F17: =PMT(debt_rate,debt_term,-debt_amount) -> 755496.45
B18: Capacity left after it | F18: =debt_capacity-debt_payment -> 3995916.5
B19: Most the remaining capacity could service | F19: =PV(debt_rate,debt_term,-debt_capacity) -> 62891268
B21: {=Selected&" uses "&TEXT(debt_limit_used,"0%")&" of its legal servicing limit. The "&MONEY(debt_capacity)&" a year still available would service about "&MONEY(debt_max_borrowing)&" of new borrowing at "&TEXT(debt_rate,"0.0%")&" over "&debt_term&" years."} -> Fernie uses 15% of its legal servicing limit. The $4.8M a year still available would service about $62.9M of new borrowing at 4.3% over 20 years.
B23: Six years of servicing against the limit
B24: Year | C24: Limit | D24: Servicing | E24: Share used
B25: 2019 | C25: {=YV(tbl_Year[liability_servicing_limit],B25)} -> 4185332 | D25: {=YV(tbl_Year[debt_servicing_cost],B25)} -> 243269 | E25: =IFERROR(D25/C25,"") -> 0.058124182
B26: 2020 | C26: {=YV(tbl_Year[liability_servicing_limit],B26)} -> 4200305 | D26: {=YV(tbl_Year[debt_servicing_cost],B26)} -> 200042 | E26: =IFERROR(D26/C26,"") -> 0.047625589
B27: 2021 | C27: {=YV(tbl_Year[liability_servicing_limit],B27)} -> 4394743 | D27: {=YV(tbl_Year[debt_servicing_cost],B27)} -> 824208 | E27: =IFERROR(D27/C27,"") -> 0.18754407
B28: 2022 | C28: {=YV(tbl_Year[liability_servicing_limit],B28)} -> 4684840 | D28: {=YV(tbl_Year[debt_servicing_cost],B28)} -> 851682 | E28: =IFERROR(D28/C28,"") -> 0.18179532
B29: 2023 | C29: {=YV(tbl_Year[liability_servicing_limit],B29)} -> 5243422 | D29: {=YV(tbl_Year[debt_servicing_cost],B29)} -> 885711 | E29: =IFERROR(D29/C29,"") -> 0.1689185
B30: 2024 | C30: {=YV(tbl_Year[liability_servicing_limit],B30)} -> 5602567 | D30: {=YV(tbl_Year[debt_servicing_cost],B30)} -> 851154 | E30: =IFERROR(D30/C30,"") -> 0.15192215

Sheet Province
B1: The province: 161 municipalities, and how far their asset data can be trusted
B2: Totals and medians by year from mart_province_trend, and the data-quality screen behind every renewal figure in this workbook.
B4: By year
B5: Year | C5: Municipalities | D5: Revenue | E5: Expenses | F5: Long-term debt | G5: Replacement value | H5: Median limit used | I5: Median house charges | J5: Replacement values plausible
B6: 2019 | C6: =_xlfn.XLOOKUP($B6,tbl_Province[year],tbl_Province[municipalities]) -> 162 | D6: =_xlfn.XLOOKUP($B6,tbl_Province[year],tbl_Province[total_revenue]) -> 11501121733 | E6: =_xlfn.XLOOKUP($B6,tbl_Province[year],tbl_Province[total_expenses]) -> 9147924119 | F6: =_xlfn.XLOOKUP($B6,tbl_Province[year],tbl_Province[long_term_debt]) -> 2979907063 | G6: =_xlfn.XLOOKUP($B6,tbl_Province[year],tbl_Province[replacement_value]) -> 96842812863 | H6: =_xlfn.XLOOKUP($B6,tbl_Province[year],tbl_Province[median_limit_used]) -> 0.11933071 | I6: =_xlfn.XLOOKUP($B6,tbl_Province[year],tbl_Province[median_house_total_charges]) -> 3556.5776 | J6: =_xlfn.XLOOKUP($B6,tbl_Province[year],tbl_Province[assets_plausible]) -> 48
B7: 2020 | C7: =_xlfn.XLOOKUP($B7,tbl_Province[year],tbl_Province[municipalities]) -> 162 | D7: =_xlfn.XLOOKUP($B7,tbl_Province[year],tbl_Province[total_revenue]) -> 11508431251 | E7: =_xlfn.XLOOKUP($B7,tbl_Province[year],tbl_Province[total_expenses]) -> 9024330913 | F7: =_xlfn.XLOOKUP($B7,tbl_Province[year],tbl_Province[long_term_debt]) -> 2981834492 | G7: =_xlfn.XLOOKUP($B7,tbl_Province[year],tbl_Province[replacement_value]) -> 98413911315 | H7: =_xlfn.XLOOKUP($B7,tbl_Province[year],tbl_Province[median_limit_used]) -> 0.11521169 | I7: =_xlfn.XLOOKUP($B7,tbl_Province[year],tbl_Province[median_house_total_charges]) -> 3758.5 | J7: =_xlfn.XLOOKUP($B7,tbl_Province[year],tbl_Province[assets_plausible]) -> 45
B8: 2021 | C8: =_xlfn.XLOOKUP($B8,tbl_Province[year],tbl_Province[municipalities]) -> 161 | D8: =_xlfn.XLOOKUP($B8,tbl_Province[year],tbl_Province[total_revenue]) -> 12760483180 | E8: =_xlfn.XLOOKUP($B8,tbl_Province[year],tbl_Province[total_expenses]) -> 9657811658 | F8: =_xlfn.XLOOKUP($B8,tbl_Province[year],tbl_Province[long_term_debt]) -> 3142615939 | G8: =_xlfn.XLOOKUP($B8,tbl_Province[year],tbl_Province[replacement_value]) -> 109223236933 | H8: =_xlfn.XLOOKUP($B8,tbl_Province[year],tbl_Province[median_limit_used]) -> 0.10818139 | I8: =_xlfn.XLOOKUP($B8,tbl_Province[year],tbl_Province[median_house_total_charges]) -> 3952 | J8: =_xlfn.XLOOKUP($B8,tbl_Province[year],tbl_Province[assets_plausible]) -> 46
B9: 2022 | C9: =_xlfn.XLOOKUP($B9,tbl_Province[year],tbl_Province[municipalities]) -> 161 | D9: =_xlfn.XLOOKUP($B9,tbl_Province[year],tbl_Province[total_revenue]) -> 13889751318 | E9: =_xlfn.XLOOKUP($B9,tbl_Province[year],tbl_Province[total_expenses]) -> 10451027567 | F9: =_xlfn.XLOOKUP($B9,tbl_Province[year],tbl_Province[long_term_debt]) -> 3353546795 | G9: =_xlfn.XLOOKUP($B9,tbl_Province[year],tbl_Province[replacement_value]) -> 109933419760 | H9: =_xlfn.XLOOKUP($B9,tbl_Province[year],tbl_Province[median_limit_used]) -> 0.10114621 | I9: =_xlfn.XLOOKUP($B9,tbl_Province[year],tbl_Province[median_house_total_charges]) -> 4180 | J9: =_xlfn.XLOOKUP($B9,tbl_Province[year],tbl_Province[assets_plausible]) -> 48
B10: 2023 | C10: =_xlfn.XLOOKUP($B10,tbl_Province[year],tbl_Province[municipalities]) -> 161 | D10: =_xlfn.XLOOKUP($B10,tbl_Province[year],tbl_Province[total_revenue]) -> 15452743100 | E10: =_xlfn.XLOOKUP($B10,tbl_Province[year],tbl_Province[total_expenses]) -> 11395628426 | F10: =_xlfn.XLOOKUP($B10,tbl_Province[year],tbl_Province[long_term_debt]) -> 3308433831 | G10: =_xlfn.XLOOKUP($B10,tbl_Province[year],tbl_Province[replacement_value]) -> 137401973100 | H10: =_xlfn.XLOOKUP($B10,tbl_Province[year],tbl_Province[median_limit_used]) -> 0.10120027 | I10: =_xlfn.XLOOKUP($B10,tbl_Province[year],tbl_Province[median_house_total_charges]) -> 4458 | J10: =_xlfn.XLOOKUP($B10,tbl_Province[year],tbl_Province[assets_plausible]) -> 55
B11: 2024 | C11: =_xlfn.XLOOKUP($B11,tbl_Province[year],tbl_Province[municipalities]) -> 161 | D11: =_xlfn.XLOOKUP($B11,tbl_Province[year],tbl_Province[total_revenue]) -> 16286389311 | E11: =_xlfn.XLOOKUP($B11,tbl_Province[year],tbl_Province[total_expenses]) -> 12313297283 | F11: =_xlfn.XLOOKUP($B11,tbl_Province[year],tbl_Province[long_term_debt]) -> 3557684743 | G11: =_xlfn.XLOOKUP($B11,tbl_Province[year],tbl_Province[replacement_value]) -> 191113796372 | H11: =_xlfn.XLOOKUP($B11,tbl_Province[year],tbl_Province[median_limit_used]) -> 0.11108429 | I11: =_xlfn.XLOOKUP($B11,tbl_Province[year],tbl_Province[median_house_total_charges]) -> 4660 | J11: =_xlfn.XLOOKUP($B11,tbl_Province[year],tbl_Province[assets_plausible]) -> 115
B14: Latest year: the renewal picture
B15: Municipalities whose replacement values pass the screen | H15: =_xlfn.XLOOKUP(LatestYear,tbl_Province[year],tbl_Province[screened_for_renewal]) -> 131
B16: …of which reinvest less than their renewal need | H16: =_xlfn.XLOOKUP(LatestYear,tbl_Province[year],tbl_Province[below_renewal_need]) -> 68
B17: Their combined reinvestment ratio | H17: =_xlfn.XLOOKUP(LatestYear,tbl_Province[year],tbl_Province[reinvestment_ratio]) -> 1.0723129
B18: Municipalities reporting no replacement value | H18: =_xlfn.XLOOKUP(LatestYear,tbl_Province[year],tbl_Province[assets_not_reported]) -> 13
B19: Municipalities with every asset class under a management plan | H19: =_xlfn.XLOOKUP(LatestYear,tbl_Province[year],tbl_Province[fully_covered_by_amp]) -> 34
B20: Municipality-years with no statements published (2019-2024) | H20: =ROWS(tbl_Missing[]) -> 9
B21: Vancouver's reported renewal need, as a share of its replacement value | H21: =_xlfn.XLOOKUP("vancouver-c:"&LatestYear,tbl_Year[municipality_year],tbl_Year[reported_need_rate]) -> 0.41000475
B23: ="In "&LatestYear&", "&prov_screened&" municipalities report replacement values that pass the screen; "&prov_below&" of them invested less over three years than their assets wore out. The field the Province labels annual replacement need is not usable as published: Vancouver's is "&TEXT(prov_vancouver_rate,"0%")&" of its replacement value a year." -> In 2024, 131 municipalities report replacement values that pass the screen; 68 of them invested less over three years than their assets wore out. The field the Province labels annual replacement need is not usable as published: Vancouver's is 41% of its replacement value a year.

Sheet Checks
B1: Checks: the model proves its own numbers
B2: =IF(COUNTIF(G5:G21,"PASS")=17,"All 17 checks pass",COUNTIF(G5:G21,"FAIL")&" of 17 checks FAIL") -> All 17 checks pass
B4: # | C4: Check | D4: Expected | E4: Actual | F4: Tolerance | G4: Status
B5: 1 | C5: Municipality-year rows loaded = dbt gold | D5: 968 | E5: =ROWS(tbl_Year[]) -> 968 | F5: 0 | G5: =IF(ABS(E5-D5)<=F5,"PASS","FAIL") -> PASS
B6: 2 | C6: Asset rows loaded = dbt gold | D6: 10648 | E6: =ROWS(tbl_Assets[]) -> 10648 | F6: 0 | G6: =IF(ABS(E6-D6)<=F6,"PASS","FAIL") -> PASS
B7: 3 | C7: Tax-class rows loaded = dbt gold | D7: 8712 | E7: =ROWS(tbl_Tax[]) -> 8712 | F7: 0 | G7: =IF(ABS(E7-D7)<=F7,"PASS","FAIL") -> PASS
B8: 4 | C8: Peer rows = active municipalities | D8: =COUNTIF(tbl_Dim[active],TRUE) -> 161 | E8: =ROWS(tbl_Peers[]) -> 161 | F8: 0 | G8: =IF(ABS(E8-D8)<=F8,"PASS","FAIL") -> PASS
B9: 5 | C9: Every active municipality is in the Dashboard list | D9: =COUNTIF(tbl_Dim[active],TRUE) -> 161 | E9: =ROWS(ActiveList) -> 161 | F9: 0 | G9: =IF(ABS(E9-D9)<=F9,"PASS","FAIL") -> PASS
B10: 6 | C10: Selection: financial assets less liabilities = net financial assets, every year | D10: 0 | E10: {=SUMPRODUCT(ABS(N(+YV(tbl_Year[total_financial_assets],{2019,2020,2021,2022,2023,2024}))-N(+YV(tbl_Year[total_liabilities],{2019,2020,2021,2022,2023,2024}))-N(+YV(tbl_Year[net_financial_assets],{2019,2020,2021,2022,2023,2024}))))} -> 0 | F10: 12 | G10: =IF(ABS(E10-D10)<=F10,"PASS","FAIL") -> PASS
B11: 7 | C11: Selection: revenue less expenses = annual surplus, every year | D11: 0 | E11: {=SUMPRODUCT(ABS(N(+YV(tbl_Year[total_revenue],{2019,2020,2021,2022,2023,2024}))-N(+YV(tbl_Year[total_expenses],{2019,2020,2021,2022,2023,2024}))-N(+YV(tbl_Year[annual_surplus],{2019,2020,2021,2022,2023,2024}))))} -> 0 | F11: 12 | G11: =IF(ABS(E11-D11)<=F11,"PASS","FAIL") -> PASS
B12: 8 | C12: Selection: the liability limit is 25% of revenue for the limit | D12: =0.25*debt_revenue_for_limit -> 5602566.5 | E12: =debt_limit -> 5602567 | F12: 1 | G12: =IF(ABS(E12-D12)<=F12,"PASS","FAIL") -> PASS
B13: 9 | C13: Levy and class multiples reproduce the published residential rate | D13: =tax_res_rate_published -> 3.13073 | E13: =tax_res_rate_implied -> 3.13073 | F13: 0.0001 | G13: =IF(ABS(E13-D13)<=F13,"PASS","FAIL") -> PASS
B14: 10 | C14: Plan year 0 taxation = the base year's statements | D14: {=YV(tbl_Year[taxation],BaseYear)} -> 15074622 | E14: =INDEX(plan_table,10,1) -> 15074622 | F14: 0.01 | G14: =IF(ABS(E14-D14)<=F14,"PASS","FAIL") -> PASS
B15: 11 | C15: Plan: taxation grows only by the cost, capital and revenue changes | D15: 0 | E15: =ABS(INDEX(plan_table,10,6)-INDEX(plan_table,10,1)-(INDEX(plan_table,2,6)-INDEX(plan_table,2,1))-INDEX(plan_table,7,6)-INDEX(plan_table,9,6)+(INDEX(plan_table,3,6)-INDEX(plan_table,3,1))) -> 9.3132257e-10 | F15: 0.01 | G15: =IF(ABS(E15-D15)<=F15,"PASS","FAIL") -> PASS
B16: 12 | C16: Data table at the live drivers = the live plan | D16: =plan_avg_increase -> 0.036874803 | E16: =INDEX(plan_grid,MATCH(plan_closure,Plan!$C$37:$C$41,0),MATCH(plan_debt,Plan!$D$36:$H$36,0)) -> 0.036874803 | F16: 1e-12 | G16: =IF(ABS(E16-D16)<=F16,"PASS","FAIL") -> PASS
B17: 13 | C17: Peer tier percentiles computed here = the pipeline's, all metrics | D17: 0 | E17: {=SUM(_xlfn.MAP(Peers!C6:C18,Peers!F6:F18,_xlfn.LAMBDA(_xlpm.k,_xlpm.f,ABS(N(_xlpm.f)-N(_xlfn.XLOOKUP(SelId,tbl_Peers[municipality_id],_xlfn.XLOOKUP(_xlpm.k&"_tier_pct",tbl_Peers[#Headers],tbl_Peers[])))))))} -> 0 | F17: 1e-09 | G17: =IF(ABS(E17-D17)<=F17,"PASS","FAIL") -> PASS
B18: 14 | C18: Asset categories' replacement value = the municipality-year total | D18: {=N(YV(tbl_Year[replacement_value],LatestYear))} -> 365516873 | E18: =SUMIFS(tbl_Assets[replacement_value],tbl_Assets[municipality_id],SelId,tbl_Assets[year],LatestYear) -> 365516873 | F18: 2 | G18: =IF(ABS(E18-D18)<=F18,"PASS","FAIL") -> PASS
B19: 15 | C19: Power Query tiers cover every peer | D19: =ROWS(tbl_Peers[]) -> 161 | E19: =SUM(tbl_Tiers[municipalities]) -> 161 | F19: 0 | G19: =IF(ABS(E19-D19)<=F19,"PASS","FAIL") -> PASS
B20: 16 | C20: Power Query categories cover the province's replacement value | D20: =SUMIFS(tbl_Assets[replacement_value],tbl_Assets[year],LatestYear) -> 191113796372 | E20: =SUM(tbl_Categories[replacement_value]) -> 191113796372 | F20: 1 | G20: =IF(ABS(E20-D20)<=F20,"PASS","FAIL") -> PASS
B21: 17 | C21: Documented missing statements = municipality-years without revenue | D21: =ROWS(tbl_Missing[]) -> 9 | E21: =COUNTIFS(tbl_Year[total_revenue],"") -> 9 | F21: 0 | G21: =IF(ABS(E21-D21)<=F21,"PASS","FAIL") -> PASS

Sheet Assumptions
B1: Assumptions and lists
B2: The selector, the names every sheet reads, and the list the Dashboard's dropdown offers. Plan drivers live on the Plan sheet, next to the data table that varies them.
B4: The selected municipality
B5: Municipality id | E5: =_xlfn.XLOOKUP(Selected,tbl_Dim[display_name],tbl_Dim[municipality_id]) -> fernie-c
B6: Type | E6: =_xlfn.XLOOKUP(SelId,tbl_Dim[municipality_id],tbl_Dim[type_name]) -> City
B7: Regional district | E7: =_xlfn.XLOOKUP(SelId,tbl_Dim[municipality_id],tbl_Dim[regional_district]) -> EKO
B8: Peer tier | E8: =_xlfn.XLOOKUP(SelId,tbl_Dim[municipality_id],tbl_Dim[size_tier]) -> 2: 2,500 to 9,999
B9: Peer tier, as shown | E9: =MID(SelTier,4,99)&" residents" -> 2,500 to 9,999 residents
B10: Municipalities in the tier | E10: =COUNTIF(tbl_Peers[size_tier],SelTier) -> 47
B11: Latest year published | E11: =MAX(tbl_Year[year]) -> 2024
B12: Latest year with statements for the selection | E12: =_xlfn.MAXIFS(tbl_Year[year],tbl_Year[municipality_id],SelId,tbl_Year[total_revenue],"<>") -> 2024
B15: Active municipalities (the Dashboard's list)
B16: {=_xlfn._xlws.SORT(_xlfn._xlws.FILTER(tbl_Dim[display_name],tbl_Dim[active]=TRUE))} -> 100 Mile House
B17: Abbotsford
B18: Alert Bay
B19: Anmore
B20: Armstrong
B21: Ashcroft
B22: Barriere
B23: Belcarra
B24: Bowen Island
B25: Burnaby
B26: Burns Lake
B27: Cache Creek
B28: Campbell River
... B176: Zeballos

Sheet PQ_Categories
B1: The province's assets by category, latest year (Power Query)
B2: Output of a Power Query query (Data > Queries & Connections) over the gold tables.
B4: asset_category | C4: municipalities | D4: historical_cost | E4: accumulated_amortization | F4: additions | G4: replacement_value | H4: replacement_under_plan | I4: share_under_plan
B5: Transportation System | C5: 142 | D5: 24416364753 | E5: 10479619816 | F5: 904174008 | G5: 52712505288 | H5: 15933245087 | I5: 0.30226689
B6: Sewer System | C6: 141 | D6: 9199695058 | E6: 3288816742 | F6: 330647754 | G6: 28226605636 | H6: 17981387097 | I6: 0.63703682
B7: Buildings | C7: 148 | D7: 12244523376 | E7: 4908761813 | F7: 818070277 | G7: 27809392162 | H7: 10354779666 | I7: 0.37234829
B8: Water System | C8: 137 | D8: 8972522524 | E8: 2965432086 | F8: 289316424 | G8: 25154476734 | H8: 14026637626 | I8: 0.55761993
B9: Drainage System | C9: 106 | D9: 6992161862 | E9: 2469216707 | F9: 195350093 | G9: 20344184181 | H9: 10761259795 | I9: 0.52896001
B10: Land | C10: 155 | D10: 17614100782 | F10: 965327404 | G10: 17614100782
B11: Parks and Recreation | C11: 113 | D11: 3001023607 | E11: 1471653398 | F11: 174327733 | G11: 7980742139 | H11: 3533176939 | I11: 0.44271283
B12: Fleet | C12: 146 | D12: 3129118191 | E12: 1848777585 | F12: 311009029 | G12: 3534387202 | H12: 1660580766 | I12: 0.46983555
B13: Work In Progress | C13: 133 | D13: 3103290401 | F13: 843987657 | G13: 3103290401
B14: Other Tangible Capital Assets | C14: 83 | D14: 2402746493 | E14: 1423394764 | F14: 196053346 | G14: 2645878274
B15: Other Engineering Systems | C15: 44 | D15: 1309859387 | E15: 516033120 | F15: 74050737 | G15: 1988233573 | H15: 762680949 | I15: 0.38359726

Sheet PQ_Tiers
B1: The peer tiers and their medians (Power Query)
B2: Output of a Power Query query (Data > Queries & Connections) over the gold tables.
B4: size_tier | C4: municipalities | D4: median_population | E4: median_revenue_per_capita | F4: median_limit_used | G4: median_reinvestment_ratio | H4: median_house_total_charges
B5: 1: under 2,500 | C5: 54 | D5: 1028.5 | E5: 5271.4077 | F5: 0.065970871 | G5: 0.83632374 | H5: 3318
B6: 2: 2,500 to 9,999 | C6: 47 | D6: 4552 | E6: 3327.878 | F6: 0.15427955 | G6: 1.0599919 | H6: 4506.5
B7: 3: 10,000 to 49,999 | C7: 39 | D7: 19703 | E7: 2840.5936 | F7: 0.11883209 | G7: 1.0106315 | H7: 5439
B8: 4: 50,000 to 149,999 | C8: 14 | D8: 99894 | E8: 2808.7202 | F8: 0.11213997 | G8: 0.99321575 | H8: 6472.5
B9: 5: 150,000 and over | C9: 7 | D9: 229781 | E9: 3528.9331 | F9: 0.075532022 | G9: 1.3761059 | H9: 7327

Sheet Data_Municipal
B1: dbt gold: fct_municipal_year, one row per municipality and year
B2: Loaded unchanged from data/gold/ (written by dbt) and dbt/seeds/. Formulas and Power Query read these tables by name.
B4: municipality_id | C4: year | D4: municipality_year | E4: population | F4: population_published | G4: population_repaired | H4: total_revenue | I4: taxation | J4: sale_of_services | K4: government_transfers | L4: investment_income | M4: developer_contributions | N4: own_source_revenue | O4: total_expenses | P4: amortization | Q4: cash_expenses | R4: general_government | S4: protective_services | T4: transportation | U4: parks_recreation | V4: water_services | W4: sewer_services | X4: annual_surplus | Y4: capital_acquisitions | Z4: cash_and_investments | AA4: total_financial_assets | AB4: total_liabilities | AC4: net_financial_assets | AD4: accumulated_surplus | AE4: operating_capital_surplus | AF4: statutory_reserves | AG4: financial_reserves | AH4: long_term_debt | AI4: debt_issued | AJ4: debt_repaid | AK4: interest_expense | AL4: revenue_for_limit | AM4: liability_servicing_limit | AN4: debt_servicing_cost | AO4: servicing_capacity | AP4: assessed_value | AQ4: residential_assessment | AR4: municipal_property_tax | AS4: total_taxes_and_charges | AT4: house_value | AU4: house_municipal_tax | AV4: house_total_charges | AW4: tca_cost | AX4: tca_net_book_value | AY4: tca_additions | AZ4: tca_additions_3yr | BA4: replacement_value | BB4: annual_replacement_need | BC4: amp_coverage | BD4: own_source_share | BE4: surplus_ratio | BF4: limit_used | BG4: debt_service_ratio | BH4: reserves_to_cash_expenses | BI4: asset_consumption_ratio | BJ4: replacement_to_cost | BK4: reported_need_rate | BL4: asset_data_quality | BM4: renewal_need | BN4: reinvestment_ratio | BO4: annual_renewal_gap | BP4: effective_municipal_rate | BQ4: house_municipal_share | BR4: revenue_per_capita | BS4: expenses_per_capita | BT4: municipal_tax_per_capita | BU4: debt_per_capita | BV4: reserves_per_capita | BW4: replacement_value_per_capita
B5: 100-mile-house-d | C5: 2019 | D5: 100-mile-house-d:2019 | E5: 2019 | F5: 2019 | G5: FALSE | H5: 9825686 | I5: 3072768 | J5: 1474865 | K5: 2583600 | L5: 288672 | M5: 0 | N5: 7242086 | O5: 6542068 | P5: 1231439 | Q5: 5310629 | R5: 2052239 | S5: 676565 | T5: 1175011 | U5: 111087 | V5: 377162 | W5: 341590 | X5: 3283618 | Y5: 3371108 | Z5: 13607758 | AA5: 15328455 | AB5: 2620228 | AC5: 12708227 | AD5: 48590164 | AE5: 989681 | AF5: 11914045 | AG5: 12903726 | AH5: 77230 | AI5: 0 | AJ5: 1275179 | AK5: 67131 | AL5: 6486834 | AM5: 1621709 | AN5: 1342310 | AO5: 279399 | AP5: 290695842 | AQ5: 163660200 | AR5: 2714523.1 | AS5: 6240533.7 | AT5: 223429 | AU5: 862.44488 | AV5: 2752.1178 | AW5: 59738422 | AX5: 35763667 | AY5: 3371108 | AZ5: 3371108 | BA5: 8315007 | BB5: 0 | BD5: 0.73705653 | BE5: 0.33418715 | BF5: 0.82771323 | BG5: 0.20692837 | BH5: 2.4297924 | BI5: 0.46622254 | BJ5: 0 | BL5: not reported | BP5: 9.3380182 | BQ5: 0.31337499 | BR5: 4866.6102 | BS5: 3240.2516 | BT5: 1344.4889 | BU5: 38.25161 | BV5: 6391.1471 | BW5: 4118.3789
B6: 100-mile-house-d | C6: 2020 | D6: 100-mile-house-d:2020 | E6: 2012 | F6: 2012 | G6: FALSE | H6: 8659279 | I6: 3142829 | J6: 1404708 | K6: 2079918 | L6: 148610 | M6: 0 | N6: 6579361 | O6: 5551516 | P6: 1461608 | Q6: 4089908 | R6: 837941 | S6: 662178 | T6: 1100566 | U6: 86655 | V6: 330885 | W6: 329261 | X6: 3107763 | Y6: 1784403 | Z6: 14941418 | AA6: 18568748 | AB6: 3032079 | AC6: 15536669 | AD6: 51691915 | AE6: 3630387 | AF6: 12077591 | AG6: 15707978 | AH6: 49656 | AI6: 0 | AJ6: 12637 | AK6: 18158 | AL6: 4962712 | AM6: 1240678 | AN6: 30795 | AO6: 1209883 | AP6: 295988116 | AQ6: 167800887 | AR6: 2755329 | AS6: 6100560 | AT6: 226700 | AU6: 861 | AV6: 2812 | AW6: 61171690 | AX6: 36033593 | AY6: 1784403 | AZ6: 2577755.5 | BA6: 2173346 | BB6: 0 | BD6: 0.75980471 | BE6: 0.35889397 | BF6: 0.024821106 | BG6: 0.0062052765 | BH6: 3.8406678 | BI6: 0.4260814 | BJ6: 0 | BL6: not reported | BP6: 9.3089177 | BQ6: 0.30618777 | BR6: 4303.8166 | BS6: 2759.2028 | BT6: 1369.4478 | BU6: 24.67992 | BV6: 7807.1461 | BW6: 1080.1918
B7: 100-mile-house-d | C7: 2021 | D7: 100-mile-house-d:2021 | E7: 2016 | F7: 2016 | G7: FALSE | H7: 8692670 | I7: 3157660 | J7: 1230930 | K7: 1635703 | L7: 109557 | M7: 1133768 | N7: 5923199 | O7: 6048436 | P7: 1493519 | Q7: 4554917 | R7: 942337 | S7: 821450 | T7: 1222655 | U7: 127920 | V7: 382800 | W7: 266187 | X7: 2644234 | Y7: 3678534 | Z7: 18059084 | AA7: 19609973 | AB7: 3607461 | AC7: 16002512 | AD7: 54342220 | AE7: 3415363 | AF7: 14730990 | AG7: 18146353 | AH7: 38135 | AI7: 0 | AJ7: 5278 | AK7: 5514 | AL7: 4723454 | AM7: 1180864 | AN7: 10792 | AO7: 1170072 | AP7: 304604588 | AQ7: 177465137 | AR7: 2786666 | AS7: 6527718 | AT7: 234129 | AU7: 864 | AV7: 2870 | AW7: 64722115 | AX7: 38218609 | AY7: 3678534 | AZ7: 2944681.7 | BA7: 4301667 | BB7: 0 | BD7: 0.68140157 | BE7: 0.30419123 | BF7: 0.0091390711 | BG7: 0.0022847687 | BH7: 3.9839042 | BI7: 0.43865127 | BJ7: 0 | BL7: not reported | BP7: 9.1484702 | BQ7: 0.3010453 | BR7: 4311.8403 | BS7: 3000.2163 | BT7: 1382.2748 | BU7: 18.916171 | BV7: 9001.1672 | BW7: 2133.7634
B8: 100-mile-house-d | C8: 2022 | D8: 100-mile-house-d:2022 | E8: 2026 | F8: 2026 | G8: FALSE | H8: 8564550 | I8: 3015003 | J8: 1168318 | K8: 2532222 | L8: 349111 | M8: 389400 | N8: 5642928 | O8: 6527624 | P8: 1636460 | Q8: 4891164 | R8: 1076178 | S8: 763297 | T8: 1390454 | U8: 126143 | V8: 484814 | W8: 303072 | X8: 2036926 | Y8: 3957800 | Z8: 16969220 | AA8: 18828241 | AB8: 3472711 | AC8: 15355530 | AD8: 56379145 | AE8: 569589 | AF8: 15361537 | AG8: 15931126 | AH8: 26038 | AI8: 0 | AJ8: 5278 | AK8: 7409 | AL8: 4977898 | AM8: 1244475 | AN8: 12687 | AO8: 1222838 | AP8: 356936205 | AQ8: 228648537 | AR8: 2636147 | AS8: 6356955 | AT8: 305457 | AU8: 910 | AV8: 3084 | AW8: 68577975 | AX8: 40474057 | AY8: 3957800 | AZ8: 3140245.7 | BA8: 4687182 | BB8: 0 | BD8: 0.65887034 | BE8: 0.23783223 | BF8: 0.01019466 | BG8: 0.0025486661 | BH8: 3.2571237 | BI8: 0.4398743 | BJ8: 0 | BL8: not reported | BP8: 7.385485 | BQ8: 0.29507134 | BR8: 4227.3198 | BS8: 3221.9269 | BT8: 1301.1584 | BU8: 12.851925 | BV8: 7863.3396 | BW8: 2313.5153
B9: 100-mile-house-d | C9: 2023 | D9: 100-mile-house-d:2023 | E9: 2083 | F9: 2083 | G9: FALSE | H9: 8705333 | I9: 3138612 | J9: 1569199 | K9: 2989878 | L9: 1004644 | M9: 3000 | N9: 5712455 | O9: 6748188 | P9: 1846957 | Q9: 4901231 | R9: 981176 | S9: 746542 | T9: 1367718 | U9: 141508 | V9: 564248 | W9: 263495 | X9: 1957145 | Y9: 2126824 | Z9: 19156595 | AA9: 20435262 | AB9: 2504166 | AC9: 17931096 | AD9: 59544517 | AE9: 2616402 | AF9: 16863872 | AG9: 19480274 | AH9: 13336 | AI9: 0 | AJ9: 5278 | AK9: 3927 | AL9: 5789162 | AM9: 1447291 | AN9: 9205 | AO9: 1438086 | AP9: 427932874 | AQ9: 290013850 | AR9: 2709333 | AS9: 6699791 | AT9: 378886 | AU9: 921 | AV9: 3346 | AW9: 70959253 | AX9: 40958042 | AY9: 2126824 | AZ9: 3254386 | BA9: 3978488 | BB9: 0 | BD9: 0.65620178 | BE9: 0.22482138 | BF9: 0.0063601584 | BG9: 0.0015900401 | BH9: 3.9745676 | BI9: 0.44790786 | BJ9: 0 | BL9: not reported | BP9: 6.3312103 | BQ9: 0.27525403 | BR9: 4179.2285 | BS9: 3239.6486 | BT9: 1300.688 | BU9: 6.4023044 | BV9: 9352.0278 | BW9: 1909.9798
B10: 100-mile-house-d | C10: 2024 | D10: 100-mile-house-d:2024 | E10: 2083 | F10: 2083 | G10: FALSE | H10: 7942355 | I10: 3195706 | J10: 2293313 | K10: 1430830 | L10: 982855 | M10: 13846 | N10: 6497679 | O10: 7235974 | P10: 1860712 | Q10: 5375262 | R10: 1171774 | S10: 762724 | T10: 1439756 | U10: 190018 | V10: 688128 | W10: 376261 | X10: 706381 | Y10: 3338540 | Z10: 18530754 | AA10: 20027579 | AB10: 2441445 | AC10: 17586134 | AD10: 60250899 | AE10: 3280520 | AF10: 15647339 | AG10: 18927859 | AH10: 0 | AI10: 0 | AJ10: 5278 | AK10: 3615 | AL10: 6665880 | AM10: 1666470 | AN10: 8893 | AO10: 1657577 | AP10: 434155427 | AQ10: 288750787 | AR10: 2748169 | AS10: 7058665 | AT10: 365808 | AU10: 943 | AV10: 3509 | AW10: 73302743 | AX10: 42417550 | AY10: 3338540 | AZ10: 3141054.7 | BA10: 176317528 | BB10: 4471702 | BC10: 0 | BD10: 0.81810483 | BE10: 0.088938482 | BF10: 0.0053364297 | BG10: 0.0013341074 | BH10: 3.5212905 | BI10: 0.45469072 | BJ10: 2.51658 | BK10: 0.026159406 | BL10: plausible | BM10: 4682630.6 | BN10: 0.67078848 | BO10: 1541576 | BP10: 6.3299197 | BQ10: 0.26873753 | BR10: 3812.9405 | BS10: 3473.8233 | BT10: 1319.3322 | BU10: 0 | BV10: 9086.8262 | BW10: 84645.957
B11: abbotsford-c | C11: 2019 | D11: abbotsford-c:2019 | E11: 158457 | F11: 158457 | G11: FALSE | H11: 305720000 | I11: 152032000 | J11: 90482000 | K11: 25832000 | L11: 9618000 | M11: 23239000 | N11: 256649000 | O11: 244201000 | P11: 38251000 | Q11: 205950000 | R11: 16427000 | S11: 76897000 | T11: 32367000 | U11: 38241000 | V11: 10445000 | W11: 8026000 | X11: 61519000 | Y11: 55381000 | Z11: 498953000 | AA11: 541951000 | AB11: 271773000 | AC11: 270178000 | AD11: 1711831000 | AE11: 99842000 | AF11: 224232000 | AG11: 324074000 | AH11: 51810000 | AI11: 0 | AJ11: 2328000 | AK11: 4250000 | AL11: 257700000 | AM11: 64425000 | AN11: 6578000 | AO11: 57847000 | AP11: 34759618836 | AQ11: 29206505574 | AR11: 1.4400534e+08 | AS11: 2.6441737e+08 | AT11: 750887 | AU11: 2321.4197 | AV11: 4308.5732 | AW11: 2399793000 | AX11: 1439567000 | AY11: 55381000 | AZ11: 55381000 | BA11: 499674000 | BB11: 0 | BD11: 0.83949038 | BE11: 0.20122661 | BF11: 0.10210322 | BG11: 0.025525805 | BH11: 1.5735567 | BI11: 0.50535045 | BJ11: 0 | BL11: not reported | BP11: 4.1428919 | BQ11: 0.53879083 | BR11: 1929.3562 | BS11: 1541.1184 | BT11: 908.79762 | BU11: 326.96568 | BV11: 2045.1858 | BW11: 3153.3728
B12: abbotsford-c | C12: 2020 | D12: abbotsford-c:2020 | E12: 161581 | F12: 161581 | G12: FALSE | H12: 305147000 | I12: 158120000 | J12: 78997000 | K12: 29881000 | L12: 10224000 | M12: 27925000 | N12: 247341000 | O12: 266866000 | P12: 37562000 | Q12: 229304000 | R12: 18466000 | S12: 82152000 | T12: 30699000 | U12: 31586000 | V12: 10861000 | W12: 8397000 | X12: 38281000 | Y12: 56169000 | Z12: 558499000 | AA12: 598494000 | AB12: 285609000 | AC12: 312885000 | AD12: 1750243000 | AE12: 108787000 | AF12: 254200000 | AG12: 362987000 | AH12: 47804000 | AI12: 0 | AJ12: 2543000 | AK12: 4250000 | AL12: 248618343 | AM12: 62154586 | AN12: 6793000 | AO12: 55361586 | AP12: 35033910203 | AQ12: 28717500198 | AR12: 149815520 | AS12: 260011180 | AT12: 733282 | AU12: 2399 | AV12: 4430 | AW12: 2427385000 | AX12: 1435060000 | AY12: 56169000 | AZ12: 55775000 | BA12: 483710000 | BB12: 0 | BD12: 0.81056343 | BE12: 0.12545101 | BF12: 0.10929202 | BG12: 0.027323004 | BH12: 1.5829946 | BI12: 0.5105406 | BJ12: 0 | BL12: not reported | BP12: 4.2763003 | BQ12: 0.54153499 | BR12: 1888.5079 | BS12: 1651.5927 | BT12: 927.18525 | BU12: 295.85162 | BV12: 2246.4708 | BW12: 2993.6069
B13: abbotsford-c | C13: 2021 | D13: abbotsford-c:2021 | E13: 165070 | F13: 165070 | G13: FALSE | H13: 324358000 | I13: 163829000 | J13: 97940000 | K13: 38646000 | L13: 9040000 | M13: 14903000 | N13: 270809000 | O13: 271325000 | P13: 42767000 | Q13: 228558000 | R13: 18812000 | S13: 100111000 | T13: 31435000 | U13: 33909000 | V13: 10201000 | W13: 8431000 | X13: 53033000 | Y13: 60881000 | Z13: 617689000 | AA13: 669825000 | AB13: 320720000 | AC13: 349105000 | AD13: 1803276000 | AE13: 116503000 | AF13: 279234000 | AG13: 395737000 | AH13: 43965000 | AI13: 0 | AJ13: 2365000 | AK13: 4250000 | AL13: 272265105 | AM13: 68066276 | AN13: 6615000 | AO13: 61451276 | AP13: 37393927775 | AQ13: 30541446528 | AR13: 154873903 | AS13: 286693281 | AT13: 784933 | AU13: 2491 | AV13: 4616 | AW13: 2479090000 | AX13: 1451504000 | AY13: 60881000 | AZ13: 57477000 | BA13: 503954000 | BB13: 0 | BD13: 0.83490773 | BE13: 0.16350144 | BF13: 0.097184691 | BG13: 0.024296173 | BH13: 1.7314511 | BI13: 0.52026088 | BJ13: 0 | BL13: not reported | BP13: 4.1416859 | BQ13: 0.53964471 | BR13: 1964.9724 | BS13: 1643.6966 | BT13: 938.23168 | BU13: 266.34155 | BV13: 2397.389 | BW13: 3052.9715
B14: abbotsford-c | C14: 2022 | D14: abbotsford-c:2022 | E14: 168478 | F14: 168478 | G14: FALSE | H14: 348515000 | I14: 173268000 | J14: 114012000 | K14: 40235000 | L14: 10168000 | M14: 10644000 | N14: 297636000 | O14: 293584000 | P14: 41898000 | Q14: 251686000 | R14: 21978000 | S14: 89077000 | T14: 55371000 | U14: 36877000 | V14: 11014000 | W14: 9341000 | X14: 54931000 | Y14: 85181000 | Z14: 646833000 | AA14: 703340000 | AB14: 343825000 | AC14: 359515000 | AD14: 1858207000 | AE14: 112930000 | AF14: 291357000 | AG14: 404287000 | AH14: 39972000 | AI14: 0 | AJ14: 2316000 | AK14: 4250000 | AL14: 298439000 | AM14: 74609750 | AN14: 6566000 | AO14: 64821750 | AP14: 49461534920 | AQ14: 41066005479 | AR14: 164114095 | AS14: 306346727 | AT14: 1073791 | AU14: 2655 | AV14: 4996 | AW14: 2559654000 | AX14: 1493892000 | AY14: 85181000 | AZ14: 67410333 | BA14: 551952000 | BB14: 0 | BD14: 0.85401202 | BE14: 0.15761445 | BF14: 0.088004584 | BG14: 0.022001146 | BH14: 1.606315 | BI14: 0.53083675 | BJ14: 0 | BL14: not reported | BP14: 3.3180146 | BQ14: 0.53142514 | BR14: 2068.6084 | BS14: 1742.5658 | BT14: 974.09807 | BU14: 237.25353 | BV14: 2399.6427 | BW14: 3276.1073
B15: abbotsford-c | C15: 2023 | D15: abbotsford-c:2023 | E15: 175589 | F15: 175589 | G15: FALSE | H15: 390769000 | I15: 187277000 | J15: 111247000 | K15: 62042000 | L15: 19501000 | M15: 9551000 | N15: 319176000 | O15: 307667000 | P15: 40207000 | Q15: 267460000 | R15: 27801000 | S15: 99867000 | T15: 41662000 | U15: 40236000 | V15: 16021000 | W15: 11722000 | X15: 83102000 | Y15: 101378000 | Z15: 780043000 | AA15: 846726000 | AB15: 466758000 | AC15: 379968000 | AD15: 1941309000 | AE15: 116795000 | AF15: 309669000 | AG15: 426464000 | AH15: 35784000 | AI15: 0 | AJ15: 2521000 | AK15: 4252000 | AL15: 318367000 | AM15: 79591750 | AN15: 6773000 | AO15: 69510350 | AP15: 56136840101 | AQ15: 45262759216 | AR15: 175745593 | AS15: 333525576 | AT15: 1156473 | AU15: 2749 | AV15: 5148 | AW15: 2659431000 | AX15: 1554791000 | AY15: 101378000 | AZ15: 82480000 | BA15: 638703000 | BB15: 0 | BD15: 0.81678946 | BE15: 0.21266272 | BF15: 0.085096759 | BG15: 0.02127419 | BH15: 1.5944964 | BI15: 0.54665447 | BJ15: 0 | BL15: not reported | BP15: 3.1306642 | BQ15: 0.53399378 | BR15: 2225.4754 | BS15: 1752.1997 | BT15: 1000.8918 | BU15: 203.79409 | BV15: 2428.7626 | BW15: 3637.4887
B16: abbotsford-c | C16: 2024 | D16: abbotsford-c:2024 | E16: 175589 | F16: 175589 | G16: FALSE | H16: 421880000 | I16: 200014000 | J16: 121396000 | K16: 39940000 | L16: 25999000 | M16: 33507000 | N16: 348433000 | O16: 355648000 | P16: 38214000 | Q16: 317434000 | R16: 28548000 | S16: 111034000 | T16: 79733000 | U16: 42859000 | V16: 15091000 | W16: 10459000 | X16: 66232000 | Y16: 100669000 | Z16: 824233000 | AA16: 886274000 | AB16: 503881000 | AC16: 382393000 | AD16: 2007541000 | AE16: 106598000 | AF16: 319753000 | AG16: 426351000 | AH16: 31436000 | AI16: 0 | AJ16: 2482000 | AK16: 4184000 | AL16: 347715000 | AM16: 86928750 | AN16: 6666000 | AO16: 76983150 | AP16: 56662122282 | AQ16: 44720046151 | AR16: 188483455 | AS16: 356721921 | AT16: 1139332 | AU16: 2916 | AV16: 5497 | AW16: 2758390000 | AX16: 1616892000 | AY16: 100669000 | AZ16: 95742667 | BA16: 4514715000 | BB16: 29599000 | BC16: 0 | BD16: 0.82590547 | BE16: 0.15699251 | BF16: 0.076683491 | BG16: 0.019170873 | BH16: 1.343117 | BI16: 0.53338237 | BJ16: 1.8206697 | BK16: 0.0075964272 | BL16: plausible | BM16: 69575071 | BN16: 1.3761059 | BO16: 0 | BP16: 3.3264454 | BQ16: 0.53047117 | BR16: 2402.6562 | BS16: 2025.4572 | BT16: 1073.4354 | BU16: 179.03172 | BV16: 2428.1191 | BW16: 25711.833
B17: alert-bay-v | C17: 2019 | D17: alert-bay-v:2019 | E17: 473 | F17: 473 | G17: FALSE | H17: 1913948 | I17: 450544 | J17: 754269 | K17: 663024 | L17: 46111 | M17: 0 | N17: 1250924 | O17: 1637211 | P17: 351778 | Q17: 1285433 | R17: 432296 | S17: 50269 | T17: 155589 | U17: 62338 | V17: 38956 | W17: 134257 | X17: 276737 | Y17: 222687 | Z17: 2394534 | AA17: 2622348 | AB17: 1207596 | AC17: 1414752 | AD17: 7793404 | AE17: 1655681 | AF17: 149380 | AG17: 1805061 | AH17: 367090 | AI17: 0 | AJ17: 35291 | AK17: 45120 | AL17: 1661899 | AM17: 415475 | AN17: 80411 | AO17: 334169 | AP17: 37941100 | AQ17: 34166000 | AR17: 358616.92 | AS17: 855477.08 | AT17: 137067 | AU17: 1132.1405 | AV17: 2653.3675 | AW17: 12979305 | AX17: 6355433 | AY17: 222687 | AZ17: 222687 | BA17: 362518 | BB17: 0 | BD17: 0.65358306 | BE17: 0.14458961 | BF17: 0.19353992 | BG17: 0.04838501 | BH17: 1.4042436 | BI17: 0.52500466 | BJ17: 0 | BL17: not reported | BP17: 9.451938 | BQ17: 0.42668063 | BR17: 4046.4017 | BS17: 3461.334 | BT17: 758.17531 | BU17: 776.08879 | BV17: 3816.1966 | BW17: 766.42283
B18: alert-bay-v | C18: 2020 | D18: alert-bay-v:2020 | E18: 441 | F18: 441 | G18: FALSE | H18: 2216644 | I18: 447704 | J18: 722056 | K18: 994458 | L18: 52426 | M18: 0 | N18: 1222186 | O18: 1659729 | P18: 353318 | Q18: 1306411 | R18: 472410 | S18: 59358 | T18: 156208 | U18: 35515 | V18: 41216 | W18: 138523 | X18: 556915 | Y18: 369175 | Z18: 2618157 | AA18: 2832140 | AB18: 876479 | AC18: 1955661 | AD18: 8350319 | AE18: 2105696 | AF18: 184380 | AG18: 2290076 | AH18: 311047 | AI18: 0 | AJ18: 35291 | AK18: 45120 | AL18: 1655434 | AM18: 413859 | AN18: 80411 | AO18: 330521 | AP18: 43371613 | AQ18: 39281000 | AR18: 356287 | AS18: 877986 | AT18: 157595 | AU18: 1129 | AV18: 2781 | AW18: 13348480 | AX18: 6371290 | AY18: 369175 | AZ18: 295931 | BA18: 185981 | BB18: 0 | BD18: 0.55136774 | BE18: 0.25124242 | BF18: 0.19429564 | BG18: 0.048573969 | BH18: 1.7529522 | BI18: 0.53008095 | BJ18: 0 | BL18: not reported | BP18: 8.214751 | BQ18: 0.40596908 | BR18: 5026.4036 | BS18: 3763.5578 | BT18: 807.90703 | BU18: 705.322 | BV18: 5192.9161 | BW18: 421.72562
B19: alert-bay-v | C19: 2021 | D19: alert-bay-v:2021 | E19: 434 | F19: 434 | G19: FALSE | H19: 1759721 | I19: 447466 | J19: 742075 | K19: 521805 | L19: 48375 | M19: 0 | N19: 1237916 | O19: 1647703 | P19: 330207 | Q19: 1317496 | R19: 412127 | S19: 57470 | T19: 214348 | U19: 44685 | V19: 35311 | W19: 164116 | X19: 112018 | Y19: 31463 | Z19: 3296427 | AA19: 3502935 | AB19: 1136098 | AC19: 2366837 | AD19: 8462337 | AE19: 2422871 | AF19: 219380 | AG19: 2642251 | AH19: 252460 | AI19: 0 | AJ19: 39119 | AK19: 54193 | AL19: 1662266 | AM19: 415567 | AN19: 93312 | AO19: 319256 | AP19: 47485295 | AQ19: 43139512 | AR19: 365264 | AS19: 923880 | AT19: 173152 | AU19: 1163 | AV19: 2867 | AW19: 13379943 | AX19: 6072546 | AY19: 31463 | AZ19: 207775 | BA19: 217444 | BB19: 0 | BD19: 0.70347288 | BE19: 0.063656682 | BF19: 0.22454141 | BG19: 0.05613542 | BH19: 2.0055097 | BI19: 0.55516791 | BJ19: 0 | BL19: not reported | BP19: 7.6921497 | BQ19: 0.40565051 | BR19: 4054.6567 | BS19: 3796.5507 | BT19: 841.62212 | BU19: 581.70507 | BV19: 6088.1359 | BW19: 501.02304
B20: alert-bay-v | C20: 2022 | D20: alert-bay-v:2022 | E20: 466 | F20: 466 | G20: FALSE | H20: 2255783 | I20: 505010 | J20: 779622 | K20: 883213 | L20: 87938 | M20: 0 | N20: 1372570 | O20: 1830057 | P20: 317634 | Q20: 1512423 | R20: 464177 | S20: 33997 | T20: 254988 | U20: 52927 | V20: 56552 | W20: 174452 | X20: 425726 | Y20: 219892 | Z20: 3683284 | AA20: 3980896 | AB20: 1077235 | AC20: 2903661 | AD20: 8888063 | AE20: 2850995 | AF20: 254380 | AG20: 3105375 | AH20: 192115 | AI20: 0 | AJ20: 39119 | AK20: 54920 | AL20: 1872264 | AM20: 468066 | AN20: 94039 | AO20: 370956 | AP20: 64058918 | AQ20: 58200675 | AR20: 405669 | AS20: 961786 | AT20: 231035 | AU20: 1288 | AV20: 2726 | AW20: 13599835 | AX20: 5974804 | AY20: 219892 | AZ20: 206843.33 | BA20: 353220 | BB20: 0 | BD20: 0.60846722 | BE20: 0.18872649 | BF20: 0.2009097 | BG20: 0.050227425 | BH20: 2.053245 | BI20: 0.57562109 | BJ20: 0 | BL20: not reported | BP20: 6.3327482 | BQ20: 0.47248716 | BR20: 4840.7361 | BS20: 3927.1609 | BT20: 870.53433 | BU20: 412.26395 | BV20: 6663.8948 | BW20: 757.98283
B21: alert-bay-v | C21: 2023 | D21: alert-bay-v:2023 | E21: 463 | F21: 463 | G21: FALSE | H21: 2962979 | I21: 541509 | J21: 823226 | K21: 1401922 | L21: 196322 | M21: 0 | N21: 1561057 | O21: 2252793 | P21: 367373 | Q21: 1885420 | R21: 465859 | S21: 33432 | T21: 171502 | U21: 65107 | V21: 50009 | W21: 166551 | X21: 710186 | Y21: 318022 | Z21: 4473978 | AA21: 4715309 | AB21: 2431217 | AC21: 2284092 | AD21: 9598249 | AE21: 2830240 | AF21: 972514 | AG21: 3802754 | AH21: 129959 | AI21: 0 | AJ21: 39119 | AK21: 57792 | AL21: 1917434 | AM21: 479359 | AN21: 96911 | AO21: 382448 | AP21: 65354922 | AQ21: 60038250 | AR21: 431654 | AS21: 993148 | AT21: 236348 | AU21: 1354 | AV21: 2777 | AW21: 15274046 | AX21: 7281642 | AY21: 318022 | AZ21: 189792.33 | BA21: 275374 | BB21: 0 | BD21: 0.52685389 | BE21: 0.23968648 | BF21: 0.2021679 | BG21: 0.050542026 | BH21: 2.0169267 | BI21: 0.53287411 | BJ21: 0 | BL21: not reported | BP21: 6.6047665 | BQ21: 0.48757652 | BR21: 6399.5227 | BS21: 4865.6436 | BT21: 932.29806 | BU21: 280.68898 | BV21: 8213.2916 | BW21: 594.76026
B22: alert-bay-v | C22: 2024 | D22: alert-bay-v:2024 | E22: 463 | F22: 463 | G22: FALSE | H22: 2708429 | I22: 537383 | J22: 895852 | K22: 1054694 | L22: 220500 | M22: 0 | N22: 1653735 | O22: 2127219 | P22: 403232 | Q22: 1723987 | R22: 480010 | S22: 65117 | T22: 145185 | U22: 78800 | V22: 78788 | W22: 150954 | X22: 581210 | Y22: 508290 | Z22: 4691492 | AA22: 4961576 | AB22: 2232617 | AC22: 2728959 | AD22: 10179457 | AE22: 3157372 | AF22: 1057512 | AG22: 4214884 | AH22: 65940 | AI22: 0 | AJ22: 39119 | AK22: 58179 | AL22: 2042640 | AM22: 510660 | AN22: 97298 | AO22: 410636 | AP22: 79969647 | AQ22: 73878775 | AR22: 445240 | AS22: 1080151 | AT22: 291655 | AU22: 1418 | AV22: 3068 | AW22: 15814884 | AX22: 7419248 | AY22: 508290 | AZ22: 348734.67 | BA22: 31702564 | BB22: 744828 | BC22: 1 | BD22: 0.61058828 | BE22: 0.21459304 | BF22: 0.19053382 | BG22: 0.047633455 | BH22: 2.4448467 | BI22: 0.54566322 | BJ22: 2.0325987 | BK22: 0.023816363 | BL22: plausible | BM22: 819608.83 | BN22: 0.42548915 | BO22: 470874.16 | BP22: 5.5676124 | BQ22: 0.46219035 | BR22: 5849.7387 | BS22: 4594.4255 | BT22: 961.64147 | BU22: 142.41901 | BV22: 9103.4212 | BW22: 68472.06
B23: anmore-v | C23: 2019 | D23: anmore-v:2019 | E23: 2515 | F23: 2515 | G23: FALSE | H23: 4740333 | I23: 2360944 | J23: 1198418 | K23: 763741 | L23: 240042 | M23: 177188 | N23: 3799404 | O23: 3538477 | P23: 996736 | Q23: 2541741 | R23: 967222 | S23: 168858 | T23: 333045 | U23: 0 | V23: 597330 | W23: 0 | X23: 1201856 | Y23: 166964 | Z23: 12187658 | AA23: 12913392 | AB23: 4275948 | AC23: 8637444 | AD23: 67833555 | AE23: 2242888 | AF23: 6458424 | AG23: 8701312 | AH23: 0 | AI23: 0 | AJ23: 0 | AK23: 0 | AL23: 4519696 | AM23: 1129924 | AN23: 0 | AO23: 1129924 | AP23: 1620341100 | AQ23: 1617472200 | AR23: 2210793.4 | AS23: 6392627.9 | AT23: 2079826 | AU23: 2837.7146 | AV23: 7640.7826 | AW23: 73837562 | AX23: 59132244 | AY23: 166964 | AZ23: 166964 | BA23: 37790548 | BB23: 0 | BD23: 0.80150572 | BE23: 0.25353831 | BF23: 0 | BG23: 0 | BH23: 3.4233669 | BI23: 0.4079483 | BJ23: 0 | BL23: not reported | BP23: 1.3644 | BQ23: 0.37139057 | BR23: 1884.8243 | BS23: 1406.9491 | BT23: 879.0431 | BU23: 0 | BV23: 3459.7662 | BW23: 15026.063
B24: anmore-v | C24: 2020 | D24: anmore-v:2020 | E24: 2412 | F24: 2412 | G24: FALSE | H24: 5713310 | I24: 2516820 | J24: 1145258 | K24: 1836154 | L24: 162560 | M24: 52518 | N24: 3824638 | O24: 4173007 | P24: 1396555 | Q24: 2776452 | R24: 1023730 | S24: 189186 | T24: 433174 | U24: 0 | V24: 663372 | W24: 0 | X24: 1540303 | Y24: 1775434 | Z24: 13234805 | AA24: 14619240 | AB24: 4839174 | AC24: 9780066 | AD24: 69373242 | AE24: 2744684 | AF24: 7142305 | AG24: 9886989 | AH24: 0 | AI24: 0 | AJ24: 0 | AK24: 0 | AL24: 4215024 | AM24: 1053756 | AN24: 0 | AO24: 1053756 | AP24: 1564397200 | AQ24: 1561412300 | AR24: 2356608 | AS24: 6743663 | AT24: 1990167 | AU24: 2998 | AV24: 8214 | AW24: 73509862 | AX24: 59486252 | AY24: 1775434 | AZ24: 971199 | BA24: 58501685 | BB24: 887465 | BC24: 1 | BD24: 0.66942595 | BE24: 0.26959906 | BF24: 0 | BG24: 0 | BH24: 3.5610156 | BI24: 0.3926058 | BJ24: 0.5798302 | BK24: 0.042849651 | BL24: replacement value implausible | BP24: 1.5064 | BQ24: 0.36498661 | BR24: 2368.7023 | BS24: 1730.1024 | BT24: 977.03483 | BU24: 0 | BV24: 4099.0833 | BW24: 24254.43
B25: anmore-v | C25: 2021 | D25: anmore-v:2021 | E25: 2632 | F25: 2632 | G25: FALSE | H25: 5914880 | I25: 2592650 | J25: 1302082 | K25: 796906 | L25: 85326 | M25: 1093500 | N25: 4024474 | O25: 4011434 | P25: 1077595 | Q25: 2933839 | R25: 1138867 | S25: 245057 | T25: 488791 | U25: 0 | V25: 636565 | W25: 0 | X25: 1903446 | Y25: 606290 | Z25: 15780723 | AA25: 16732984 | AB25: 4543791 | AC25: 12189193 | AD25: 71276688 | AE25: 4002532 | AF25: 8259208 | AG25: 12261740 | AH25: 0 | AI25: 0 | AJ25: 0 | AK25: 0 | AL25: 4597281 | AM25: 1149320 | AN25: 0 | AO25: 1149320 | AP25: 1584029300 | AQ25: 1581260400 | AR25: 2425941 | AS25: 6912364 | AT25: 2031353 | AU25: 3111 | AV25: 8437 | AW25: 73909419 | AX25: 59014948 | AY25: 606290 | AZ25: 849562.67 | BA25: 55447430 | BB25: 1076029 | BC25: 1 | BD25: 0.68039825 | BE25: 0.32180636 | BF25: 0 | BG25: 0 | BH25: 4.1794182 | BI25: 0.41969614 | BJ25: 0.47977839 | BK25: 0.063196523 | BL25: replacement value implausible | BP25: 1.5315001 | BQ25: 0.36873296 | BR25: 2247.2948 | BS25: 1524.1011 | BT25: 921.71011 | BU25: 0 | BV25: 4658.7158 | BW25: 21066.653
B26: anmore-v | C26: 2022 | D26: anmore-v:2022 | E26: 2485 | F26: 2485 | G26: FALSE | H26: 7206378 | I26: 2669828 | J26: 1409069 | K26: 2848611 | L26: 278870 | M26: 0 | N26: 4357767 | O26: 3966962 | P26: 1071135 | Q26: 2895827 | R26: 1177075 | S26: 252526 | T26: 585180 | U26: 0 | V26: 573399 | W26: 0 | X26: 3239416 | Y26: 3718611 | Z26: 16848672 | AA26: 19941529 | AB26: 7155494 | AC26: 12786035 | AD26: 74516105 | AE26: 4425472 | AF26: 8428209 | AG26: 12853681 | AH26: 0 | AI26: 0 | AJ26: 0 | AK26: 0 | AL26: 4813767 | AM26: 1203442 | AN26: 0 | AO26: 1203442 | AP26: 1874461800 | AQ26: 1870951000 | AR26: 2490597 | AS26: 7308710 | AT26: 2368756 | AU26: 3147 | AV26: 8548 | AW26: 77628027 | AX26: 61662424 | AY26: 3718611 | AZ26: 2033445 | BA26: 61662423 | BB26: 1071135 | BC26: 1 | BD26: 0.60470974 | BE26: 0.44952069 | BF26: 0 | BG26: 0 | BH26: 4.4386909 | BI26: 0.44028107 | BJ26: 0.5597189 | BK26: 0.052773868 | BL26: replacement value implausible | BP26: 1.3286998 | BQ26: 0.36815629 | BR26: 2899.9509 | BS26: 1596.363 | BT26: 1002.2523 | BU26: 0 | BV26: 5172.5074 | BW26: 24813.852
B27: anmore-v | C27: 2023 | D27: anmore-v:2023 | E27: 2533 | F27: 2533 | G27: FALSE | H27: 9263209 | I27: 2890637 | J27: 1396627 | K27: 3901665 | L27: 624280 | M27: 450000 | N27: 4911544 | O27: 4342651 | P27: 1153853 | Q27: 3188798 | R27: 1249508 | S27: 277453 | T27: 664239 | U27: 0 | V27: 638085 | W27: 0 | X27: 4920558 | Y27: 9602077 | Z27: 15609983 | AA27: 18438044 | AB27: 9185794 | AC27: 9252250 | AD27: 79436662 | AE27: 3557457 | AF27: 8302495 | AG27: 11859952 | AH27: 2500000 | AI27: 2500000 | AJ27: 0 | AK27: 0 | AL27: 5271544 | AM27: 1317886 | AN27: 0 | AO27: 1317886 | AP27: 1984145400 | AQ27: 1980381600 | AR27: 2699430 | AS27: 7689055 | AT27: 2510312 | AU27: 3415 | AV27: 10633 | AW27: 87187302 | AX27: 70076710 | AY27: 9602077 | AZ27: 4642326 | BA27: 49117013 | BB27: 0 | BD27: 0.53022057 | BE27: 0.53119367 | BF27: 0 | BG27: 0 | BH27: 3.7192547 | BI27: 0.44944739 | BJ27: 0 | BL27: not reported | BP27: 1.3605001 | BQ27: 0.32116994 | BR27: 3657.0111 | BS27: 1714.4299 | BT27: 1065.7047 | BU27: 986.97197 | BV27: 4682.1761 | BW27: 19390.846
B28: anmore-v | C28: 2024 | D28: anmore-v:2024 | E28: 2533 | F28: 2533 | G28: FALSE | H28: 7540763 | I28: 3154395 | J28: 1742974 | K28: 1862730 | L28: 630664 | M28: 150000 | N28: 5528033 | O28: 5163979 | P28: 1499260 | Q28: 3664719 | R28: 1661908 | S28: 191896 | T28: 629698 | U28: 0 | V28: 637859 | W28: 0 | X28: 2376784 | Y28: 2317801 | Z28: 16476469 | AA28: 18480016 | AB28: 7667449 | AC28: 10812567 | AD28: 81813447 | AE28: 4219516 | AF28: 9030048 | AG28: 13249564 | AH28: 2436997 | AI28: 0 | AJ28: 62496 | AK28: 123743 | AL28: 5928926 | AM28: 1482232 | AN28: 186239 | AO28: 1295993 | AP28: 2011625400 | AQ28: 2008008400 | AR28: 2945422 | AS28: 8245182 | AT28: 2535365 | AU28: 3712 | AV28: 11292 | AW28: 89505104 | AX28: 70895253 | AY28: 2317801 | AZ28: 5212829.7 | BA28: 112640548 | BB28: 1906000 | BC28: 1 | BD28: 0.73308669 | BE28: 0.31519145 | BF28: 0.12564767 | BG28: 0.031411929 | BH28: 3.6154379 | BI28: 0.36030867 | BJ28: 1.4479295 | BK28: 0.02548633 | BL28: plausible | BM28: 2170822.8 | BN28: 2.4013152 | BO28: 0 | BP28: 1.4642 | BQ28: 0.3287283 | BR28: 2977.0087 | BS28: 2038.681 | BT28: 1162.8196 | BU28: 962.09909 | BV28: 5230.7793 | BW28: 44469.225
B29: armstrong-c | C29: 2019 | D29: armstrong-c:2019 | E29: 5499 | F29: 5499 | G29: FALSE | H29: 7744737 | I29: 2917289 | J29: 3314663 | K29: 1315916 | L29: 187869 | M29: 9000 | N29: 6419821 | O29: 6662701 | P29: 1318306 | Q29: 5344395 | R29: 738155 | S29: 1100089 | T29: 778649 | U29: 1002487 | V29: 635231 | W29: 675889 | X29: 1082036 | Y29: 1854036 | Z29: 8494855 | AA29: 9752717 | AB29: 2647453 | AC29: 7105264 | AD29: 53294706 | AE29: 1725902 | AF29: 6300147 | AG29: 8026049 | AH29: 846510 | AI29: 0 | AJ29: 76686 | AK29: 29850 | AL29: 6996518 | AM29: 1749130 | AN29: 106536 | AO29: 1642594 | AP29: 883021119 | AQ29: 811317900 | AR29: 2909582.3 | AS29: 6589370.6 | AT29: 402560 | AU29: 1140.2874 | AV29: 2736.6342 | AW29: 74363691 | AX29: 46115167 | AY29: 1854036 | AZ29: 1854036 | BA29: 1556927 | BB29: 0 | BD29: 0.82892692 | BE29: 0.13971243 | BF29: 0.060907994 | BG29: 0.015227003 | BH29: 1.5017694 | BI29: 0.38799313 | BJ29: 0 | BL29: not reported | BP29: 3.2950314 | BQ29: 0.41667513 | BR29: 1408.3901 | BS29: 1211.6205 | BT29: 529.11117 | BU29: 153.9389 | BV29: 1459.547 | BW29: 283.12911
B30: armstrong-c | C30: 2020 | D30: armstrong-c:2020 | E30: 5433 | F30: 5433 | G30: FALSE | H30: 10915595 | I30: 3090497 | J30: 3434756 | K30: 2519066 | L30: 141892 | M30: 1721884 | N30: 6674645 | O30: 7301481 | P30: 1373369 | Q30: 5928112 | R30: 800680 | S30: 1199764 | T30: 747391 | U30: 788089 | V30: 711165 | W30: 1207771 | X30: 3614114 | Y30: 3615670 | Z30: 10522607 | AA30: 12057347 | AB30: 3572366 | AC30: 8484981 | AD30: 56908820 | AE30: 2615632 | AF30: 6710748 | AG30: 9326380 | AH30: 781427 | AI30: 0 | AJ30: 54185 | AK30: 29850 | AL30: 7246851 | AM30: 1811713 | AN30: 84035 | AO30: 1727678 | AP30: 918846386 | AQ30: 841127700 | AR30: 3099889 | AS30: 7441514 | AT30: 414548 | AU30: 1197 | AV30: 3100 | AW30: 77687154 | AX30: 48338401 | AY30: 3615670 | AZ30: 2734853 | BA30: 1556927 | BB30: 0 | BD30: 0.61147789 | BE30: 0.33109638 | BF30: 0.046384278 | BG30: 0.011596071 | BH30: 1.5732463 | BI30: 0.38550723 | BJ30: 0 | BL30: not reported | BP30: 3.3736749 | BQ30: 0.38612903 | BR30: 2009.1285 | BS30: 1343.9133 | BT30: 570.56672 | BU30: 143.82974 | BV30: 1716.617 | BW30: 286.56856
B31: armstrong-c | C31: 2021 | D31: armstrong-c:2021 | E31: 5529 | F31: 5529 | G31: FALSE | H31: 9023584 | I31: 3273690 | J31: 4236702 | K31: 1204116 | L31: 123594 | M31: 20120 | N31: 7799348 | O31: 7176629 | P31: 1376994 | Q31: 5799635 | R31: 634559 | S31: 1494218 | T31: 800587 | U31: 919278 | V31: 675380 | W31: 802607 | X31: 1846955 | Y31: 1595760 | Z31: 11171415 | AA31: 13196627 | AB31: 3067393 | AC31: 10129234 | AD31: 58755775 | AE31: 3192049 | AF31: 7721080 | AG31: 10913129 | AH31: 714522 | AI31: 0 | AJ31: 54186 | AK31: 29850 | AL31: 8374069 | AM31: 2093517 | AN31: 84036 | AO31: 2009481 | AP31: 964737985 | AQ31: 886947812 | AR31: 3272160 | AS31: 8034781 | AT31: 433306 | AU31: 1258 | AV31: 3261 | AW31: 79282917 | AX31: 48557168 | AY31: 1595760 | AZ31: 2355155.3 | BA31: 2194629 | BB31: 0 | BD31: 0.8643293 | BE31: 0.20468087 | BF31: 0.040141064 | BG31: 0.010035265 | BH31: 1.8816924 | BI31: 0.39857869 | BJ31: 0 | BL31: not reported | BP31: 3.3917603 | BQ31: 0.38577124 | BR31: 1632.0463 | BS31: 1297.9976 | BT31: 591.81769 | BU31: 129.23169 | BV31: 1973.798 | BW31: 396.93055
B32: armstrong-c | C32: 2022 | D32: armstrong-c:2022 | E32: 5677 | F32: 5677 | G32: FALSE | H32: 9333227 | I32: 3433125 | J32: 4460041 | K32: 1179428 | L32: 252033 | M32: 0 | N32: 8153799 | O32: 8360290 | P32: 1568891 | Q32: 6791399 | R32: 713645 | S32: 1394411 | T32: 919423 | U32: 987211 | V32: 1343011 | W32: 863746 | X32: 972937 | Y32: 5901479 | Z32: 11414080 | AA32: 13940857 | AB32: 6815508 | AC32: 7125349 | AD32: 59728712 | AE32: 665833 | AF32: 9194275 | AG32: 9860108 | AH32: 661728 | AI32: 0 | AJ32: 38186 | AK32: 67367 | AL32: 8866593 | AM32: 2216648 | AN32: 105553 | AO32: 1753095 | AP32: 1256480543 | AQ32: 1172221524 | AR32: 3428707 | AS32: 8671549 | AT32: 584063 | AU32: 1347 | AV32: 3404 | AW32: 84780705 | AX32: 52530332 | AY32: 5901479 | AZ32: 3704303 | BA32: 5953129 | BB32: 0 | BD32: 0.87363127 | BE32: 0.10424444 | BF32: 0.047618296 | BG32: 0.011904573 | BH32: 1.4518523 | BI32: 0.40912552 | BJ32: 0 | BL32: not reported | BP32: 2.7288182 | BQ32: 0.39571093 | BR32: 1644.0421 | BS32: 1472.6599 | BT32: 603.96459 | BU32: 116.56297 | BV32: 1736.8519 | BW32: 1048.64
B33: armstrong-c | C33: 2023 | D33: armstrong-c:2023 | E33: 5899 | F33: 5899 | G33: FALSE | H33: 13660120 | I33: 3774511 | J33: 4631396 | K33: 4390524 | L33: 617252 | M33: 198383 | N33: 9071213 | O33: 8885044 | P33: 1300069 | Q33: 7584975 | R33: 926043 | S33: 1781522 | T33: 965082 | U33: 1068429 | V33: 848147 | W33: 1189031 | X33: 4775076 | Y33: 3715759 | Z33: 28844410 | AA33: 32021319 | AB33: 23430181 | AC33: 8591138 | AD33: 63617142 | AE33: 2868672 | AF33: 11419953 | AG33: 14288625 | AH33: 4606975 | AI33: 2000000 | AJ33: 38185 | AK33: 122584 | AL33: 9575191 | AM33: 2393798 | AN33: -1839231 | AO33: 4233029 | AP33: 1433238801 | AQ33: 1338246887 | AR33: 3762652 | AS33: 9232976 | AT33: 668225 | AU33: 1479 | AV33: 3679 | AW33: 88236543 | AX33: 54920583 | AY33: 3715759 | AZ33: 3737666 | BA33: 2231536 | BB33: 0 | BD33: 0.6640654 | BE33: 0.34956325 | BF33: -0.76833175 | BG33: -0.19208296 | BH33: 1.8838065 | BI33: 0.38737233 | BJ33: 0 | BL33: not reported | BP33: 2.6252792 | BQ33: 0.40201142 | BR33: 2315.6671 | BS33: 1506.1949 | BT33: 637.84574 | BU33: 780.97559 | BV33: 2422.2114 | BW33: 378.29056
B34: armstrong-c | C34: 2024 | D34: armstrong-c:2024 | E34: 5899 | F34: 5899 | G34: FALSE | H34: 11115894 | I34: 4088217 | J34: 4394163 | K34: 1682252 | L34: 789849 | M34: 113288 | N34: 9320354 | O34: 9013631 | P34: 1439707 | Q34: 7573924 | R34: 935874 | S34: 1685017 | T34: 805574 | U34: 1077010 | V34: 933964 | W34: 1087166 | X34: 2102263 | Y34: 2359607 | Z34: 31010513 | AA34: 34079923 | AB34: 24205820 | AC34: 9874103 | AD34: 65719405 | AE34: 630658 | AF34: 13769122 | AG34: 14399780 | AH34: 4475220 | AI34: 0 | AJ34: 113154 | AK34: 235639 | AL34: 9889728 | AM34: 2472432 | AN34: 348793 | AO34: 2123639 | AP34: 1466099467 | AQ34: 1358301900 | AR34: 4092935 | AS34: 9820375 | AT34: 674865 | AU34: 1594 | AV34: 4028 | AW34: 90054897 | AX34: 55794845 | AY34: 2359607 | AZ34: 3992281.7 | BA34: 211677072 | BB34: 3694000 | BC34: 0 | BD34: 0.83847093 | BE34: 0.18912226 | BF34: 0.14107284 | BG34: 0.03526821 | BH34: 1.9012311 | BI34: 0.39074934 | BJ34: 2.3871486 | BK34: 0.017649307 | BL34: plausible | BM34: 3436794.6 | BN34: 1.1616294 | BO34: 0 | BP34: 2.7917171 | BQ34: 0.39572989 | BR34: 1884.3692 | BS34: 1527.993 | BT34: 693.8354 | BU34: 758.64045 | BV34: 2441.0544 | BW34: 35883.552
B35: ashcroft-v | C35: 2019 | D35: ashcroft-v:2019 | E35: 1575 | F35: 1575 | G35: FALSE | H35: 8049701 | I35: 1500680 | J35: 1096114 | K35: 5363783 | L35: 58934 | M35: 30190 | N35: 2655728 | O35: 3102891 | P35: 287435 | Q35: 2815456 | R35: 209913 | S35: 154943 | T35: 533534 | U35: 734365 | V35: 406058 | W35: 406032 | X35: 4946810 | Y35: 5620488 | Z35: 3712613 | AA35: 5426102 | AB35: 1773084 | AC35: 3653018 | AD35: 18376714 | AE35: 3076747 | AF35: 2056794 | AG35: 5133541 | AH35: 1367789 | AI35: 1000000 | AJ35: 14401 | AK35: 9393 | AL35: 3318457 | AM35: 829614 | AN35: 23794 | AO35: 499055 | AP35: 173776722 | AQ35: 151472725 | AR35: 1481757.2 | AS35: 3750752.4 | AT35: 211179 | AU35: 1068.3334 | AV35: 3239.5107 | AW35: 29027326 | AX35: 14610962 | AY35: 5620488 | AZ35: 5620488 | BA35: 60788848 | BB35: 913775 | BC35: 1 | BD35: 0.32991635 | BE35: 0.61453338 | BF35: 0.028680808 | BG35: 0.0071701999 | BH35: 1.8233426 | BI35: 0.69786956 | BJ35: 2.5375166 | BK35: 0.017432067 | BL35: plausible | BM35: 729371.09 | BP35: 8.5267876 | BQ35: 0.32978235 | BR35: 5110.9213 | BS35: 1970.0895 | BT35: 940.79822 | BU35: 868.43746 | BV35: 3259.3911 | BW35: 38596.094
B36: ashcroft-v | C36: 2020 | D36: ashcroft-v:2020 | E36: 1559 | F36: 1559 | G36: FALSE | H36: 4856334 | I36: 1497379 | J36: 1220298 | K36: 2092640 | L36: 46017 | M36: 0 | N36: 2763694 | O36: 3369144 | P36: 514509 | Q36: 2854635 | R36: 233492 | S36: 119714 | T36: 563896 | U36: 760340 | V36: 563722 | W36: 342585 | X36: 1487190 | Y36: 1138310 | Z36: 4702696 | AA36: 5338926 | AB36: 734326 | AC36: 4604600 | AD36: 19863904 | AE36: 2375434 | AF36: 2253707 | AG36: 4629141 | AH36: 0 | AI36: 0 | AJ36: 1367789 | AK36: 6940 | AL36: 3440616 | AM36: 860154 | AN36: 1374729 | AO36: -841158 | AP36: 198718377 | AQ36: 175339500 | AR36: 1481774 | AS36: 3879288 | AT36: 244109 | AU36: 1067 | AV36: 3428 | AW36: 30147407 | AX36: 15234763 | AY36: 1138310 | AZ36: 3379399 | BA36: 63836171 | BB36: 1317759 | BC36: 1 | BD36: 0.56909059 | BE36: 0.30623717 | BF36: 1.5982359 | BG36: 0.39955897 | BH36: 1.6216227 | BI36: 0.51275442 | BJ36: 2.1583501 | BK36: 0.020992727 | BL36: plausible | BM36: 1110490.6 | BP36: 7.4566531 | BQ36: 0.31126021 | BR36: 3115.0314 | BS36: 2161.093 | BT36: 950.4644 | BU36: 0 | BV36: 2969.3015 | BW36: 40946.87
B37: ashcroft-v | C37: 2021 | D37: ashcroft-v:2021 | E37: 1578 | F37: 1578 | G37: FALSE | H37: 5168508 | I37: 1541797 | J37: 1543690 | K37: 2058671 | L37: 24350 | M37: 0 | N37: 3109837 | O37: 3725708 | P37: 577109 | Q37: 3148599 | R37: 397811 | S37: 218257 | T37: 643895 | U37: 759152 | V37: 496743 | W37: 354369 | X37: 1442800 | Y37: 2444573 | Z37: 4101426 | AA37: 4952642 | AB37: 782121 | AC37: 4170521 | AD37: 21306704 | AE37: 2103693 | AF37: 2100786 | AG37: 4204479 | AH37: 0 | AI37: 0 | AJ37: 0 | AK37: 0 | AL37: 3839920 | AM37: 959980 | AN37: 0 | AO37: 959980 | AP37: 209868202 | AQ37: 185023200 | AR37: 1538027 | AS37: 4057092 | AT37: 254583 | AU37: 1083 | AV37: 3486 | AW37: 32543980 | AX37: 17102225 | AY37: 2444573 | AZ37: 3067790.3 | BA37: 1614600 | BB37: 0 | BD37: 0.6016895 | BE37: 0.27915213 | BF37: 0 | BG37: 0 | BH37: 1.3353492 | BI37: 0.49925847 | BJ37: 0 | BL37: not reported | BP37: 7.3285376 | BQ37: 0.31067126 | BR37: 3275.3536 | BS37: 2361.0317 | BT37: 974.66857 | BU37: 0 | BV37: 2664.4354 | BW37: 1023.1939
B38: ashcroft-v | C38: 2022 | D38: ashcroft-v:2022 | E38: 1703 | F38: 1703 | G38: FALSE | H38: 5149783 | I38: 1733372 | J38: 1434374 | K38: 1890445 | L38: 91592 | M38: 0 | N38: 3259338 | O38: 3900278 | P38: 613595 | Q38: 3286683 | R38: 339464 | S38: 195138 | T38: 695142 | U38: 863101 | V38: 533644 | W38: 375849 | X38: 1249505 | Y38: 1161195 | Z38: 4774880 | AA38: 5479833 | AB38: 622241 | AC38: 4857592 | AD38: 22556209 | AE38: 2574997 | AF38: 2331387 | AG38: 4906384 | AH38: 0 | AI38: 0 | AJ38: 0 | AK38: 0 | AL38: 3800338 | AM38: 950085 | AN38: 0 | AO38: 950085 | AP38: 279483816 | AQ38: 243947825 | AR38: 1733258 | AS38: 4377423 | AT38: 341122 | AU38: 1139 | AV38: 3659 | AW38: 33705175 | AX38: 17649825 | AY38: 1161195 | AZ38: 1581359.3 | BA38: 66458816 | BB38: 1252587 | BC38: 1 | BD38: 0.63290783 | BE38: 0.24263255 | BF38: 0 | BG38: 0 | BH38: 1.4928072 | BI38: 0.50566581 | BJ38: 2.0315811 | BK38: 0.019418583 | BL38: plausible | BM38: 1246568 | BN38: 1.2685704 | BO38: 0 | BP38: 6.20164 | BQ38: 0.31128724 | BR38: 3023.9477 | BS38: 2290.2396 | BT38: 1017.7675 | BU38: 0 | BV38: 2881.0241 | BW38: 39024.554
B39: ashcroft-v | C39: 2023 | D39: ashcroft-v:2023 | E39: 1747 | F39: 1747 | G39: FALSE | H39: 6611025 | I39: 1923138 | J39: 1491558 | K39: 2910147 | L39: 286182 | M39: 0 | N39: 3700878 | O39: 4135489 | P39: 657687 | Q39: 3477802 | R39: 327659 | S39: 181017 | T39: 752426 | U39: 936163 | V39: 555258 | W39: 449486 | X39: 2475536 | Y39: 2126277 | Z39: 5560641 | AA39: 6651875 | AB39: 993471 | AC39: 5658404 | AD39: 25031747 | AE39: 3312530 | AF39: 2608310 | AG39: 5920840 | AH39: 0 | AI39: 0 | AJ39: 0 | AK39: 0 | AL39: 4115878 | AM39: 1028970 | AN39: 0 | AO39: 1028970 | AP39: 332212931 | AQ39: 287196000 | AR39: 1915444 | AS39: 4753246 | AT39: 399671 | AU39: 1167 | AV39: 3836 | AW39: 36024497 | AX39: 19343733 | AY39: 2126277 | AZ39: 1910681.7 | BA39: 69601080 | BB39: 1365021 | BC39: 1 | BD39: 0.55980396 | BE39: 0.3744557 | BF39: 0 | BG39: 0 | BH39: 1.7024661 | BI39: 0.50914381 | BJ39: 2.0248517 | BK39: 0.020576459 | BL39: plausible | BM39: 1331718.6 | BN39: 1.4347488 | BO39: 0 | BP39: 5.7657118 | BQ39: 0.30422315 | BR39: 3784.2158 | BS39: 2367.1946 | BT39: 1096.419 | BU39: 0 | BV39: 3389.1471 | BW39: 39840.343
B40: ashcroft-v | C40: 2024 | D40: ashcroft-v:2024 | E40: 1747 | F40: 1747 | G40: FALSE | H40: 5144200 | I40: 2066172 | J40: 1366509 | K40: 1378604 | L40: 332915 | M40: 0 | N40: 3765596 | O40: 4448637 | P40: 713673 | Q40: 3734964 | R40: 426216 | S40: 190606 | T40: 753640 | U40: 959858 | V40: 582012 | W40: 470428 | X40: 695563 | Y40: 316166 | Z40: 7284473 | AA40: 7884265 | AB40: 1238117 | AC40: 6646148 | AD40: 25727310 | AE40: 3761212 | AF40: 3019872 | AG40: 6781084 | AH40: 0 | AI40: 0 | AJ40: 0 | AK40: 0 | AL40: 4218896 | AM40: 1054724 | AN40: 0 | AO40: 1054724 | AP40: 320788886 | AQ40: 267710975 | AR40: 2028487 | AS40: 4891660 | AT40: 368292 | AU40: 1200 | AV40: 3783 | AW40: 36340661 | AX40: 18946226 | AY40: 316166 | AZ40: 1201212.7 | BA40: 69731911 | BB40: 4170174 | BC40: 1 | BD40: 0.73200809 | BE40: 0.13521306 | BF40: 0 | BG40: 0 | BH40: 1.8155688 | BI40: 0.5062143 | BJ40: 1.9717549 | BK40: 0.061549612 | BL40: plausible | BM40: 1407188.3 | BN40: 0.85362613 | BO40: 205975.6 | BP40: 6.3234329 | BQ40: 0.31720856 | BR40: 2944.5907 | BS40: 2546.4436 | BT40: 1161.1259 | BU40: 0 | BV40: 3881.5592 | BW40: 39915.232
B41: barriere-d | C41: 2019 | D41: barriere-d:2019 | E41: 1867 | F41: 1867 | G41: FALSE | H41: 2908432 | I41: 940609 | J41: 848310 | K41: 473603 | L41: 45032 | M41: 0 | N41: 2434829 | O41: 3372426 | P41: 710599 | Q41: 2661827 | R41: 637964 | S41: 186198 | T41: 433229 | U41: 119043 | V41: 651432 | W41: 237109 | X41: -463994 | Y41: 475725 | Z41: 3325984 | AA41: 4021069 | AB41: 1229032 | AC41: 2792037 | AD41: 29449472 | AE41: 1219131 | AF41: 1604027 | AG41: 2823158 | AH41: 0 | AI41: 0 | AJ41: 0 | AK41: 0 | AL41: 2286839 | AM41: 571710 | AN41: 0 | AO41: 571710 | AP41: 212805907 | AQ41: 190687000 | AR41: 876600.73 | AS41: 1882428.6 | AT41: 217826 | AU41: 751.40821 | AV41: 1584.8475 | AW41: 32935761 | AX41: 26626315 | AY41: 475725 | AZ41: 475725 | BA41: 4945629 | BB41: 0 | BD41: 0.83716209 | BE41: -0.15953407 | BF41: 0 | BG41: 0 | BH41: 1.0606091 | BI41: 0.2254168 | BJ41: 0 | BL41: not reported | BP41: 4.11925 | BQ41: 0.47412019 | BR41: 1557.8104 | BS41: 1806.3342 | BT41: 469.52369 | BU41: 0 | BV41: 1512.136 | BW41: 2648.9711
B42: barriere-d | C42: 2020 | D42: barriere-d:2020 | E42: 1881 | F42: 1881 | G42: FALSE | H42: 3418452 | I42: 928923 | J42: 1204612 | K42: 1256795 | L42: 28122 | M42: 0 | N42: 2161657 | O42: 2884071 | P42: 601133 | Q42: 2282938 | R42: 631362 | S42: 146394 | T42: 359055 | U42: 148178 | V42: 571706 | W42: 233219 | X42: 534381 | Y42: 614824 | Z42: 3577633 | AA42: 4295222 | AB42: 1113242 | AC42: 3181980 | AD42: 29983853 | AE42: 1866869 | AF42: 1476979 | AG42: 3343848 | AH42: 0 | AI42: 0 | AJ42: 0 | AK42: 0 | AL42: 2618085 | AM42: 654521 | AN42: 0 | AO42: 654521 | AP42: 235889980 | AQ42: 212118312 | AR42: 876600 | AS42: 1879909 | AT42: 242693 | AU42: 759 | AV42: 1652 | AW42: 33550585 | AX42: 26640005 | AY42: 614824 | AZ42: 545274.5 | BA42: 4945629 | BB42: 0 | BD42: 0.63234967 | BE42: 0.15632251 | BF42: 0 | BG42: 0 | BH42: 1.4647126 | BI42: 0.24158681 | BJ42: 0 | BL42: not reported | BP42: 3.7161392 | BQ42: 0.4594431 | BR42: 1817.3589 | BS42: 1533.2648 | BT42: 466.02871 | BU42: 0 | BV42: 1777.697 | BW42: 2629.2552
B43: barriere-d | C43: 2021 | D43: barriere-d:2021 | E43: 1892 | F43: 1892 | G43: FALSE | H43: 4245482 | I43: 986547 | J43: 2107277 | K43: 1120383 | L43: 31275 | M43: 0 | N43: 3125099 | O43: 3677646 | P43: 634482 | Q43: 3043164 | R43: 832340 | S43: 283810 | T43: 415909 | U43: 320143 | V43: 655449 | W43: 297261 | X43: 567836 | Y43: 1066274 | Z43: 3775238 | AA43: 4356925 | AB43: 913126 | AC43: 3443799 | AD43: 30551689 | AE43: 1270709 | AF43: 2209183 | AG43: 3479892 | AH43: 0 | AI43: 0 | AJ43: 0 | AK43: 0 | AL43: 3588649 | AM43: 897162 | AN43: 0 | AO43: 897162 | AP43: 256203281 | AQ43: 230623600 | AR43: 920429 | AS43: 2033809 | AT43: 262338 | AU43: 804 | AV43: 1725 | AW43: 34616859 | AX43: 27071797 | AY43: 1066274 | AZ43: 718941 | BA43: 4945629 | BB43: 0 | BD43: 0.73609993 | BE43: 0.13375066 | BF43: 0 | BG43: 0 | BH43: 1.1435112 | BI43: 0.25428882 | BJ43: 0 | BL43: not reported | BP43: 3.592573 | BQ43: 0.46608696 | BR43: 2243.9123 | BS43: 1943.7875 | BT43: 486.48467 | BU43: 0 | BV43: 1839.2664 | BW43: 2613.9688
B44: barriere-d | C44: 2022 | D44: barriere-d:2022 | E44: 1913 | F44: 1913 | G44: FALSE | H44: 3457229 | I44: 1043497 | J44: 1330327 | K44: 1046850 | L44: 36555 | M44: 0 | N44: 2410379 | O44: 3507323 | P44: 647862 | Q44: 2859461 | R44: 1098552 | S44: 158645 | T44: 367146 | U44: 332483 | V44: 429542 | W44: 250932 | X44: -50094 | Y44: 851412 | Z44: 4163928 | AA44: 4861370 | AB44: 1683965 | AC44: 3177405 | AD44: 30618903 | AE44: 1103675 | AF44: 2122573 | AG44: 3226248 | AH44: 0 | AI44: 0 | AJ44: 0 | AK44: 0 | AL44: 2984454 | AM44: 746114 | AN44: 0 | AO44: 746114 | AP44: 339210558 | AQ44: 308726300 | AR44: 966450 | AS44: 2192279 | AT44: 349344 | AU44: 865 | AV44: 1885 | AW44: 35468271 | AX44: 27392655 | AY44: 851412 | AZ44: 844170 | BA44: 4945629 | BB44: 0 | BD44: 0.69719969 | BE44: -0.014489639 | BF44: 0 | BG44: 0 | BH44: 1.1282714 | BI44: 0.26457788 | BJ44: 0 | BL44: not reported | BP44: 2.8491153 | BQ44: 0.45888594 | BR44: 1807.229 | BS44: 1833.4151 | BT44: 505.20125 | BU44: 0 | BV44: 1686.4861 | BW44: 2585.2739
B45: barriere-d | C45: 2023 | D45: barriere-d:2023 | E45: 1982 | F45: 1982 | G45: FALSE | H45: 5961751 | I45: 1082241 | J45: 1256133 | K45: 3569215 | L45: 53037 | M45: 1125 | N45: 2391411 | O45: 3480129 | P45: 623420 | Q45: 2856709 | R45: 1100173 | S45: 296195 | T45: 458255 | U45: 209153 | V45: 315242 | W45: 219422 | X45: 2481622 | Y45: 1934899 | Z45: 4706918 | AA45: 5665884 | AB45: 1233539 | AC45: 4432345 | AD45: 33100525 | AE45: 3673779 | AF45: 891584 | AG45: 4565363 | AH45: 0 | AI45: 0 | AJ45: 0 | AK45: 0 | AL45: 2822411 | AM45: 705603 | AN45: 0 | AO45: 705603 | AP45: 395092396 | AQ45: 360253400 | AR45: 1012148 | AS45: 2306262 | AT45: 404871 | AU45: 904 | AV45: 2001 | AW45: 37461592 | AX45: 28614079 | AY45: 1934899 | AZ45: 1284195 | BA45: 4945629 | BB45: 0 | BD45: 0.40112561 | BE45: 0.41625724 | BF45: 0 | BG45: 0 | BH45: 1.5981197 | BI45: 0.27209752 | BJ45: 0 | BL45: not reported | BP45: 2.5618008 | BQ45: 0.45177411 | BR45: 3007.947 | BS45: 1755.8673 | BT45: 510.67003 | BU45: 0 | BV45: 2303.4122 | BW45: 2495.2719
B46: barriere-d | C46: 2024 | D46: barriere-d:2024 | E46: 1982 | F46: 1982 | G46: FALSE | K46: 0 | AF46: 0 | AP46: 384895672 | AQ46: 346276000 | AR46: 1062194 | AS46: 3093354 | AT46: 384326 | AU46: 910 | AV46: 3251 | AZ46: 1393155.5 | BL46: not reported | BP46: 2.7596933 | BQ46: 0.27991387 | BT46: 535.92028
B47: belcarra-v | C47: 2019 | D47: belcarra-v:2019 | E47: 693 | F47: 693 | G47: FALSE | H47: 2055620 | I47: 989977 | J47: 515054 | K47: 444807 | L47: 64676 | M47: 0 | N47: 1610813 | O47: 1912899 | P47: 306282 | Q47: 1606617 | R47: 697702 | S47: 73830 | T47: 280310 | U47: 0 | V47: 345137 | W47: 0 | X47: 142721 | Y47: 74808 | Z47: 1912134 | AA47: 2062667 | AB47: 4187710 | AC47: -2125043 | AD47: 8987700 | AE47: 353111 | AF47: 1164717 | AG47: 1517828 | AH47: 3599016 | AI47: 0 | AJ47: 106645 | AK47: 128799 | AL47: 1839001 | AM47: 459750 | AN47: 235444 | AO47: 224306 | AP47: 653730300 | AQ47: 645174700 | AR47: 734048.79 | AS47: 2523749.5 | AT47: 1491539 | AU47: 1673.3725 | AV47: 6549.2054 | AW47: 14264988 | AX47: 11068888 | AY47: 74808 | AZ47: 74808 | BA47: 341987 | BB47: 0 | BD47: 0.78361419 | BE47: 0.069429661 | BF47: 0.5121131 | BG47: 0.12802821 | BH47: 0.94473543 | BI47: 0.2295554 | BJ47: 0 | BL47: not reported | BP47: 1.1228618 | BQ47: 0.25550772 | BR47: 2966.2626 | BS47: 2760.316 | BT47: 1059.2335 | BU47: 5193.3853 | BV47: 2190.228 | BW47: 493.48773
B48: belcarra-v | C48: 2020 | D48: belcarra-v:2020 | E48: 673 | F48: 673 | G48: FALSE | H48: 2485811 | I48: 1097018 | J48: 536132 | K48: 782959 | L48: 69702 | M48: 0 | N48: 1702852 | O48: 2080419 | P48: 312035 | Q48: 1768384 | R48: 754908 | S48: 96440 | T48: 337542 | U48: 5703 | V48: 311791 | W48: 0 | X48: 405392 | Y48: 47439 | Z48: 2420056 | AA48: 2531737 | AB48: 3962107 | AC48: -1430370 | AD48: 9401193 | AE48: 543759 | AF48: 1502344 | AG48: 2046103 | AH48: 3449202 | AI48: 0 | AJ48: 106645 | AK48: 128799 | AL48: 1925504 | AM48: 481376 | AN48: 235444 | AO48: 245932 | AP48: 592141000 | AQ48: 584525700 | AR48: 847645 | AS48: 2648602 | AT48: 1355482 | AU48: 1939 | AV48: 6943 | AW48: 14312427 | AX48: 10804292 | AY48: 47439 | AZ48: 61123.5 | BA48: 363330 | BB48: 0 | BD48: 0.68502875 | BE48: 0.16308239 | BF48: 0.48910623 | BG48: 0.12227656 | BH48: 1.1570468 | BI48: 0.25149549 | BJ48: 0 | BL48: not reported | BP48: 1.4314918 | BQ48: 0.27927409 | BR48: 3693.627 | BS48: 3091.2615 | BT48: 1259.5022 | BU48: 5125.1144 | BV48: 3040.2719 | BW48: 539.86627
B49: belcarra-v | C49: 2021 | D49: belcarra-v:2021 | E49: 678 | F49: 678 | G49: FALSE | H49: 2339581 | I49: 1172197 | J49: 539309 | K49: 556343 | L49: 71732 | M49: 0 | N49: 1783238 | O49: 2124393 | P49: 304665 | Q49: 1819728 | R49: 698404 | S49: 124771 | T49: 318515 | U49: 91 | V49: 397884 | W49: 0 | X49: 215188 | Y49: 98590 | Z49: 2749046 | AA49: 2935156 | AB49: 3899498 | AC49: -964342 | AD49: 9616381 | AE49: 409105 | AF49: 1947914 | AG49: 2357019 | AH49: 3301843 | AI49: 0 | AJ49: 106645 | AK49: 128799 | AL49: 2002960 | AM49: 500740 | AN49: 235444 | AO49: 265296 | AP49: 594584900 | AQ49: 586965100 | AR49: 913783 | AS49: 2854400 | AT49: 1366808 | AU49: 2099 | AV49: 7462 | AW49: 14351647 | AX49: 10561205 | AY49: 98590 | AZ49: 73612.333 | BA49: 21936318 | BB49: 0 | BC49: 0 | BD49: 0.762204 | BE49: 0.091977153 | BF49: 0.47019212 | BG49: 0.11754803 | BH49: 1.295259 | BI49: 0.27031472 | BJ49: 1.5408995 | BK49: 0 | BL49: reported need implausible | BM49: 469458.15 | BN49: 0.15680276 | BO49: 395845.82 | BP49: 1.5368419 | BQ49: 0.28129188 | BR49: 3450.7094 | BS49: 3133.323 | BT49: 1347.7625 | BU49: 4869.9749 | BV49: 3476.4292 | BW49: 32354.451
B50: belcarra-v | C50: 2022 | D50: belcarra-v:2022 | E50: 716 | F50: 716 | G50: FALSE | H50: 2552114 | I50: 1219691 | J50: 666282 | K50: 551651 | L50: 114490 | M50: 0 | N50: 2000463 | O50: 2221815 | P50: 303456 | Q50: 1918359 | R50: 652249 | S50: 99405 | T50: 377605 | U50: 978 | V50: 475732 | W50: 0 | X50: 330299 | Y50: 248242 | Z50: 3098578 | AA50: 3250786 | AB50: 3848884 | AC50: -598098 | AD50: 9946680 | AE50: 416291 | AF50: 2174532 | AG50: 2590823 | AH50: 3150134 | AI50: 0 | AJ50: 106645 | AK50: 134045 | AL50: 2285494 | AM50: 571374 | AN50: 240690 | AO50: 330684 | AP50: 725673000 | AQ50: 715599700 | AR50: 966671 | AS50: 3065537 | AT50: 1663056 | AU50: 2213 | AV50: 7998 | AW50: 14592988 | AX50: 10505991 | AY50: 248242 | AZ50: 131423.67 | BA50: 23284509 | BB50: 1132100 | BC50: 0 | BD50: 0.78384547 | BE50: 0.12942173 | BF50: 0.42124773 | BG50: 0.10531202 | BH50: 1.3505413 | BI50: 0.28703888 | BJ50: 1.6104248 | BK50: 0.049372002 | BL50: plausible | BM50: 488693.07 | BN50: 0.26892885 | BO50: 357269.41 | BP50: 1.3321028 | BQ50: 0.27669417 | BR50: 3564.405 | BS50: 3103.0936 | BT50: 1350.0992 | BU50: 4399.6285 | BV50: 3618.4679 | BW50: 32520.264
B51: belcarra-v | C51: 2023 | D51: belcarra-v:2023 | E51: 729 | F51: 729 | G51: FALSE | H51: 3618533 | I51: 1290160 | J51: 769436 | K51: 1329802 | L51: 229135 | M51: 0 | N51: 2288731 | O51: 2507634 | P51: 306857 | Q51: 2200777 | R51: 686336 | S51: 106756 | T51: 376896 | U51: 17164 | V51: 547126 | W51: 0 | X51: 1110899 | Y51: 295603 | Z51: 4088372 | AA51: 4328787 | AB51: 3735373 | AC51: 593414 | AD51: 11057579 | AE51: 402658 | AF51: 3210860 | AG51: 3613518 | AH51: 2984969 | AI51: 0 | AJ51: 119002 | AK51: 150561 | AL51: 2501568 | AM51: 625392 | AN51: 269563 | AO51: 355829 | AP51: 795593200 | AQ51: 785128800 | AR51: 995667 | AS51: 3344179 | AT51: 1825005 | AU51: 2282 | AV51: 8763 | AW51: 14734961 | AX51: 10429030 | AY51: 295603 | AZ51: 214145 | BA51: 21885401 | BB51: 575737 | BC51: 1 | BD51: 0.63250245 | BE51: 0.30700259 | BF51: 0.43103046 | BG51: 0.10775761 | BH51: 1.6419283 | BI51: 0.29958112 | BJ51: 1.4974852 | BK51: 0.026749088 | BL51: plausible | BM51: 459513.81 | BN51: 0.46602517 | BO51: 245368.81 | BP51: 1.2514775 | BQ51: 0.2604131 | BR51: 4963.6941 | BS51: 3439.8272 | BT51: 1365.7984 | BU51: 4094.6077 | BV51: 4956.8148 | BW51: 30021.126
B52: belcarra-v | C52: 2024 | D52: belcarra-v:2024 | E52: 729 | F52: 729 | G52: FALSE | H52: 3242083 | I52: 1390116 | J52: 807593 | K52: 783426 | L52: 260948 | M52: 0 | N52: 2458657 | O52: 2537176 | P52: 295396 | Q52: 2241780 | R52: 718784 | S52: 127284 | T52: 421144 | U52: 51 | V52: 571507 | W52: 0 | X52: 704907 | Y52: 612408 | Z52: 4276014 | AA52: 4664205 | AB52: 3723227 | AC52: 940978 | AD52: 11720080 | AE52: 395154 | AF52: 3400333 | AG52: 3795487 | AH52: 2813955 | AI52: 0 | AJ52: 119002 | AK52: 150561 | AL52: 2695245 | AM52: 673811 | AN52: 269563 | AO52: 404248 | AP52: 846202200 | AQ52: 835188800 | AR52: 1099236 | AS52: 3734016 | AT52: 1941000 | AU52: 2519 | AV52: 9789 | AW52: 15322061 | AX52: 10738548 | AY52: 612408 | AZ52: 385417.67 | BA52: 22487952 | BB52: 601923 | BC52: 1 | BD52: 0.7583572 | BE52: 0.21742411 | BF52: 0.40005729 | BG52: 0.10001428 | BH52: 1.6930685 | BI52: 0.31332716 | BJ52: 1.4898575 | BK52: 0.027618226 | BL52: plausible | BM52: 440097.95 | BN52: 0.87575428 | BO52: 54680.285 | BP52: 1.2990229 | BQ52: 0.25732966 | BR52: 4447.3018 | BS52: 3480.3512 | BT52: 1507.8683 | BU52: 3860.0206 | BV52: 5206.4294 | BW52: 30847.671
B53: bowen-island-d | C53: 2019 | D53: bowen-island-d:2019 | E53: 3957 | F53: 3957 | G53: FALSE | H53: 10338020 | I53: 6491675 | J53: 1703683 | K53: 1091418 | L53: 338819 | M53: 571387 | N53: 8675215 | O53: 9054894 | P53: 1639294 | Q53: 7415600 | R53: 1624763 | S53: 806737 | T53: 873484 | U53: 1202194 | V53: 823317 | W53: 207489 | X53: 1283126 | Y53: 3774804 | Z53: 12603968 | AA53: 13499693 | AB53: 6215643 | AC53: 7284050 | AD53: 68215440 | AE53: 3098772 | AF53: 6228449 | AG53: 9327221 | AH53: 1979397 | AI53: 0 | AJ53: 78649 | AK53: 103184 | AL53: 9080973 | AM53: 2270243 | AN53: 181833 | AO53: 2088410 | AP53: 2547973100 | AQ53: 2486508744 | AR53: 5379364.2 | AS53: 11261432 | AT53: 1151773 | AU53: 2426.3365 | AV53: 6187.6952 | AW53: 84716086 | AX53: 60867616 | AY53: 3774804 | AZ53: 3774804 | BA53: 26964255 | BB53: 0 | BD53: 0.83915634 | BE53: 0.12411719 | BF53: 0.080094069 | BG53: 0.020023515 | BH53: 1.2577837 | BI53: 0.41294743 | BJ53: 0 | BL53: not reported | BP53: 2.1112327 | BQ53: 0.39212282 | BR53: 2612.5903 | BS53: 2288.323 | BT53: 1359.4552 | BU53: 500.22669 | BV53: 2357.1446 | BW53: 6814.3177
B54: bowen-island-d | C54: 2020 | D54: bowen-island-d:2020 | E54: 3982 | F54: 3982 | G54: FALSE | H54: 19059642 | I54: 7184031 | J54: 1741649 | K54: 5401368 | L54: 446678 | M54: 3206120 | N54: 10452154 | O54: 9575778 | P54: 1752443 | Q54: 7823335 | R54: 1710843 | S54: 977738 | T54: 822801 | U54: 1134378 | V54: 686617 | W54: 173531 | X54: 9483864 | Y54: 10299644 | Z54: 14224540 | AA54: 16293281 | AB54: 7849637 | AC54: 8443644 | AD54: 77699302 | AE54: 7633964 | AF54: 5280127 | AG54: 12914091 | AH54: 4404493 | AI54: 2533000 | AJ54: 107904 | AK54: 97455 | AL54: 10070912 | AM54: 2517728 | AN54: 205359 | AO54: 2312369 | AP54: 2497690287 | AQ54: 2436053669 | AR54: 5679096 | AS54: 12228283 | AT54: 1095357 | AU54: 2485 | AV54: 6673 | AW54: 94612148 | AX54: 69234134 | AY54: 10299644 | AZ54: 7037224 | BA54: 37121494 | BB54: 0 | BD54: 0.54839194 | BE54: 0.49758878 | BF54: 0.081565205 | BG54: 0.020391301 | BH54: 1.6507143 | BI54: 0.44142851 | BJ54: 0 | BL54: not reported | BP54: 2.2737391 | BQ54: 0.37239622 | BR54: 4786.4495 | BS54: 2404.7659 | BT54: 1426.1919 | BU54: 1106.1007 | BV54: 3243.1168 | BW54: 9322.324
B55: bowen-island-d | C55: 2021 | D55: bowen-island-d:2021 | E55: 4222 | F55: 4222 | G55: FALSE | H55: 12611421 | I55: 7880471 | J55: 2341288 | K55: 1648796 | L55: -8777 | M55: 293484 | N55: 10669141 | O55: 9817370 | P55: 1783825 | Q55: 8033545 | R55: 1889897 | S55: 731566 | T55: 956013 | U55: 1280156 | V55: 839832 | W55: 264819 | X55: 2794051 | Y55: 8694477 | Z55: 13679602 | AA55: 16263099 | AB55: 11936138 | AC55: 4326961 | AD55: 80493354 | AE55: 4980757 | AF55: 5242683 | AG55: 10223440 | AH55: 5839650 | AI55: 1500000 | AJ55: 109273 | AK55: 119957 | AL55: 10797615 | AM55: 2699404 | AN55: 229230 | AO55: 1992626 | AP55: 2806993675 | AQ55: 2744055757 | AR55: 6113091 | AS55: 13638462 | AT55: 1229648 | AU55: 2673 | AV55: 7003 | AW55: 102682648 | AX55: 76108664 | AY55: 8694477 | AZ55: 7589641.7 | BA55: 42018516 | BB55: 0 | BD55: 0.84599039 | BE55: 0.22154926 | BF55: 0.084918745 | BG55: 0.021229688 | BH55: 1.2725939 | BI55: 0.43805101 | BJ55: 0 | BL55: not reported | BP55: 2.1778072 | BQ55: 0.38169356 | BR55: 2987.0727 | BS55: 2325.289 | BT55: 1447.9135 | BU55: 1383.1478 | BV55: 2421.4685 | BW55: 9952.2776
B56: bowen-island-d | C56: 2022 | D56: bowen-island-d:2022 | E56: 4058 | F56: 4058 | G56: FALSE | H56: 16392421 | I56: 8610504 | J56: 2676343 | K56: 4005254 | L56: 29361 | M56: 741385 | N56: 11645782 | O56: 11253187 | P56: 2269137 | Q56: 8984050 | R56: 2311800 | S56: 895240 | T56: 1373171 | U56: 1051020 | V56: 982787 | W56: 292809 | X56: 5139234 | Y56: 11831732 | Z56: 15190833 | AA56: 18278199 | AB56: 18437862 | AC56: -159663 | AD56: 85632587 | AE56: 7903139 | AF56: 4557449 | AG56: 12460588 | AH56: 12499259 | AI56: 8335530 | AJ56: 1670774 | AK56: 270220 | AL56: 12192635 | AM56: 3048159 | AN56: 1940994 | AO56: 1107165 | AP56: 3499302362 | AQ56: 3424648332 | AR56: 6590362 | AS56: 15096935 | AT56: 1538776 | AU56: 2890 | AV56: 9529 | AW56: 113540736 | AX56: 85671258 | AY56: 11831732 | AZ56: 10275284 | BA56: 46195353 | BB56: 0 | BD56: 0.71043698 | BE56: 0.31351281 | BF56: 0.63677584 | BG56: 0.15919397 | BH56: 1.3869678 | BI56: 0.41382908 | BJ56: 0 | BL56: not reported | BP56: 1.883336 | BQ56: 0.30328471 | BR56: 4039.532 | BS56: 2773.087 | BT56: 1624.0419 | BU56: 3080.1525 | BV56: 3070.623 | BW56: 11383.774
B57: bowen-island-d | C57: 2023 | D57: bowen-island-d:2023 | E57: 4181 | F57: 4181 | G57: FALSE | H57: 26526833 | I57: 9575799 | J57: 2682468 | K57: 7745707 | L57: 838115 | M57: 5286238 | N57: 13494888 | O57: 11689500 | P57: 2037796 | Q57: 9651704 | R57: 2512741 | S57: 935032 | T57: 1432825 | U57: 1166349 | V57: 1187740 | W57: 307155 | X57: 14837333 | Y57: 15822610 | Z57: 13441689 | AA57: 17607518 | AB57: 16900609 | AC57: 706909 | AD57: 100469921 | AE57: 5430662 | AF57: 7696107 | AG57: 13126769 | AH57: 12072978 | AI57: 0 | AJ57: 418483 | AK57: 469860 | AL57: 13833090 | AM57: 3458273 | AN57: 888343 | AO57: 2224797 | AP57: 3723304179 | AQ57: 3629693444 | AR57: 7529985 | AS57: 16018026 | AT57: 1616039 | AU57: 3229 | AV57: 9073 | AW57: 129268267 | AX57: 99693494 | AY57: 15822610 | AZ57: 12116273 | BA57: 57006371 | BB57: 0 | BD57: 0.50872594 | BE57: 0.559333 | BF57: 0.25687475 | BG57: 0.064218696 | BH57: 1.3600468 | BI57: 0.40927203 | BJ57: 0 | BL57: not reported | BP57: 2.0223932 | BQ57: 0.35589111 | BR57: 6344.6144 | BS57: 2795.8622 | BT57: 1801.001 | BU57: 2887.5814 | BV57: 3139.6243 | BW57: 13634.626
B58: bowen-island-d | C58: 2024 | D58: bowen-island-d:2024 | E58: 4181 | F58: 4181 | G58: FALSE | H58: 16969581 | I58: 10598738 | J58: 2474238 | K58: 1903228 | L58: 796854 | M58: 1116385 | N58: 13949968 | O58: 12625661 | P58: 2166340 | Q58: 10459321 | R58: 2746924 | S58: 993444 | T58: 1628021 | U58: 1397447 | V58: 1280189 | W58: 274888 | X58: 4343920 | Y58: 7374422 | Z58: 15548768 | AA58: 18216037 | AB58: 18461318 | AC58: -245281 | AD58: 104813841 | AE58: 4529301 | AF58: 7765720 | AG58: 12295021 | AH58: 12088448 | AI58: 500805 | AJ58: 470045 | AK58: 471031 | AL58: 14416501 | AM58: 3604125 | AN58: 941076 | AO58: 2136898 | AP58: 3642927676 | AQ58: 3554253927 | AR58: 8245344 | AS58: 17662995 | AT58: 1605650 | AU58: 3593 | AV58: 10323 | AW58: 136397405 | AX58: 104896577 | AY58: 7374422 | AZ58: 11676255 | BA58: 268938616 | BB58: 3387250 | BC58: 0 | BD58: 0.8220573 | BE58: 0.25598275 | BF58: 0.26111081 | BG58: 0.065277698 | BH58: 1.1755085 | BI58: 0.42354032 | BJ58: 2.7820658 | BK58: 0.01637015 | BL58: plausible | BM58: 6026900.4 | BN58: 1.9373565 | BO58: 0 | BP58: 2.2633839 | BQ58: 0.34805774 | BR58: 4058.7374 | BS58: 3019.7706 | BT58: 1972.0985 | BU58: 2891.2815 | BV58: 2940.6891 | BW58: 64323.993
B59: burnaby-c | C59: 2019 | D59: burnaby-c:2019 | E59: 253007 | F59: 253007 | G59: FALSE | H59: 585922077 | I59: 303534244 | J59: 122498768 | K59: 30765664 | L59: 56666253 | M59: 16631761 | N59: 538524652 | O59: 472987764 | P59: 64961015 | Q59: 408026749 | R59: 75375997 | S59: 112906833 | T59: 24824679 | U59: 98924615 | V59: 36594428 | W59: 33279522 | X59: 112934313 | Y59: 132547977 | Z59: 1777692583 | AA59: 1986264886 | AB59: 375563778 | AC59: 1610701108 | AD59: 4527535054 | AE59: 251805492 | AF59: 1494731973 | AG59: 1746537465 | AH59: 0 | AI59: 0 | AJ59: 0 | AK59: 0 | AL59: 540804689 | AM59: 135201172 | AN59: 0 | AO59: 135201172 | AP59: 113987053052 | AQ59: 89985021125 | AR59: 2.7368482e+08 | AS59: 6.0258035e+08 | AT59: 1593082 | AU59: 2408.5807 | AV59: 5791.1153 | AW59: 4052634020 | AX59: 2911454589 | AY59: 132547977 | AZ59: 132547977 | BA59: 1783884301 | BB59: 0 | BD59: 0.91910627 | BE59: 0.1927463 | BF59: 0 | BG59: 0 | BH59: 4.2804484 | BI59: 0.50299926 | BJ59: 0 | BL59: not reported | BP59: 2.4010167 | BQ59: 0.41590964 | BR59: 2315.8335 | BS59: 1869.4651 | BT59: 1081.7283 | BU59: 0 | BV59: 6903.1191 | BW59: 7050.731
B60: burnaby-c | C60: 2020 | D60: burnaby-c:2020 | E60: 257926 | F60: 257926 | G60: FALSE | H60: 619355536 | I60: 306603981 | J60: 107363048 | K60: 28051301 | L60: 51984393 | M60: 36763786 | N60: 554540449 | O60: 480314323 | P60: 68623357 | Q60: 411690966 | R60: 68517509 | S60: 120277532 | T60: 27207923 | U60: 90037700 | V60: 38124363 | W60: 35957653 | X60: 139041213 | Y60: 169998727 | Z60: 1884996964 | AA60: 2114020438 | AB60: 461560977 | AC60: 1652459461 | AD60: 4666576267 | AE60: 1055664231 | AF60: 602610917 | AG60: 1658275148 | AH60: 0 | AI60: 0 | AJ60: 0 | AK60: 0 | AL60: 523093496 | AM60: 130773374 | AN60: 0 | AO60: 130773374 | AP60: 108071587951 | AQ60: 83173795836 | AR60: 282667028 | AS60: 557168476 | AT60: 1441032 | AU60: 2455 | AV60: 5863 | AW60: 4202326453 | AX60: 3008301119 | AY60: 169998727 | AZ60: 151273352 | BA60: 1866266569 | BB60: 0 | BD60: 0.89535076 | BE60: 0.22449337 | BF60: 0 | BG60: 0 | BH60: 4.027961 | BI60: 0.51112788 | BJ60: 0 | BL60: not reported | BP60: 2.6155536 | BQ60: 0.41872761 | BR60: 2401.2916 | BS60: 1862.2175 | BT60: 1095.923 | BU60: 0 | BV60: 6429.2671 | BW60: 7235.6667
B61: burnaby-c | C61: 2021 | D61: burnaby-c:2021 | E61: 260918 | F61: 260918 | G61: FALSE | H61: 954515394 | I61: 321606805 | J61: 116849718 | K61: 21644029 | L61: 42263976 | M61: 367774525 | N61: 565096840 | O61: 522157286 | P61: 73634140 | Q61: 448523146 | R61: 83604230 | S61: 131097541 | T61: 26283514 | U61: 98693477 | V61: 39818071 | W61: 38034244 | X61: 432358108 | Y61: 242200447 | Z61: 2021565206 | AA61: 2348510551 | AB61: 431421246 | AC61: 1917089305 | AD61: 5098934375 | AE61: 1320349258 | AF61: 602550525 | AG61: 1922899783 | AH61: 0 | AI61: 0 | AJ61: 0 | AK61: 0 | AL61: 544358576 | AM61: 136089644 | AN61: 0 | AO61: 136089644 | AP61: 111127483213 | AQ61: 87173209398 | AR61: 292497127 | AS61: 640641213 | AT61: 1523022 | AU61: 2590 | AV61: 6132 | AW61: 4425659340 | AX61: 3176034592 | AY61: 242200447 | AZ61: 1.8158238e+08 | BA61: 1961246269 | BB61: 0 | BD61: 0.59202486 | BE61: 0.45296085 | BF61: 0 | BG61: 0 | BH61: 4.2871807 | BI61: 0.50706789 | BJ61: 0 | BL61: not reported | BP61: 2.6320863 | BQ61: 0.42237443 | BR61: 3658.2965 | BS61: 2001.2314 | BT61: 1121.0308 | BU61: 0 | BV61: 7369.7475 | BW61: 7516.7151
B62: burnaby-c | C62: 2022 | D62: burnaby-c:2022 | E62: 270264 | F62: 270264 | G62: FALSE | H62: 989114043 | I62: 340966120 | J62: 131947031 | K62: 41765263 | L62: 62946483 | M62: 314866584 | N62: 632482196 | O62: 585812386 | P62: 75276090 | Q62: 510536296 | R62: 109637051 | S62: 135633202 | T62: 28920117 | U62: 113205201 | V62: 40990749 | W62: 38079910 | X62: 403301657 | Y62: 275735815 | Z62: 2206434933 | AA62: 2602789540 | AB62: 471614609 | AC62: 2131174931 | AD62: 5502236032 | AE62: 1563373643 | AF62: 574429932 | AG62: 2137803575 | AH62: 0 | AI62: 0 | AJ62: 0 | AK62: 0 | AL62: 631224359 | AM62: 157806090 | AN62: 0 | AO62: 157806090 | AP62: 129597735336 | AQ62: 100779976583 | AR62: 310478063 | AS62: 678445706 | AT62: 1810127 | AU62: 2800 | AV62: 6485 | AW62: 4675479548 | AX62: 3364432457 | AY62: 275735815 | AZ62: 229311663 | BA62: 2041647549 | BB62: 0 | BD62: 0.63944315 | BE62: 0.4077403 | BF62: 0 | BG62: 0 | BH62: 4.1873684 | BI62: 0.49777172 | BJ62: 0 | BL62: not reported | BP62: 2.3957059 | BQ62: 0.43176561 | BR62: 3659.8069 | BS62: 2167.5561 | BT62: 1148.7955 | BU62: 0 | BV62: 7910.0567 | BW62: 7554.2712
B63: burnaby-c | C63: 2023 | D63: burnaby-c:2023 | E63: 279948 | F63: 279948 | G63: FALSE | H63: 864869965 | I63: 359758119 | J63: 250140202 | K63: 57564736 | L63: 90777246 | M63: 97464096 | N63: 709841133 | O63: 623110858 | P63: 78511042 | Q63: 544599816 | R63: 122564476 | S63: 145212509 | T63: 30522815 | U63: 126054006 | V63: 42593772 | W63: 41180318 | X63: 241759107 | Y63: 282513314 | Z63: 2242938806 | AA63: 2648330131 | AB63: 488383820 | AC63: 2159946311 | AD63: 5742168285 | AE63: 1566217886 | AF63: 610928832 | AG63: 2177146718 | AH63: 0 | AI63: 0 | AJ63: 0 | AK63: 0 | AL63: 703176567 | AM63: 175794142 | AN63: 0 | AO63: 175794142 | AP63: 146522747198 | AQ63: 113739171045 | AR63: 328121425 | AS63: 723496747 | AT63: 1991503 | AU63: 2914 | AV63: 6807 | AW63: 4948724586 | AX63: 3573094579 | AY63: 282513314 | AZ63: 2.6681653e+08 | BA63: 2167866313 | BB63: 0 | BD63: 0.82074897 | BE63: 0.27953232 | BF63: 0 | BG63: 0 | BH63: 3.9977001 | BI63: 0.49467822 | BJ63: 0 | BL63: not reported | BP63: 2.239389 | BQ63: 0.42808873 | BR63: 3089.395 | BS63: 2225.8093 | BT63: 1172.0799 | BU63: 0 | BV63: 7776.9683 | BW63: 7743.8178
B64: burnaby-c | C64: 2024 | D64: burnaby-c:2024 | E64: 279948 | F64: 279948 | G64: FALSE | H64: 977425314 | I64: 381984552 | J64: 225369432 | K64: 48400916 | L64: 99707529 | M64: 218581055 | N64: 710443343 | O64: 666099760 | P64: 87978985 | Q64: 578120775 | R64: 106808669 | S64: 158760541 | T64: 35343904 | U64: 137091647 | V64: 45125487 | W64: 51937196 | X64: 311325554 | Y64: 461039449 | Z64: 2215283071 | AA64: 2674413710 | AB64: 572579804 | AC64: 2101833906 | AD64: 6053493839 | AE64: 1595311762 | AF64: 515892520 | AG64: 2111204282 | AH64: 0 | AI64: 0 | AJ64: 0 | AK64: 0 | AL64: 709572513 | AM64: 177393128 | AN64: 0 | AO64: 177393128 | AP64: 154805597280 | AQ64: 120464359054 | AR64: 349573565 | AS64: 782806377 | AT64: 2079173 | AU64: 3098 | AV64: 7327 | AW64: 5380087868 | AX64: 3942289557 | AY64: 461039449 | AZ64: 3.3976286e+08 | BA64: 10333556649 | BB64: 206006645 | BC64: 0.93846686 | BD64: 0.72685179 | BE64: 0.31851595 | BF64: 0 | BG64: 0 | BH64: 3.6518395 | BI64: 0.46581696 | BJ64: 2.6048216 | BK64: 0.025622445 | BL64: plausible | BM64: 2.2916956e+08 | BN64: 1.4825829 | BO64: 0 | BP64: 2.2581455 | BQ64: 0.42281971 | BR64: 3491.4531 | BS64: 2379.3696 | BT64: 1248.7089 | BU64: 0 | BV64: 7541.4158 | BW64: 36912.415
B65: burns-lake-v | C65: 2019 | D65: burns-lake-v:2019 | E65: 1871 | F65: 1871 | G65: FALSE | H65: 10151324 | I65: 1906886 | J65: 1162765 | K65: 5545996 | L65: 200395 | M65: 0 | N65: 4605328 | O65: 4744885 | P65: 940730 | Q65: 3804155 | R65: 658262 | S65: 403252 | T65: 857008 | U65: 785189 | V65: 322389 | W65: 377854 | X65: 5406439 | Y65: 2735621 | Z65: 8481136 | AA65: 18939123 | AB65: 908126 | AC65: 18030997 | AD65: 38623871 | AE65: 14924307 | AF65: 3459559 | AG65: 18383866 | AH65: 279592 | AI65: 187262 | AJ65: 98761 | AK65: 11299 | AL65: 4073673 | AM65: 1018418 | AN65: 110060 | AO65: 770903 | AP65: 123159080 | AQ65: 89173300 | AR65: 1182973.8 | AS65: 3247115.1 | AT65: 151832 | AU65: 1067.0176 | AV65: 3228.1089 | AW65: 35250142 | AX65: 20519597 | AY65: 2735621 | AZ65: 2735621 | BA65: 505211 | BB65: 0 | BD65: 0.45366772 | BE65: 0.53258462 | BF65: 0.10806957 | BG65: 0.027017387 | BH65: 4.8325754 | BI65: 0.42396242 | BJ65: 0 | BL65: not reported | BP65: 9.6052504 | BQ65: 0.33053953 | BR65: 5425.6141 | BS65: 2536.0155 | BT65: 632.2682 | BU65: 149.43453 | BV65: 9825.69 | BW65: 270.02191
B66: burns-lake-v | C66: 2020 | D66: burns-lake-v:2020 | E66: 1869 | F66: 1869 | G66: FALSE | H66: 9663725 | I66: 1945386 | J66: 1278386 | K66: 6567707 | L66: 168696 | M66: 0 | N66: 3096018 | O66: 4774983 | P66: 803888 | Q66: 3971095 | R66: 608052 | S66: 383312 | T66: 974756 | U66: 889641 | V66: 424995 | W66: 290294 | X66: 4888742 | Y66: 6191431 | Z66: 8493359 | AA66: 18895545 | AB66: 1381883 | AC66: 17513662 | AD66: 43512613 | AE66: 14900381 | AF66: 3219039 | AG66: 18119420 | AH66: 513947 | AI66: 297163 | AJ66: 62808 | AK66: 4376 | AL66: 4025273 | AM66: 1006318 | AN66: 67184 | AO66: 939134 | AP66: 125852250 | AQ66: 89907100 | AR66: 1233522 | AS66: 3458273 | AT66: 152801 | AU66: 1077 | AV66: 3203 | AW66: 41414548 | AX66: 25907140 | AY66: 6191431 | AZ66: 4463526 | BA66: 4847475 | BB66: 0 | BD66: 0.32037522 | BE66: 0.50588588 | BF66: 0.066762196 | BG66: 0.016690545 | BH66: 4.5628271 | BI66: 0.42408119 | BJ66: 0 | BL66: not reported | BP66: 9.8013504 | BQ66: 0.33624727 | BR66: 5170.5324 | BS66: 2554.8331 | BT66: 659.99037 | BU66: 274.98502 | BV66: 9694.7138 | BW66: 2593.6196
B67: burns-lake-v | C67: 2021 | D67: burns-lake-v:2021 | E67: 1880 | F67: 1880 | G67: FALSE | H67: 10974650 | I67: 2046348 | J67: 1490207 | K67: 3103353 | L67: 92868 | M67: 0 | N67: 7871297 | O67: 5283271 | P67: 987967 | Q67: 4295304 | R67: 798946 | S67: 351723 | T67: 907258 | U67: 844866 | V67: 628157 | W67: 335442 | X67: 5691379 | Y67: 2293525 | Z67: 8686910 | AA67: 24351482 | AB67: 2062052 | AC67: 22289430 | AD67: 49604535 | AE67: 20290604 | AF67: 2634431 | AG67: 22925035 | AH67: 533198 | AI67: 87469 | AJ67: 68218 | AK67: 4742 | AL67: 4238387 | AM67: 1059597 | AN67: 72960 | AO67: 986637 | AP67: 141289470 | AQ67: 102654500 | AR67: 1287074 | AS67: 3683248 | AT67: 174980 | AU67: 1187 | AV67: 3400 | AW67: 43699931 | AX67: 27212698 | AY67: 2293525 | AZ67: 3740192.3 | BA67: 564680 | BB67: 0 | BD67: 0.71722533 | BE67: 0.51859321 | BF67: 0.068856367 | BG67: 0.017214096 | BH67: 5.3372322 | BI67: 0.38222179 | BJ67: 0 | BL67: not reported | BP67: 9.1094828 | BQ67: 0.34911765 | BR67: 5837.5798 | BS67: 2810.2505 | BT67: 684.61383 | BU67: 283.61596 | BV67: 12194.168 | BW67: 300.3617
B68: burns-lake-v | C68: 2022 | D68: burns-lake-v:2022 | E68: 1887 | F68: 1887 | G68: FALSE | H68: 8769831 | I68: 2264755 | J68: 1536504 | K68: 2688945 | L68: 180362 | M68: 0 | N68: 6080886 | O68: 5454542 | P68: 971042 | Q68: 4483500 | R68: 867942 | S68: 409292 | T68: 877994 | U68: 908127 | V68: 522941 | W68: 354155 | X68: 3315289 | Y68: 2869825 | Z68: 9553805 | AA68: 24103990 | AB68: 1347055 | AC68: 22756935 | AD68: 51877844 | AE68: 21474235 | AF68: 1905052 | AG68: 23379287 | AH68: 528315 | AI68: 123080 | AJ68: 127963 | AK68: 11408 | AL68: 6272543 | AM68: 1568136 | AN68: 139371 | AO68: 1263190 | AP68: 165723025 | AQ68: 125459000 | AR68: 1369488 | AS68: 3903404 | AT68: 213542 | AU68: 1344 | AV68: 3654 | AW68: 45975486 | AX68: 29026872 | AY68: 2869825 | AZ68: 3784927 | BA68: 1890414 | BB68: 0 | BD68: 0.69338691 | BE68: 0.3780334 | BF68: 0.088876858 | BG68: 0.022219218 | BH68: 5.214517 | BI68: 0.38445245 | BJ68: 0 | BL68: not reported | BP68: 8.2637159 | BQ68: 0.36781609 | BR68: 4647.4992 | BS68: 2890.5893 | BT68: 725.74881 | BU68: 279.97615 | BV68: 12389.659 | BW68: 1001.8092
B69: burns-lake-v | C69: 2023 | D69: burns-lake-v:2023 | E69: 1932 | F69: 1932 | G69: FALSE | H69: 11129627 | I69: 2476665 | J69: 2046991 | K69: 4197671 | L69: 536507 | M69: 0 | N69: 6931956 | O69: 6339470 | P69: 1202378 | Q69: 5137092 | R69: 765532 | S69: 654970 | T69: 1047455 | U69: 1065446 | V69: 521632 | W69: 408702 | X69: 4790157 | Y69: 4464624 | Z69: 10644736 | AA69: 27232350 | AB69: 3178360 | AC69: 24053990 | AD69: 56662108 | AE69: 23173586 | AF69: 1645970 | AG69: 24819556 | AH69: 440314 | AI69: 0 | AJ69: 88001 | AK69: 25309 | AL69: 6694128 | AM69: 1673532 | AN69: 113310 | AO69: 1390207 | AP69: 187769725 | AQ69: 143327900 | AR69: 1464673 | AS69: 4224224 | AT69: 242635 | AU69: 1449 | AV69: 3921 | AW69: 50503466 | AX69: 32445418 | AY69: 4464624 | AZ69: 3209324.7 | BA69: 2665131 | BB69: 0 | BD69: 0.62283812 | BE69: 0.4303969 | BF69: 0.067707101 | BG69: 0.016926775 | BH69: 4.8314408 | BI69: 0.3774807 | BJ69: 0 | BL69: not reported | BP69: 7.8003682 | BQ69: 0.36954858 | BR69: 5760.6765 | BS69: 3281.2992 | BT69: 758.11232 | BU69: 227.9058 | BV69: 12846.561 | BW69: 1379.4674
B70: burns-lake-v | C70: 2024 | D70: burns-lake-v:2024 | E70: 1932 | F70: 1932 | G70: FALSE | H70: 14359788 | I70: 2459029 | J70: 2336712 | K70: 8514138 | L70: 492124 | M70: 788573 | N70: 5057077 | O70: 6902724 | P70: 1279955 | Q70: 5622769 | R70: 954611 | S70: 548644 | T70: 1187026 | U70: 1216957 | V70: 519863 | W70: 425399 | X70: 7457064 | Y70: 8950050 | Z70: 9573723 | AA70: 27457340 | AB70: 2182577 | AC70: 25274763 | AD70: 65573750 | AE70: 22543649 | AF70: 3085139 | AG70: 25628788 | AH70: 0 | AI70: 0 | AJ70: 440314 | AK70: 14379 | AL70: 5845065 | AM70: 1461266 | AN70: 454693 | AO70: 1006573 | AP70: 190848390 | AQ70: 139901400 | AR70: 1555739 | AS70: 4392066 | AT70: 234629 | AU70: 1422 | AV70: 3840 | AW70: 59452018 | AX70: 40114016 | AY70: 8950050 | AZ70: 5428166.3 | BA70: 139952696 | BB70: 4980000 | BC70: 0 | BD70: 0.35216934 | BE70: 0.51930182 | BF70: 0.31116374 | BG70: 0.077790923 | BH70: 4.5580368 | BI70: 0.35958921 | BJ70: 2.4969062 | BK70: 0.037087039 | BL70: plausible | BM70: 3195927.6 | BN70: 1.6984635 | BO70: 0 | BP70: 8.1517009 | BQ70: 0.3703125 | BR70: 7432.6025 | BS70: 3572.8385 | BT70: 805.24793 | BU70: 0 | BV70: 13265.418 | BW70: 72439.284
B71: cache-creek-v | C71: 2019 | D71: cache-creek-v:2019 | E71: 1052 | F71: 1052 | G71: FALSE | H71: 3344615 | I71: 803066 | J71: 508997 | K71: 1945077 | L71: 78307 | M71: 0 | N71: 1399538 | O71: 2822825 | P71: 601648 | Q71: 2221177 | R71: 619572 | S71: 67792 | T71: 431975 | U71: 286157 | V71: 266919 | W71: 302244 | X71: 521790 | Y71: 1596176 | Z71: 2535139 | AA71: 3484863 | AB71: 624339 | AC71: 2860524 | AD71: 16651967 | AE71: 2882598 | AF71: 10383 | AG71: 2892981 | AH71: 0 | AI71: 0 | AJ71: 0 | AK71: 0 | AL71: 1781157 | AM71: 445289 | AN71: 0 | AO71: 445289 | AP71: 100029762 | AQ71: 73075800 | AR71: 522109.59 | AS71: 1745919.9 | AT71: 150095 | AU71: 453.36195 | AV71: 2060.8498 | AW71: 23529811 | AX71: 13758986 | AY71: 1596176 | AZ71: 1596176 | BA71: 35565970 | BB71: 807500 | BC71: 0 | BD71: 0.41844517 | BE71: 0.15600899 | BF71: 0 | BG71: 0 | BH71: 1.3024541 | BI71: 0.45101997 | BJ71: 1.5555875 | BK71: 0.023961424 | BL71: plausible | BM71: 935916.1 | BP71: 5.2195424 | BQ71: 0.21998786 | BR71: 3179.2918 | BS71: 2683.2937 | BT71: 496.30189 | BU71: 0 | BV71: 2749.9819 | BW71: 33807.956
B72: cache-creek-v | C72: 2020 | D72: cache-creek-v:2020 | E72: 1058 | F72: 1058 | G72: FALSE | H72: 3047340 | I72: 780180 | J72: 614375 | K72: 1622694 | L72: 30091 | M72: 0 | N72: 1424646 | O72: 3131972 | P72: 612115 | Q72: 2519857 | R72: 571599 | S72: 68989 | T72: 827862 | U72: 168103 | V72: 250687 | W72: 271309 | X72: -84632 | Y72: 488193 | Z72: 3111187 | AA72: 3317745 | AB72: 384047 | AC72: 2933698 | AD72: 16567335 | AE72: 2921889 | AF72: 10383 | AG72: 2932272 | AH72: 0 | AI72: 0 | AJ72: 0 | AK72: 0 | AL72: 1827177 | AM72: 456794 | AN72: 0 | AO72: 456794 | AP72: 105889612 | AQ72: 77982200 | AR72: 544911 | AS72: 1732913 | AT72: 159985 | AU72: 483 | AV72: 2139 | AW72: 23972180 | AX72: 13589240 | AY72: 488193 | AZ72: 1042184.5 | BA72: 35619052 | BB72: 647500 | BC72: 0 | BD72: 0.46750477 | BE72: -0.027772418 | BF72: 0 | BG72: 0 | BH72: 1.163666 | BI72: 0.47081484 | BJ72: 1.5281279 | BK72: 0.01921365 | BL72: plausible | BM72: 935390 | BP72: 5.1460289 | BQ72: 0.22580645 | BR72: 2880.2836 | BS72: 2960.276 | BT72: 515.03875 | BU72: 0 | BV72: 2771.5236 | BW72: 33666.401
B73: cache-creek-v | C73: 2021 | D73: cache-creek-v:2021 | E73: 1064 | F73: 1064 | G73: FALSE | H73: 3475015 | I73: 901823 | J73: 962388 | K73: 1593761 | L73: 17043 | M73: 0 | N73: 1881254 | O73: 2582887 | P73: 626966 | Q73: 1955921 | R73: 615707 | S73: 102841 | T73: 337207 | U73: 140090 | V73: 200067 | W73: 230216 | X73: 892128 | Y73: 1156568 | Z73: 3179525 | AA73: 3653947 | AB73: 363801 | AC73: 3290146 | AD73: 17459463 | AE73: 3330238 | AF73: 10383 | AG73: 3340621 | AH73: 0 | AI73: 0 | AJ73: 0 | AK73: 0 | AL73: 2292781 | AM73: 573195 | AN73: 0 | AO73: 573195 | AP73: 112833717 | AQ73: 85776500 | AR73: 622864 | AS73: 2029888 | AT73: 179609 | AU73: 641 | AV73: 2572 | AW73: 25128748 | AX73: 14118842 | AY73: 1156568 | AZ73: 1080312.3 | BA73: 36597783 | BB73: 647500 | BC73: 0 | BD73: 0.54136572 | BE73: 0.25672637 | BF73: 0 | BG73: 0 | BH73: 1.7079529 | BI73: 0.49525093 | BJ73: 1.5159036 | BK73: 0.01921365 | BL73: plausible | BM73: 950420.02 | BN73: 1.1366683 | BO73: 0 | BP73: 5.5201939 | BQ73: 0.2492224 | BR73: 3265.9915 | BS73: 2427.5254 | BT73: 585.3985 | BU73: 0 | BV73: 3139.6814 | BW73: 34396.413
B74: cache-creek-v | C74: 2022 | D74: cache-creek-v:2022 | E74: 1076 | F74: 1076 | G74: FALSE | H74: 4473055 | I74: 1169745 | J74: 1264725 | K74: 1973279 | L74: 65306 | M74: 0 | N74: 2499776 | O74: 2970805 | P74: 629330 | Q74: 2341475 | R74: 683388 | S74: 64812 | T74: 334071 | U74: 156954 | V74: 217524 | W74: 272244 | X74: 1502250 | Y74: 1396908 | Z74: 3802151 | AA74: 4761199 | AB74: 482046 | AC74: 4279153 | AD74: 18961712 | AE74: 4288279 | AF74: 10383 | AG74: 4298662 | AH74: 0 | AI74: 0 | AJ74: 0 | AK74: 0 | AL74: 3017776 | AM74: 754444 | AN74: 0 | AO74: 754444 | AP74: 146022798 | AQ74: 115422300 | AR74: 803213 | AS74: 1761587 | AT74: 246828 | AU74: 943 | AV74: 3281 | AW74: 26302286 | AX74: 14663050 | AY74: 1396908 | AZ74: 1013889.7 | BA74: 14663050 | BB74: 670000 | BC74: 0 | BD74: 0.55885206 | BE74: 0.33584429 | BF74: 0 | BG74: 0 | BH74: 1.8358778 | BI74: 0.48926703 | BJ74: 0.51073297 | BK74: 0.055144523 | BL74: replacement value implausible | BP74: 5.5006 | BQ74: 0.28741237 | BR74: 4157.1143 | BS74: 2760.9712 | BT74: 746.48048 | BU74: 0 | BV74: 3995.039 | BW74: 13627.37
B75: cache-creek-v | C75: 2023 | D75: cache-creek-v:2023 | E75: 1111 | F75: 1111 | G75: FALSE | H75: 5998163 | I75: 1301274 | J75: 1397068 | K75: 3049245 | L75: 250576 | M75: 0 | N75: 2948918 | O75: 3690628 | P75: 669144 | Q75: 3021484 | R75: 581661 | S75: 85991 | T75: 1120027 | U75: 131628 | V75: 259479 | W75: 417582 | X75: 2307535 | Y75: 1003620 | Z75: 5659355 | AA75: 7193374 | AB75: 1415933 | AC75: 5777441 | AD75: 20859804 | AE75: 6279647 | AF75: 10383 | AG75: 6290030 | AH75: 0 | AI75: 0 | AJ75: 0 | AK75: 0 | AL75: 3350918 | AM75: 837730 | AN75: 0 | AO75: 837730 | AP75: 169365675 | AQ75: 136497727 | AR75: 852548 | AS75: 2638896 | AT75: 291086 | AU75: 1034 | AV75: 3640 | AW75: 27361389 | AX75: 15021473 | AY75: 1003620 | AZ75: 1185698.7 | BA75: 15021473 | BB75: 670000 | BC75: 0 | BD75: 0.49163686 | BE75: 0.38470695 | BF75: 0 | BG75: 0 | BH75: 2.0817684 | BI75: 0.47001334 | BJ75: 0.52998666 | BK75: 0.048151282 | BL75: replacement value implausible | BP75: 5.0337709 | BQ75: 0.28406593 | BR75: 5398.8866 | BS75: 3321.8974 | BT75: 767.36994 | BU75: 0 | BV75: 5661.5932 | BW75: 13520.678
B76: cache-creek-v | C76: 2024 | D76: cache-creek-v:2024 | E76: 1111 | F76: 1111 | G76: FALSE | H76: 6221134 | I76: 1434438 | J76: 1699444 | K76: 2752809 | L76: 334443 | M76: 0 | N76: 3468325 | O76: 3308552 | P76: 726950 | Q76: 2581602 | R76: 767708 | S76: 121282 | T76: 374416 | U76: 131949 | V76: 337507 | W76: 305007 | X76: 2912582 | Y76: 2135424 | Z76: 6464426 | AA76: 8442054 | AB76: 1172828 | AC76: 7269226 | AD76: 23772386 | AE76: 6756424 | AF76: 1057361 | AG76: 7813785 | AH76: 0 | AI76: 0 | AJ76: 0 | AK76: 0 | AL76: 3909525 | AM76: 977381 | AN76: 0 | AO76: 977381 | AP76: 174453341 | AQ76: 138323394 | AR76: 916533 | AS76: 2892258 | AT76: 291523 | AU76: 1093 | AV76: 3851 | AW76: 29496813 | AX76: 16429941 | AY76: 2135424 | AZ76: 1511984 | BA76: 26345066 | BB76: 9915125 | BC76: 0 | BD76: 0.55750688 | BE76: 0.46817542 | BF76: 0 | BG76: 0 | BH76: 3.0267195 | BI76: 0.47775514 | BJ76: 0.88476482 | BK76: 0.40973596 | BL76: replacement value implausible | BP76: 5.2537429 | BQ76: 0.28382238 | BR76: 5599.5806 | BS76: 2977.9946 | BT76: 824.9622 | BU76: 0 | BV76: 7033.1098 | BW76: 23712.931
B77: campbell-river-c | C77: 2019 | D77: campbell-river-c:2019 | E77: 35849 | F77: 35849 | G77: FALSE | H77: 80659769 | I77: 35733155 | J77: 27305293 | K77: 4961948 | L77: 1844826 | M77: 10476156 | N77: 65221665 | O77: 65446255 | P77: 9740160 | Q77: 55706095 | R77: 7663354 | S77: 18173757 | T77: 8045251 | U77: 7176015 | V77: 4833709 | W77: 2836749 | X77: 15213514 | Y77: 25542531 | Z77: 90738076 | AA77: 98352186 | AB77: 53503125 | AC77: 44849061 | AD77: 319829637 | AE77: 54067553 | AF77: 3727514 | AG77: 57795067 | AH77: 12552229 | AI77: 0 | AJ77: 521856 | AK77: 525724 | AL77: 65879452 | AM77: 16469863 | AN77: 1047580 | AO77: 15422283 | AP77: 6105615853 | AQ77: 5432578045 | AR77: 34792329 | AS77: 76415568 | AT77: 419705 | AU77: 1972.7478 | AV77: 4431.5766 | AW77: 485578908 | AX77: 274586799 | AY77: 25542531 | AZ77: 25542531 | BA77: 45263234 | BB77: 0 | BD77: 0.80860218 | BE77: 0.18861341 | BF77: 0.063605872 | BG77: 0.015901468 | BH77: 1.0374999 | BI77: 0.47918373 | BJ77: 0 | BL77: not reported | BP77: 5.6984144 | BQ77: 0.4451571 | BR77: 2249.9866 | BS77: 1825.6089 | BT77: 970.5244 | BU77: 350.14168 | BV77: 1612.1807 | BW77: 1262.608
B78: campbell-river-c | C78: 2020 | D78: campbell-river-c:2020 | E78: 36167 | F78: 36167 | G78: FALSE | H78: 80893466 | I78: 37116850 | J78: 25154974 | K78: 13423632 | L78: 921336 | M78: 3991202 | N78: 63478632 | O78: 63366776 | P78: 10323551 | Q78: 53043225 | R78: 8870627 | S78: 17719006 | T78: 7598943 | U78: 6132341 | V78: 4281471 | W78: 2788966 | X78: 17526690 | Y78: 22095440 | Z78: 99280783 | AA78: 107977634 | AB78: 56822868 | AC78: 51154766 | AD78: 337356328 | AE78: 59865870 | AF78: 3477059 | AG78: 63342929 | AH78: 11691943 | AI78: 0 | AJ78: 779937 | AK78: 428411 | AL78: 63701429 | AM78: 15925357 | AN78: 1208348 | AO78: 14717009 | AP78: 6730042905 | AQ78: 6002921895 | AR78: 36445185 | AS78: 78262139 | AT78: 455481 | AU78: 2031 | AV78: 4607 | AW78: 506345107 | AX78: 285705342 | AY78: 22095440 | AZ78: 23818986 | BA78: 50399399 | BB78: 0 | BD78: 0.7847189 | BE78: 0.21666385 | BF78: 0.075875724 | BG78: 0.018968931 | BH78: 1.1941757 | BI78: 0.48391675 | BJ78: 0 | BL78: not reported | BP78: 5.4152976 | BQ78: 0.44085088 | BR78: 2236.6651 | BS78: 1752.0606 | BT78: 1007.6917 | BU78: 323.27655 | BV78: 1751.4012 | BW78: 1393.5189
B79: campbell-river-c | C79: 2021 | D79: campbell-river-c:2021 | E79: 36623 | F79: 36623 | G79: FALSE | H79: 78724805 | I79: 38595055 | J79: 28133556 | K79: 3586616 | L79: 1177820 | M79: 6217350 | N79: 68920839 | O79: 67766160 | P79: 11013762 | Q79: 56752398 | R79: 8846123 | S79: 18276907 | T79: 5997194 | U79: 7091549 | V79: 4756253 | W79: 3469240 | X79: 10958645 | Y79: 16931605 | Z79: 106981305 | AA79: 113352086 | AB79: 55820140 | AC79: 57531946 | AD79: 348314974 | AE79: 66040930 | AF79: 2752286 | AG79: 68793216 | AH79: 10746957 | AI79: -56433 | AJ79: 782314 | AK79: 412844 | AL79: 69213280 | AM79: 17303320 | AN79: 1195158 | AO79: 16108162 | AP79: 7191535157 | AQ79: 6467252099 | AR79: 36341415 | AS79: 81646463 | AT79: 483444 | AU79: 2000 | AV79: 4668 | AW79: 520935303 | AX79: 290325148 | AY79: 16931605 | AZ79: 21523192 | BA79: 34727482 | BB79: 0 | BD79: 0.87546535 | BE79: 0.13920193 | BF79: 0.069071022 | BG79: 0.017267756 | BH79: 1.212164 | BI79: 0.47430367 | BJ79: 0 | BL79: not reported | BP79: 5.0533598 | BQ79: 0.42844901 | BR79: 2149.6001 | BS79: 1850.3716 | BT79: 992.31125 | BU79: 293.4483 | BV79: 1878.4156 | BW79: 948.24242
B80: campbell-river-c | C80: 2022 | D80: campbell-river-c:2022 | E80: 37185 | F80: 37185 | G80: FALSE | H80: 84004139 | I80: 40595645 | J80: 29278304 | K80: 9378944 | L80: 2669532 | M80: 1286692 | N80: 73338503 | O80: 75782043 | P80: 11368854 | Q80: 64413189 | R80: 15063692 | S80: 17617759 | T80: 6496778 | U80: 7562375 | V80: 4655255 | W80: 3478476 | X80: 8222096 | Y80: 14070986 | Z80: 110720934 | AA80: 119313172 | AB80: 56209450 | AC80: 63103722 | AD80: 356537069 | AE80: 70255913 | AF80: 3227105 | AG80: 73483018 | AH80: 9812720 | AI80: 0 | AJ80: 784367 | AK80: 403071 | AL80: 73905034 | AM80: 18476259 | AN80: 1187438 | AO80: 17288821 | AP80: 9505244578 | AQ80: 8646880744 | AR80: 38036573 | AS80: 84909817 | AT80: 644357 | AU80: 2105 | AV80: 4870 | AW80: 534184045 | AX80: 292866771 | AY80: 14070986 | AZ80: 17699344 | BA80: 41604629 | BB80: 0 | BD80: 0.8730344 | BE80: 0.097877272 | BF80: 0.064268313 | BG80: 0.016067079 | BH80: 1.140807 | BI80: 0.48990532 | BJ80: 0 | BL80: not reported | BP80: 4.0016406 | BQ80: 0.43223819 | BR80: 2259.0867 | BS80: 2037.9735 | BT80: 1022.901 | BU80: 263.8892 | BV80: 1976.1468 | BW80: 1118.8552
B81: campbell-river-c | C81: 2023 | D81: campbell-river-c:2023 | E81: 38658 | F81: 38658 | G81: FALSE | H81: 100556715 | I81: 45235399 | J81: 31157067 | K81: 13982384 | L81: 5471221 | M81: 4195613 | N81: 82378718 | O81: 81685959 | P81: 11788784 | Q81: 69897175 | R81: 12028401 | S81: 21912766 | T81: 6943050 | U81: 8502437 | V81: 5043440 | W81: 4572185 | X81: 18870756 | Y81: 19578789 | Z81: 127713587 | AA81: 134800307 | AB81: 69345422 | AC81: 65454885 | AD81: 371585474 | AE81: 81031014 | AF81: 3161690 | AG81: 84192704 | AH81: 8859654 | AI81: 0 | AJ81: 784367 | AK81: 400494 | AL81: 82835923 | AM81: 20708981 | AN81: 1184861 | AO81: 19524120 | AP81: 10690050060 | AQ81: 9745168830 | AR81: 42290835 | AS81: 92588583 | AT81: 715714 | AU81: 2306 | AV81: 5251 | AW81: 561320683 | AX81: 305478712 | AY81: 19578789 | AZ81: 16860460 | BA81: 1494710163 | BB81: 0 | BC81: 0 | BD81: 0.81922642 | BE81: 0.18766281 | BF81: 0.057214838 | BG81: 0.01430371 | BH81: 1.2045223 | BI81: 0.49203642 | BJ81: 2.7950988 | BK81: 0 | BL81: reported need implausible | BM81: 32950816 | BN81: 0.51168566 | BO81: 16090356 | BP81: 3.9560933 | BQ81: 0.43915445 | BR81: 2601.1877 | BS81: 2113.0415 | BT81: 1093.9737 | BU81: 229.18035 | BV81: 2177.8857 | BW81: 38664.964
B82: campbell-river-c | C82: 2024 | D82: campbell-river-c:2024 | E82: 38658 | F82: 38658 | G82: FALSE | H82: 101459015 | I82: 46883156 | J82: 34671347 | K82: 7322159 | L82: 5688076 | M82: 5435737 | N82: 88701119 | O82: 84988793 | P82: 12264275 | Q82: 72724518 | R82: 11238715 | S82: 23308160 | T82: 6379351 | U82: 9368516 | V82: 5401161 | W82: 4000236 | X82: 16470222 | Y82: 29294658 | Z82: 135389078 | AA82: 142442136 | AB82: 77181618 | AC82: 65260518 | AD82: 388055696 | AE82: 76472143 | AF82: 3203012 | AG82: 79675155 | AH82: 7990985 | AI82: 0 | AJ82: 715448 | AK82: 363538 | AL82: 87732062 | AM82: 21933016 | AN82: 1078986 | AO82: 20854030 | AP82: 10870710297 | AQ82: 9864319373 | AR82: 44547070 | AS82: 103910174 | AT82: 714553 | AU82: 2404 | AV82: 5556 | AW82: 588345756 | AX82: 322131951 | AY82: 29294658 | AZ82: 20981478 | BA82: 1470627666 | BB82: 273893835 | BC82: 0 | BD82: 0.87425567 | BE82: 0.16233375 | BF82: 0.049194602 | BG82: 0.012298651 | BH82: 1.0955749 | BI82: 0.49885389 | BJ82: 2.6532943 | BK82: 0.19343703 | BL82: reported need implausible | BM82: 32540731 | BN82: 0.64477586 | BO82: 11559253 | BP82: 4.0978987 | BQ82: 0.43268539 | BR82: 2624.5283 | BS82: 2198.4788 | BT82: 1152.3377 | BU82: 206.70974 | BV82: 2061.0263 | BW82: 38042.001
B83: canal-flats-v | C83: 2019 | D83: canal-flats-v:2019 | E83: 723 | F83: 723 | G83: FALSE | H83: 2565688 | I83: 1075618 | J83: 360096 | K83: 1055772 | L83: 19546 | M83: 40184 | N83: 1469732 | O83: 3149535 | P83: 1114659 | Q83: 2034876 | R83: 443526 | S83: 205657 | T83: 352062 | U83: 432388 | V83: 204945 | W83: 155892 | X83: -583847 | Y83: 233804 | Z83: 1211982 | AA83: 1637131 | AB83: 2805268 | AC83: -1168137 | AD83: 31694335 | AE83: 915533 | AF83: 145828 | AG83: 1061361 | AH83: 2200804 | AI83: 0 | AJ83: 83509 | AK83: 67331 | AL83: 1801327 | AM83: 450332 | AN83: 150840 | AO83: 299492 | AP83: 134088484 | AQ83: 123351700 | AR83: 559685.39 | AS83: 1742019.5 | AT83: 220022 | AU83: 779.53795 | AV83: 2170.5181 | AW83: 48310836 | AX83: 32833779 | AY83: 233804 | AZ83: 233804 | BA83: 939367 | BB83: 0 | BD83: 0.57284128 | BE83: -0.22755963 | BF83: 0.33495288 | BG83: 0.083738266 | BH83: 0.5215851 | BI83: 0.32671685 | BJ83: 0 | BL83: not reported | BP83: 4.1740004 | BQ83: 0.35914832 | BR83: 3548.6694 | BS83: 4356.2033 | BT83: 774.11534 | BU83: 3043.9889 | BV83: 1467.9959 | BW83: 1299.2628
B84: canal-flats-v | C84: 2020 | D84: canal-flats-v:2020 | E84: 733 | F84: 733 | G84: FALSE | H84: 3330307 | I84: 1150017 | J84: 332809 | K84: 1738861 | L84: 9887 | M84: 73230 | N84: 1518216 | O84: 2963260 | P84: 1085633 | Q84: 1877627 | R84: 360037 | S84: 167140 | T84: 358334 | U84: 375313 | V84: 215814 | W84: 140827 | X84: 367047 | Y84: 912778 | Z84: 2770260 | AA84: 3194609 | AB84: 3819774 | AC84: -625165 | AD84: 32061380 | AE84: 1265081 | AF84: 244600 | AG84: 1509681 | AH84: 2109224 | AI84: 0 | AJ84: 85009 | AK84: 67605 | AL84: 1863518 | AM84: 465880 | AN84: 152614 | AO84: 313266 | AP84: 144374724 | AQ84: 129420300 | AR84: 607948 | AS84: 1884987 | AT84: 230647 | AU84: 801 | AV84: 2767 | AW84: 49223614 | AX84: 32660924 | AY84: 912778 | AZ84: 573291 | BA84: 1170710 | BB84: 0 | BD84: 0.45587869 | BE84: 0.11021416 | BF84: 0.32758221 | BG84: 0.08189564 | BH84: 0.80403669 | BI84: 0.34467615 | BJ84: 0 | BL84: not reported | BP84: 4.2109033 | BQ84: 0.28948319 | BR84: 4543.3929 | BS84: 4042.6467 | BT84: 829.397 | BU84: 2877.5225 | BV84: 2059.5921 | BW84: 1597.1487
B85: canal-flats-v | C85: 2021 | D85: canal-flats-v:2021 | E85: 742 | F85: 742 | G85: FALSE | H85: 3666747 | I85: 1179480 | J85: 347686 | K85: 1966699 | L85: 4312 | M85: 165032 | N85: 1535016 | O85: 2874426 | P85: 1090211 | Q85: 1784215 | R85: 350104 | S85: 192936 | T85: 256321 | U85: 411298 | V85: 226527 | W85: 143177 | X85: 792321 | Y85: 1567721 | Z85: 3435420 | AA85: 3785990 | AB85: 4091055 | AC85: -305065 | AD85: 32855540 | AE85: 2135378 | AF85: 303181 | AG85: 2438559 | AH85: 2719990 | AI85: 700000 | AJ85: 80871 | AK85: 63522 | AL85: 1865684 | AM85: 466421 | AN85: 144393 | AO85: 322028 | AP85: 156290176 | AQ85: 141295487 | AR85: 645663 | AS85: 2021620 | AT85: 257538 | AU85: 888 | AV85: 2870 | AW85: 50786022 | AX85: 33136971 | AY85: 1567721 | AZ85: 904767.67 | BA85: 33136971 | BB85: 1128000 | BC85: 0 | BD85: 0.41863156 | BE85: 0.21608281 | BF85: 0.30957654 | BG85: 0.077394135 | BH85: 1.3667406 | BI85: 0.3650166 | BJ85: 0.6349834 | BK85: 0.036739902 | BL85: replacement value implausible | BP85: 4.131181 | BQ85: 0.30940767 | BR85: 4941.7075 | BS85: 3873.8895 | BT85: 870.16577 | BU85: 3665.7547 | BV85: 3286.4677 | BW85: 44658.991
B86: canal-flats-v | C86: 2022 | D86: canal-flats-v:2022 | E86: 749 | F86: 749 | G86: FALSE | H86: 3868894 | I86: 1255131 | J86: 373059 | K86: 2177445 | L86: 52038 | M86: 1578 | N86: 1689871 | O86: 3083509 | P86: 1113657 | Q86: 1969852 | R86: 434992 | S86: 179636 | T86: 294438 | U86: 504064 | V86: 245541 | W86: 153801 | X86: 785385 | Y86: 2043862 | Z86: 2911076 | AA86: 3679767 | AB86: 4129244 | AC86: -449477 | AD86: 33640923 | AE86: 1825424 | AF86: 390113 | AG86: 2215537 | AH86: 2636806 | AI86: 0 | AJ86: 72970 | AK86: 58606 | AL86: 2095014 | AM86: 523754 | AN86: 131576 | AO86: 392178 | AP86: 194256784 | AQ86: 177219525 | AR86: 674536 | AS86: 2183883 | AT86: 331751 | AU86: 956 | AV86: 2778 | AW86: 52824901 | AX86: 34062192 | AY86: 2043862 | AZ86: 1508120.3 | BA86: 21631230 | BB86: 0 | BC86: 0 | BD86: 0.436784 | BE86: 0.20299988 | BF86: 0.25121717 | BG86: 0.062804354 | BH86: 1.1247226 | BI86: 0.38552089 | BJ86: 0.35905782 | BK86: 0 | BL86: replacement value implausible | BP86: 3.4723935 | BQ86: 0.34413247 | BR86: 5165.4126 | BS86: 4116.8344 | BT86: 900.58211 | BU86: 3520.4352 | BV86: 2957.9933 | BW86: 28880.147
B87: canal-flats-v | C87: 2023 | D87: canal-flats-v:2023 | E87: 774 | F87: 774 | G87: FALSE | H87: 4823339 | I87: 1332671 | J87: 856782 | K87: 2512215 | L87: 119131 | M87: 2540 | N87: 2308584 | O87: 4800876 | P87: 1190532 | Q87: 3610344 | R87: 603481 | S87: 216505 | T87: 397735 | U87: 888630 | V87: 247276 | W87: 170474 | X87: 22463 | Y87: 2048263 | Z87: 2905080 | AA87: 3562396 | AB87: 3936981 | AC87: -374585 | AD87: 33663386 | AE87: 1805067 | AF87: 415081 | AG87: 2220148 | AH87: 2563158 | AI87: 0 | AJ87: 61144 | AK87: 81310 | AL87: 2624080 | AM87: 656020 | AN87: 142454 | AO87: 513566 | AP87: 214085952 | AQ87: 193378937 | AR87: 696459 | AS87: 2313675 | AT87: 363513 | AU87: 965 | AV87: 2829 | AW87: 53827802 | AX87: 34006396 | AY87: 2048263 | AZ87: 1886615.3 | BA87: 34006396 | BB87: 0 | BC87: 0 | BD87: 0.47862777 | BE87: 0.0046571473 | BF87: 0.21714887 | BG87: 0.054287217 | BH87: 0.61494085 | BI87: 0.3837813 | BJ87: 0.6162187 | BK87: 0 | BL87: replacement value implausible | BP87: 3.2531747 | BQ87: 0.34110993 | BR87: 6231.7041 | BS87: 6202.6822 | BT87: 899.81783 | BU87: 3311.5736 | BV87: 2868.4083 | BW87: 43935.912
B88: canal-flats-v | C88: 2024 | D88: canal-flats-v:2024 | E88: 774 | F88: 774 | G88: FALSE | H88: 4202382 | I88: 1434534 | J88: 611615 | K88: 2018402 | L88: 133352 | M88: 4479 | N88: 2179501 | O88: 5395114 | P88: 1164993 | Q88: 4230121 | R88: 637464 | S88: 194408 | T88: 293235 | U88: 669980 | V88: 227607 | W88: 167130 | X88: -1192732 | Y88: 1516529 | Z88: 3015525 | AA88: 3717334 | AB88: 3769116 | AC88: -51782 | AD88: 32470653 | AE88: 2263356 | AF88: 464877 | AG88: 2728233 | AH88: 2737144 | AI88: 250000 | AJ88: 61144 | AK88: 81310 | AL88: 2526131 | AM88: 631533 | AN88: 142454 | AO88: 489079 | AP88: 237007395 | AQ88: 214573825 | AR88: 744500 | AS88: 2496926 | AT88: 401483 | AU88: 953 | AV88: 2942 | AW88: 53465965 | AX88: 32479566 | AY88: 1516529 | AZ88: 1869551.3 | BA88: 53465965 | BB88: 20986399 | BC88: 0 | BD88: 0.51863467 | BE88: -0.28382284 | BF88: 0.22556858 | BG88: 0.056392167 | BH88: 0.64495389 | BI88: 0.4056444 | BJ88: 1 | BK88: 0.4056444 | BL88: reported need implausible | BM88: 1164993 | BN88: 1.6047747 | BO88: 0 | BP88: 3.1412522 | BQ88: 0.3239293 | BR88: 5429.4341 | BS88: 6970.4315 | BT88: 961.8863 | BU88: 3536.3618 | BV88: 3524.8488 | BW88: 69077.474
B89: castlegar-c | C89: 2019 | D89: castlegar-c:2019 | E89: 8625 | F89: 8625 | G89: FALSE | H89: 19155388 | I89: 9945372 | J89: 4787906 | K89: 3001213 | L89: 214773 | M89: 0 | N89: 16154175 | O89: 17489117 | P89: 3546118 | Q89: 13942999 | R89: 2531079 | S89: 3192275 | T89: 2342539 | U89: 1397811 | V89: 1032255 | W89: 889484 | X89: 1666271 | Y89: 4133120 | Z89: 12655178 | AA89: 15717455 | AB89: 10413379 | AC89: 5304076 | AD89: 82981909 | AE89: 6901822 | AF89: 2957260 | AG89: 9859082 | AH89: 4384247 | AI89: 3118668 | AJ89: 221544 | AK89: 104873 | AL89: 16221639 | AM89: 4055410 | AN89: 326417 | AO89: 3728993 | AP89: 1299523347 | AQ89: 974101042 | AR89: 8364937.2 | AS89: 20355671 | AT89: 309686 | AU89: 1030.666 | AV89: 3348.2116 | AW89: 153488926 | AX89: 77507074 | AY89: 4133120 | AZ89: 4133120 | BA89: 15985972 | BB89: 0 | BD89: 0.84332278 | BE89: 0.086987066 | BF89: 0.080489272 | BG89: 0.020122319 | BH89: 0.7070991 | BI89: 0.55258342 | BJ89: 0 | BL89: not reported | BP89: 6.4369272 | BQ89: 0.30782582 | BR89: 2220.9146 | BS89: 2027.7237 | BT89: 969.84779 | BU89: 508.31849 | BV89: 1143.082 | BW89: 1853.446
B90: castlegar-c | C90: 2020 | D90: castlegar-c:2020 | E90: 8600 | F90: 8600 | G90: FALSE | H90: 21659142 | I90: 10357591 | J90: 4344305 | K90: 5029263 | L90: 129891 | M90: 214413 | N90: 16415466 | O90: 17945460 | P90: 3839551 | Q90: 14105909 | R90: 2950160 | S90: 2895037 | T90: 2586693 | U90: 1305047 | V90: 1001946 | W90: 931461 | X90: 3713682 | Y90: 6150477 | Z90: 16515693 | AA90: 19436364 | AB90: 12754812 | AC90: 6681552 | AD90: 86695045 | AE90: 9704884 | AF90: 3722647 | AG90: 13427531 | AH90: 6519714 | AI90: 2386459 | AJ90: 250992 | AK90: 134796 | AL90: 15675055 | AM90: 3918764 | AN90: 385788 | AO90: 3532106 | AP90: 1365985972 | AQ90: 1034535842 | AR90: 8844013 | AS90: 20322836 | AT90: 326602 | AU90: 1098 | AV90: 3473 | AW90: 159608634 | AX90: 79787229 | AY90: 6150477 | AZ90: 5141798.5 | BA90: 16071352 | BB90: 0 | BD90: 0.75790011 | BE90: 0.17146025 | BF90: 0.098446347 | BG90: 0.024611588 | BH90: 0.95190824 | BI90: 0.55610225 | BJ90: 0 | BL90: not reported | BP90: 6.4744538 | BQ90: 0.31615318 | BR90: 2518.5049 | BS90: 2086.6814 | BT90: 1028.3736 | BU90: 758.10628 | BV90: 1561.3408 | BW90: 1868.7619
B91: castlegar-c | C91: 2021 | D91: castlegar-c:2021 | E91: 8570 | F91: 8570 | G91: FALSE | H91: 19466527 | I91: 10838865 | J91: 4900471 | K91: 3153837 | L91: 126606 | M91: 0 | N91: 16312690 | O91: 19599585 | P91: 4038057 | Q91: 15561528 | R91: 2810758 | S91: 3028313 | T91: 3431254 | U91: 1380636 | V91: 1187607 | W91: 928951 | X91: -133058 | Y91: 9406626 | Z91: 17214850 | AA91: 20483723 | AB91: 19012593 | AC91: 1471130 | AD91: 86562533 | AE91: 11263020 | AF91: 3028971 | AG91: 14291991 | AH91: 12512553 | AI91: 6738982 | AJ91: 745598 | AK91: 156804 | AL91: 16176373 | AM91: 4044093 | AN91: 902402 | AO91: 3141691 | AP91: 1452802470 | AQ91: 1119296941 | AR91: 12247188 | AS91: 24589342 | AT91: 353410 | AU91: 1147 | AV91: 3568 | AW91: 168549393 | AX91: 84783095 | AY91: 9406626 | AZ91: 6563407.7 | BA91: 16449168 | BB91: 0 | BD91: 0.83798666 | BE91: -0.0068352203 | BF91: 0.22314076 | BG91: 0.055785187 | BH91: 0.91841823 | BI91: 0.55073093 | BJ91: 0 | BL91: not reported | BP91: 8.4300435 | BQ91: 0.32146861 | BR91: 2271.4734 | BS91: 2286.9994 | BT91: 1429.0768 | BU91: 1460.0412 | BV91: 1667.6769 | BW91: 1919.3895
B92: castlegar-c | C92: 2022 | D92: castlegar-c:2022 | E92: 8744 | F92: 8744 | G92: FALSE | H92: 22045811 | I92: 11655807 | J92: 6429307 | K92: 2750102 | L92: 519361 | M92: 206936 | N92: 19088773 | O92: 21528749 | P92: 3898674 | Q92: 17630075 | R92: 3578990 | S92: 3267829 | T92: 3622065 | U92: 1436141 | V92: 1106898 | W92: 1603694 | X92: 517062 | Y92: 2553191 | Z92: 20688680 | AA92: 23298575 | AB92: 20013109 | AC92: 3285466 | AD92: 86697095 | AE92: 12481003 | AF92: 3219786 | AG92: 15700789 | AH92: 12156990 | AI92: 0 | AJ92: 347096 | AK92: 323482 | AL92: 18854349 | AM92: 4713587 | AN92: 670578 | AO92: 4043009 | AP92: 1746909110 | AQ92: 1379533541 | AR92: 12898097 | AS92: 25636055 | AT92: 435250 | AU92: 1224 | AV92: 3893 | AW92: 169084446 | AX92: 83153296 | AY92: 2553191 | AZ92: 6036764.7 | BA92: 16483568 | BB92: 0 | BD92: 0.86586849 | BE92: 0.02345398 | BF92: 0.1422649 | BG92: 0.035566224 | BH92: 0.89056847 | BI92: 0.56311046 | BJ92: 0 | BL92: not reported | BP92: 7.3833818 | BQ92: 0.31441048 | BR92: 2521.2501 | BS92: 2462.1168 | BT92: 1475.0797 | BU92: 1390.3237 | BV92: 1795.6072 | BW92: 1885.129
B93: castlegar-c | C93: 2023 | D93: castlegar-c:2023 | E93: 9042 | F93: 9042 | G93: FALSE | H93: 28124591 | I93: 12191137 | J93: 6831347 | K93: 7679987 | L93: 1224823 | M93: 192587 | N93: 20252017 | O93: 24152981 | P93: 4414957 | Q93: 19738024 | R93: 3779965 | S93: 3690253 | T93: 3943097 | U93: 1502049 | V93: 1350242 | W93: 1486466 | X93: 3971610 | Y93: 4239786 | Z93: 21731147 | AA93: 26748165 | AB93: 20653367 | AC93: 6094798 | AD93: 89713368 | AE93: 16150055 | AF93: 3554928 | AG93: 19704983 | AH93: 11951852 | AI93: 0 | AJ93: 191281 | AK93: 495039 | AL93: 20210215 | AM93: 5052554 | AN93: 686320 | AO93: 3796454 | AP93: 1985964545 | AQ93: 1587376041 | AR93: 10910166 | AS93: 26406641 | AT93: 502047 | AU93: 1318 | AV93: 4823 | AW93: 173703693 | AX93: 83281393 | AY93: 4239786 | AZ93: 5399867.7 | BA93: 18153105 | BB93: 0 | BD93: 0.72008219 | BE93: 0.14121485 | BF93: 0.13583625 | BG93: 0.033959065 | BH93: 0.99832602 | BI93: 0.58130478 | BJ93: 0 | BL93: not reported | BP93: 5.4936358 | BQ93: 0.2732739 | BR93: 3110.4392 | BS93: 2671.199 | BT93: 1206.6098 | BU93: 1321.8151 | BV93: 2179.2726 | BW93: 2007.6427
B94: castlegar-c | C94: 2024 | D94: castlegar-c:2024 | E94: 9042 | F94: 9042 | G94: FALSE | H94: 28401585 | I94: 13031654 | J94: 7044300 | K94: 3693550 | L94: 1089176 | M94: 2172270 | N94: 22535765 | O94: 26118271 | P94: 4521652 | Q94: 21596619 | R94: 3912428 | S94: 4681641 | T94: 4424362 | U94: 1871201 | V94: 1431719 | W94: 1579881 | X94: 2283314 | Y94: 11063476 | Z94: 21385443 | AA94: 28531099 | AB94: 26171405 | AC94: 2359694 | AD94: 92419423 | AE94: 15981493 | AF94: 3822959 | AG94: 19804452 | AH94: 15717210 | AI94: 3976032 | AJ94: 191281 | AK94: 604980 | AL94: 21919205 | AM94: 5479801 | AN94: 796261 | AO94: 4466722 | AP94: 2021564905 | AQ94: 1589286141 | AR94: 11191203 | AS94: 26077080 | AT94: 498897 | AU94: 1385 | AV94: 4317 | AW94: 184523584 | AX94: 89653337 | AY94: 11063476 | AZ94: 5952151 | BA94: 418113487 | BB94: 9985216 | BC94: 0.95014911 | BD94: 0.79346857 | BE94: 0.080393894 | BF94: 0.14530838 | BG94: 0.036327093 | BH94: 0.91701632 | BI94: 0.56390456 | BJ94: 2.3884481 | BK94: 0.024849476 | BL94: plausible | BM94: 10799731 | BN94: 0.55113882 | BO94: 4847580 | BP94: 5.5359108 | BQ94: 0.32082465 | BR94: 3141.0733 | BS94: 2888.5502 | BT94: 1237.6911 | BU94: 1738.2449 | BV94: 2190.2734 | BW94: 46241.262
B95: central-saanich-d | C95: 2019 | D95: central-saanich-d:2019 | E95: 18089 | F95: 18089 | G95: FALSE | H95: 32073217 | I95: 17440454 | J95: 8972615 | K95: 2032515 | L95: 933108 | M95: 2521525 | N95: 27519177 | O95: 25442064 | P95: 3159058 | Q95: 22283006 | R95: 2256689 | S95: 8584073 | T95: 2825946 | U95: 2588828 | V95: 4596299 | W95: 795615 | X95: 6631153 | Y95: 5323100 | Z95: 37499131 | AA95: 41308334 | AB95: 20087027 | AC95: 21221307 | AD95: 112726715 | AE95: 17668007 | AF95: 13152717 | AG95: 30820724 | AH95: 8792427 | AI95: 0 | AJ95: 535783 | AK95: 352895 | AL95: 27848193 | AM95: 6962048 | AN95: 888678 | AO95: 6073370 | AP95: 5365510151 | AQ95: 4718527662 | AR95: 16975630 | AS95: 39207273 | AT95: 796126 | AU95: 2231.167 | AV95: 4773.176 | AW95: 181219378 | AX95: 90698418 | AY95: 5323100 | AZ95: 5323100 | BA95: 30972766 | BB95: 0 | BD95: 0.85801112 | BE95: 0.20675048 | BF95: 0.12764606 | BG95: 0.031911514 | BH95: 1.3831493 | BI95: 0.60248254 | BJ95: 0 | BL95: not reported | BP95: 3.1638427 | BQ95: 0.46743866 | BR95: 1773.0785 | BS95: 1406.4937 | BT95: 938.45045 | BU95: 486.06485 | BV95: 1703.8379 | BW95: 1712.2431
B96: central-saanich-d | C96: 2020 | D96: central-saanich-d:2020 | E96: 18353 | F96: 18353 | G96: FALSE | H96: 34788464 | I96: 18157240 | J96: 9736596 | K96: 4837520 | L96: 1065667 | M96: 948691 | N96: 29002253 | O96: 27015698 | P96: 3112243 | Q96: 23903455 | R96: 2940906 | S96: 8959836 | T96: 2930554 | U96: 2569981 | V96: 4972711 | W96: 895171 | X96: 7772766 | Y96: 2420659 | Z96: 49154386 | AA96: 53958437 | AB96: 24190229 | AC96: 29768208 | AD96: 120494607 | AE96: 21434853 | AF96: 17432018 | AG96: 38866871 | AH96: 8379098 | AI96: 0 | AJ96: 335363 | AK96: 311887 | AL96: 29380348 | AM96: 7345087 | AN96: 647250 | AO96: 6697837 | AP96: 5523666798 | AQ96: 4801132406 | AR96: 17771275 | AS96: 38923904 | AT96: 798851 | AU96: 2305 | AV96: 5043 | AW96: 183640037 | AX96: 90006834 | AY96: 2420659 | AZ96: 3871879.5 | BA96: 30982005 | BB96: 0 | BD96: 0.83367443 | BE96: 0.22342941 | BF96: 0.088120127 | BG96: 0.022030032 | BH96: 1.6259939 | BI96: 0.61335261 | BJ96: 0 | BL96: not reported | BP96: 3.2172967 | BQ96: 0.4570692 | BR96: 1895.5192 | BS96: 1472.0045 | BT96: 968.30355 | BU96: 456.55195 | BV96: 2117.7394 | BW96: 1688.1167
B97: central-saanich-d | C97: 2021 | D97: central-saanich-d:2021 | E97: 18522 | F97: 18522 | G97: FALSE | H97: 34506798 | I97: 18874993 | J97: 11721526 | K97: 2342572 | L97: 284261 | M97: 883446 | N97: 31280780 | O97: 28938358 | P97: 3294116 | Q97: 25644242 | R97: 2928933 | S97: 9689535 | T97: 3120722 | U97: 3006597 | V97: 5280912 | W97: 939467 | X97: 5568440 | Y97: 2725037 | Z97: 54319850 | AA97: 58734369 | AB97: 22762131 | AC97: 35972238 | AD97: 126109454 | AE97: 22480698 | AF97: 22090342 | AG97: 44571040 | AH97: 7899341 | AI97: 0 | AJ97: 339102 | AK97: 284997 | AL97: 31227605 | AM97: 7806901 | AN97: 624099 | AO97: 7182802 | AP97: 5763566627 | AQ97: 5035528083 | AR97: 18369725 | AS97: 41736092 | AT97: 842720 | AU97: 2395 | AV97: 5199 | AW97: 185426958 | AX97: 89437755 | AY97: 2725037 | AZ97: 3489598.7 | BA97: 31134315 | BB97: 0 | BD97: 0.90651065 | BE97: 0.16137226 | BF97: 0.079941964 | BG97: 0.01998549 | BH97: 1.7380525 | BI97: 0.6221243 | BJ97: 0 | BL97: not reported | BP97: 3.1872148 | BQ97: 0.46066551 | BR97: 1863.0168 | BS97: 1562.3776 | BT97: 991.7787 | BU97: 426.48423 | BV97: 2406.3838 | BW97: 1680.937
B98: central-saanich-d | C98: 2022 | D98: central-saanich-d:2022 | E98: 18689 | F98: 18689 | G98: FALSE | H98: 35557016 | I98: 19869149 | J98: 11239787 | K98: 2146032 | L98: 1447724 | M98: 854324 | N98: 32556660 | O98: 29192337 | P98: 2967547 | Q98: 26224790 | R98: 2928605 | S98: 10297399 | T98: 2791003 | U98: 3303241 | V98: 5345540 | W98: 909507 | X98: 6364679 | Y98: 4103267 | Z98: 58525837 | AA98: 63994936 | AB98: 22887546 | AC98: 41107390 | AD98: 132474133 | AE98: 24159343 | AF98: 25187929 | AG98: 49347272 | AH98: 7446614 | AI98: 0 | AJ98: 344091 | AK98: 266797 | AL98: 32873427 | AM98: 8218357 | AN98: 610888 | AO98: 7607469 | AP98: 7049670377 | AQ98: 6243391031 | AR98: 19355422 | AS98: 43478347 | AT98: 1053480 | AU98: 2547 | AV98: 5415 | AW98: 189304537 | AX98: 90573475 | AY98: 4103267 | AZ98: 3082987.7 | BA98: 31062503 | BB98: 0 | BD98: 0.91561845 | BE98: 0.17899924 | BF98: 0.074332132 | BG98: 0.018583034 | BH98: 1.8817032 | BI98: 0.62392437 | BJ98: 0 | BL98: not reported | BP98: 2.7455783 | BQ98: 0.47036011 | BR98: 1902.5639 | BS98: 1562.0064 | BT98: 1035.6585 | BU98: 398.44903 | BV98: 2640.4448 | BW98: 1662.0741
B99: central-saanich-d | C99: 2023 | D99: central-saanich-d:2023 | E99: 19326 | F99: 19326 | G99: FALSE | H99: 44020502 | I99: 20981502 | J99: 12475007 | K99: 7095865 | L99: 2778440 | M99: 689688 | N99: 36234949 | O99: 31436197 | P99: 2767924 | Q99: 28668273 | R99: 3553577 | S99: 11109135 | T99: 3202645 | U99: 3573513 | V99: 5535808 | W99: 883703 | X99: 12584305 | Y99: 4722529 | Z99: 69306230 | AA99: 75334903 | AB99: 24340131 | AC99: 50994772 | AD99: 145058438 | AE99: 30669705 | AF99: 28838870 | AG99: 59508575 | AH99: 6978217 | AI99: 0 | AJ99: 344091 | AK99: 266797 | AL99: 36472643 | AM99: 9118161 | AN99: 610888 | AO99: 8507273 | AP99: 7964177585 | AQ99: 7085871072 | AR99: 20469742 | AS99: 46240292 | AT99: 1190801 | AU99: 2694 | AV99: 5716 | AW99: 194179770 | AX99: 93221935 | AY99: 4722529 | AZ99: 3850277.7 | BA99: 31529189 | BB99: 0 | BD99: 0.82313802 | BE99: 0.28587373 | BF99: 0.066996843 | BG99: 0.016749211 | BH99: 2.0757642 | BI99: 0.62070381 | BJ99: 0 | BL99: not reported | BP99: 2.5702267 | BQ99: 0.47130861 | BR99: 2277.7865 | BS99: 1626.6272 | BT99: 1059.1815 | BU99: 361.07922 | BV99: 3079.1977 | BW99: 1631.4389
B100: central-saanich-d | C100: 2024 | D100: central-saanich-d:2024 | E100: 19326 | F100: 19326 | G100: FALSE | H100: 46138944 | I100: 22599727 | J100: 11507377 | K100: 7727216 | L100: 3204728 | M100: 1099896 | N100: 37311832 | O100: 33570018 | P100: 2897487 | Q100: 30672531 | R100: 3797414 | S100: 12072697 | T100: 3412242 | U100: 3851227 | V100: 5416992 | W100: 992364 | X100: 12568926 | Y100: 23409077 | Z100: 63429942 | AA100: 71080436 | AB100: 28229762 | AC100: 42850674 | AD100: 157338362 | AE100: 30876865 | AF100: 19961651 | AG100: 50838516 | AH100: 6493069 | AI100: 0 | AJ100: 344091 | AK100: 266797 | AL100: 37523975 | AM100: 9380994 | AN100: 610888 | AO100: 8770106 | AP100: 8048899709 | AQ100: 7118278959 | AR100: 22056252 | AS100: 50340883 | AT100: 1192021 | AU100: 2899 | AV100: 6127 | AW100: 216110737 | AX100: 113717491 | AY100: 23409077 | AZ100: 10744958 | BA100: 710716394 | BB100: 12247120 | BC100: 1 | BD100: 0.80868413 | BE100: 0.27241469 | BF100: 0.065119752 | BG100: 0.016279938 | BH100: 1.6574607 | BI100: 0.61467105 | BJ100: 3.969139 | BK100: 0.018522906 | BL100: plausible | BM100: 11500529 | BN100: 0.93430119 | BO100: 755571 | BP100: 2.7402816 | BQ100: 0.47315162 | BR100: 2387.4027 | BS100: 1737.0391 | BT100: 1141.2735 | BU100: 335.97584 | BV100: 2630.5762 | BW100: 36775.142
B101: chase-v | C101: 2019 | D101: chase-v:2019 | E101: 2478 | F101: 2478 | G101: FALSE | H101: 4076611 | I101: 2076300 | J101: 1089757 | K101: 811330 | L101: 85090 | M101: 0 | N101: 3265281 | O101: 3927199 | P101: 1170413 | Q101: 2756786 | R101: 837543 | S101: 239926 | T101: 546547 | U101: 366000 | V101: 329995 | W101: 152166 | X101: 149412 | Y101: 52690 | Z101: 3629036 | AA101: 3976247 | AB101: 2512178 | AC101: 1464069 | AD101: 33734438 | AE101: 3515697 | AF101: 0 | AG101: 3515697 | AH101: 1977503 | AI101: 0 | AJ101: 147050 | AK101: 86465 | AL101: 3658460 | AM101: 914615 | AN101: 233515 | AO101: 681100 | AP101: 384411857 | AQ101: 336953300 | AR101: 1946945.6 | AS101: 4702182.9 | AT101: 276558 | AU101: 1221.8609 | AV101: 2954.7677 | AW101: 47297034 | AX101: 32196244 | AY101: 52690 | AZ101: 52690 | BA101: 7012701 | BB101: 0 | BD101: 0.80097929 | BE101: 0.036651032 | BF101: 0.25531508 | BG101: 0.063828769 | BH101: 1.2752883 | BI101: 0.37485516 | BJ101: 0 | BL101: not reported | BP101: 5.0647386 | BQ101: 0.41352181 | BR101: 1645.1215 | BS101: 1584.8261 | BT101: 785.69232 | BU101: 798.02381 | BV101: 1418.7639 | BW101: 2829.9843
...

Sheet Data_Assets
B1: dbt gold: fct_asset_category, schedule 503 by category
B2: Loaded unchanged from data/gold/ (written by dbt) and dbt/seeds/. Formulas and Power Query read these tables by name.
B4: municipality_id | C4: year | D4: asset_category | E4: historical_cost | F4: accumulated_amortization | G4: net_book_value | H4: additions | I4: replacement_value | J4: annual_replacement_need | K4: amp_status | L4: consumption_ratio
B5: 100-mile-house-d | C5: 2019 | D5: Buildings | E5: 3399886 | F5: 2330259 | G5: 1069627 | H5: 35424 | I5: 0 | J5: 0 | K5: In_Progress | L5: 0.68539327
B6: 100-mile-house-d | C6: 2019 | D6: Drainage System | E6: 0 | F6: 0 | G6: 0 | H6: 0 | I6: 0 | J6: 0 | K6: In_Progress
B7: 100-mile-house-d | C7: 2019 | D7: Fleet | E7: 4582766 | F7: 2748773 | G7: 1833993 | H7: 80823 | I7: 0 | J7: 0 | K7: In_Progress | L7: 0.59980654
B8: 100-mile-house-d | C8: 2019 | D8: Land | E8: 1916301 | G8: 1916301 | H8: 338141 | I8: 1916301 | K8: Not applicable
B9: 100-mile-house-d | C9: 2019 | D9: Other Engineering Systems | E9: 0 | F9: 0 | G9: 0 | H9: 0 | I9: 0 | J9: 0 | K9: In_Progress
B10: 100-mile-house-d | C10: 2019 | D10: Other Tangible Capital Assets | E10: 0 | F10: 0 | G10: 0 | H10: 0 | I10: 0 | J10: 0 | K10: Not applicable
B11: 100-mile-house-d | C11: 2019 | D11: Parks and Recreation | E11: 2120823 | F11: 848550 | G11: 1272273 | H11: 13897 | I11: 0 | J11: 0 | K11: In_Progress | L11: 0.40010411
B12: 100-mile-house-d | C12: 2019 | D12: Sewer System | E12: 8004607 | F12: 3811844 | G12: 4192763 | H12: 0 | I12: 0 | J12: 0 | K12: In_Progress | L12: 0.47620626
B13: 100-mile-house-d | C13: 2019 | D13: Transportation System | E13: 23521135 | F13: 9979328 | G13: 13541807 | H13: 1658870 | I13: 0 | J13: 0 | K13: In_Progress | L13: 0.42427068
B14: 100-mile-house-d | C14: 2019 | D14: Water System | E14: 9794198 | F14: 4256001 | G14: 5538197 | H14: 1243953 | I14: 0 | J14: 0 | K14: In_Progress | L14: 0.43454308
B15: 100-mile-house-d | C15: 2019 | D15: Work In Progress | E15: 6398706 | G15: 6398706 | H15: 0 | I15: 6398706 | K15: Not applicable
B16: 100-mile-house-d | C16: 2020 | D16: Buildings | E16: 3399886 | F16: 2407982 | G16: 991904 | H16: 0 | I16: 0 | J16: 0 | K16: In_Progress | L16: 0.70825375
B17: 100-mile-house-d | C17: 2020 | D17: Drainage System | E17: 0 | F17: 0 | G17: 0 | H17: 0 | I17: 0 | J17: 0 | K17: Not applicable
B18: 100-mile-house-d | C18: 2020 | D18: Fleet | E18: 5046504 | F18: 2694340 | G18: 2352164 | H18: 814873 | I18: 0 | J18: 0 | K18: In_Progress | L18: 0.53390228
B19: 100-mile-house-d | C19: 2020 | D19: Land | E19: 1916301 | G19: 1916301 | H19: 0 | I19: 1916301 | K19: Not applicable
B20: 100-mile-house-d | C20: 2020 | D20: Other Engineering Systems | E20: 0 | F20: 0 | G20: 0 | H20: 0 | I20: 0 | J20: 0 | K20: Not applicable
B21: 100-mile-house-d | C21: 2020 | D21: Other Tangible Capital Assets | E21: 0 | F21: 0 | G21: 0 | H21: 0 | I21: 0 | J21: 0 | K21: Not applicable
B22: 100-mile-house-d | C22: 2020 | D22: Parks and Recreation | E22: 2120823 | F22: 928492 | G22: 1192331 | H22: 0 | I22: 0 | J22: 0 | K22: In_Progress | L22: 0.43779797
B23: 100-mile-house-d | C23: 2020 | D23: Sewer System | E23: 8038704 | F23: 3980247 | G23: 4058457 | H23: 76493 | I23: 0 | J23: 0 | K23: In_Progress | L23: 0.49513541
B24: 100-mile-house-d | C24: 2020 | D24: Transportation System | E24: 24080220 | F24: 10531273 | G24: 13548947 | H24: 391573 | I24: 0 | J24: 0 | K24: In_Progress | L24: 0.43734123
B25: 100-mile-house-d | C25: 2020 | D25: Water System | E25: 16312207 | F25: 4595763 | G25: 11716444 | H25: 481331 | I25: 0 | J25: 0 | K25: In_Progress | L25: 0.28173766
B26: 100-mile-house-d | C26: 2020 | D26: Work In Progress | E26: 257045 | G26: 257045 | H26: 20133 | I26: 257045 | K26: Not applicable
B27: 100-mile-house-d | C27: 2021 | D27: Buildings | E27: 3399886 | F27: 2484899 | G27: 914987 | H27: 0 | I27: 0 | J27: 0 | K27: In_Progress | L27: 0.73087715
B28: 100-mile-house-d | C28: 2021 | D28: Drainage System | E28: 0 | F28: 0 | G28: 0 | H28: 0 | I28: 0 | J28: 0 | K28: Not applicable
B29: 100-mile-house-d | C29: 2021 | D29: Fleet | E29: 5353574 | F29: 2833708 | G29: 2519866 | H29: 435180 | I29: 0 | J29: 0 | K29: In_Progress | L29: 0.52931145
B30: 100-mile-house-d | C30: 2021 | D30: Land | E30: 2088612 | G30: 2088612 | H30: 172310 | I30: 2088612 | K30: Not applicable
B31: 100-mile-house-d | C31: 2021 | D31: Other Engineering Systems | E31: 0 | F31: 0 | G31: 0 | H31: 0 | I31: 0 | J31: 0 | K31: Not applicable
B32: 100-mile-house-d | C32: 2021 | D32: Other Tangible Capital Assets | E32: 0 | F32: 0 | G32: 0 | H32: 0 | I32: 0 | J32: 0 | K32: Not applicable
B33: 100-mile-house-d | C33: 2021 | D33: Parks and Recreation | E33: 2120823 | F33: 1008434 | G33: 1112389 | H33: 0 | I33: 0 | J33: 0 | K33: In_Progress | L33: 0.47549183
B34: 100-mile-house-d | C34: 2021 | D34: Sewer System | E34: 8298042 | F34: 4152806 | G34: 4145236 | H34: 259338 | I34: 0 | J34: 0 | K34: In_Progress | L34: 0.50045613
B35: 100-mile-house-d | C35: 2021 | D35: Transportation System | E35: 24612720 | F35: 11085578 | G35: 13527142 | H35: 532500 | I35: 0 | J35: 0 | K35: In_Progress | L35: 0.45040036
B36: 100-mile-house-d | C36: 2021 | D36: Water System | E36: 16635403 | F36: 4938081 | G36: 11697322 | H36: 323196 | I36: 0 | J36: 0 | K36: In_Progress | L36: 0.29684168
B37: 100-mile-house-d | C37: 2021 | D37: Work In Progress | E37: 2213055 | G37: 2213055 | H37: 1956010 | I37: 2213055 | K37: Not applicable
B38: 100-mile-house-d | C38: 2022 | D38: Buildings | E38: 3901918 | F38: 2589538 | G38: 1312380 | H38: 502033 | I38: 0 | J38: 0 | K38: In_Progress | L38: 0.66365772
B39: 100-mile-house-d | C39: 2022 | D39: Drainage System | E39: 0 | F39: 0 | G39: 0 | H39: 0 | I39: 0 | J39: 0 | K39: Not applicable
B40: 100-mile-house-d | C40: 2022 | D40: Fleet | E40: 5438038 | F40: 3082072 | G40: 2355966 | H40: 97234 | I40: 0 | J40: 0 | K40: In_Progress | L40: 0.56676176
B41: 100-mile-house-d | C41: 2022 | D41: Land | E41: 2114120 | G41: 2114120 | H41: 91400 | I41: 2114120 | K41: Not applicable
B42: 100-mile-house-d | C42: 2022 | D42: Other Engineering Systems | E42: 0 | F42: 0 | G42: 0 | H42: 0 | I42: 0 | J42: 0 | K42: No
B43: 100-mile-house-d | C43: 2022 | D43: Other Tangible Capital Assets | E43: 0 | F43: 0 | G43: 0 | H43: 0 | I43: 0 | J43: 0 | K43: Not applicable
B44: 100-mile-house-d | C44: 2022 | D44: Parks and Recreation | E44: 2097545 | F44: 1070779 | G44: 1026766 | H44: 0 | I44: 0 | J44: 0 | K44: No | L44: 0.51049155
B45: 100-mile-house-d | C45: 2022 | D45: Sewer System | E45: 8325015 | F45: 4330753 | G45: 3994262 | H45: 26973 | I45: 0 | J45: 0 | K45: In_Progress | L45: 0.52020963
B46: 100-mile-house-d | C46: 2022 | D46: Transportation System | E46: 27492874 | F46: 11755121 | G46: 15737753 | H46: 2880160 | I46: 0 | J46: 0 | K46: In_Progress | L46: 0.42756974
B47: 100-mile-house-d | C47: 2022 | D47: Water System | E47: 16635403 | F47: 5275655 | G47: 11359748 | H47: 0 | I47: 0 | J47: 0 | K47: In_Progress | L47: 0.31713419
B48: 100-mile-house-d | C48: 2022 | D48: Work In Progress | E48: 2573062 | G48: 2573062 | H48: 360000 | I48: 2573062 | K48: Not applicable
B49: 100-mile-house-d | C49: 2023 | D49: Buildings | E49: 4614636 | F49: 2883046 | G49: 1731590 | H49: 361488 | I49: 0 | J49: 0 | K49: In_Progress | L49: 0.6247613
B50: 100-mile-house-d | C50: 2023 | D50: Drainage System | E50: 3735504 | F50: 1516823 | G50: 2218681 | H50: 0 | I50: 0 | J50: 0 | K50: In_Progress | L50: 0.40605578
B51: 100-mile-house-d | C51: 2023 | D51: Fleet | E51: 5957364 | F51: 3451391 | G51: 2505973 | H51: 519326 | I51: 0 | J51: 0 | K51: In_Progress | L51: 0.57934869
B52: 100-mile-house-d | C52: 2023 | D52: Land | E52: 2114120 | G52: 2114120 | H52: 0 | I52: 2114120 | K52: Not applicable
B53: 100-mile-house-d | C53: 2023 | D53: Other Engineering Systems | E53: 0 | F53: 0 | G53: 0 | H53: 0 | I53: 0 | J53: 0 | K53: Not applicable
B54: 100-mile-house-d | C54: 2023 | D54: Other Tangible Capital Assets | E54: 0 | F54: 0 | G54: 0 | H54: 0 | I54: 0 | J54: 0 | K54: Not applicable
B55: 100-mile-house-d | C55: 2023 | D55: Parks and Recreation | E55: 2301034 | F55: 1171815 | G55: 1129219 | H55: 216832 | I55: 0 | J55: 0 | K55: In_Progress | L55: 0.50925584
B56: 100-mile-house-d | C56: 2023 | D56: Sewer System | E56: 8325015 | F56: 4504982 | G56: 3820033 | H56: 0 | I56: 0 | J56: 0 | K56: In_Progress | L56: 0.541138
B57: 100-mile-house-d | C57: 2023 | D57: Transportation System | E57: 24435524 | F57: 10837187 | G57: 13598337 | H57: 772915 | I57: 0 | J57: 0 | K57: In_Progress | L57: 0.44350131
B58: 100-mile-house-d | C58: 2023 | D58: Water System | E58: 17611688 | F58: 5635967 | G58: 11975721 | H58: 964956 | I58: 0 | J58: 0 | K58: In_Progress | L58: 0.32001288
B59: 100-mile-house-d | C59: 2023 | D59: Work In Progress | E59: 1864368 | G59: 1864368 | H59: -708693 | I59: 1864368 | K59: Not applicable
B60: 100-mile-house-d | C60: 2024 | D60: Buildings | E60: 4137875 | F60: 2548710 | G60: 1589165 | H60: 24636 | I60: 9274849 | J60: 397893 | K60: In_Progress | L60: 0.61594659
B61: 100-mile-house-d | C61: 2024 | D61: Drainage System | E61: 3791449 | F61: 1631622 | G61: 2159827 | H61: 0 | I61: 9327325 | J61: 186546 | K61: In_Progress | L61: 0.43034259
B62: 100-mile-house-d | C62: 2024 | D62: Fleet | E62: 7049114 | F62: 3374748 | G62: 3674366 | H62: 1557210 | I62: 9151913 | J62: 762659 | K62: In_Progress | L62: 0.47874783
B63: 100-mile-house-d | C63: 2024 | D63: Land | E63: 2172862 | G63: 2172862 | H63: 58742 | I63: 2172862 | K63: Not applicable
B64: 100-mile-house-d | C64: 2024 | D64: Other Engineering Systems | E64: 0 | F64: 0 | G64: 0 | H64: 0 | I64: 0 | J64: 0
B65: 100-mile-house-d | C65: 2024 | D65: Other Tangible Capital Assets | E65: 0 | F65: 0 | G65: 0 | H65: 0 | I65: 0 | J65: 0 | K65: Not applicable
B66: 100-mile-house-d | C66: 2024 | D66: Parks and Recreation | E66: 2328033 | F66: 1268257 | G66: 1059776 | H66: 26999 | I66: 3323177 | J66: 126254 | K66: In_Progress | L66: 0.54477621
B67: 100-mile-house-d | C67: 2024 | D67: Sewer System | E67: 8325015 | F67: 4679216 | G67: 3645799 | H67: 0 | I67: 25626702 | J67: 401524 | K67: In_Progress | L67: 0.56206698
B68: 100-mile-house-d | C68: 2024 | D68: Transportation System | E68: 24678882 | F68: 11388286 | G68: 13290596 | H68: 327498 | I68: 76837134 | J68: 1835880 | K68: In_Progress | L68: 0.46145875
B69: 100-mile-house-d | C69: 2024 | D69: Water System | E69: 17615349 | F69: 5994354 | G69: 11620995 | H69: 3661 | I69: 37399402 | J69: 760946 | K69: In_Progress | L69: 0.34029153
B70: 100-mile-house-d | C70: 2024 | D70: Work In Progress | E70: 3204164 | G70: 3204164 | H70: 1339794 | I70: 3204164 | K70: Not applicable
B71: abbotsford-c | C71: 2019 | D71: Buildings | E71: 228841000 | F71: 127257000 | G71: 101584000 | H71: 1266000 | I71: 0 | J71: 0 | K71: In_Progress | L71: 0.55609353
B72: abbotsford-c | C72: 2019 | D72: Drainage System | E72: 269529000 | F72: 89001000 | G72: 180528000 | H72: 2931000 | I72: 0 | J72: 0 | K72: In_Progress | L72: 0.33020937
B73: abbotsford-c | C73: 2019 | D73: Fleet | E73: 71006000 | F73: 53230000 | G73: 17776000 | H73: 2766000 | I73: 0 | J73: 0 | K73: In_Progress | L73: 0.74965496
B74: abbotsford-c | C74: 2019 | D74: Land | E74: 455844000 | G74: 455844000 | H74: 14634000 | I74: 455844000 | K74: Not applicable
B75: abbotsford-c | C75: 2019 | D75: Other Engineering Systems | E75: 51465000 | F75: 32736000 | G75: 18729000 | H75: 0 | I75: 0 | J75: 0 | K75: In_Progress | L75: 0.63608277
B76: abbotsford-c | C76: 2019 | D76: Other Tangible Capital Assets | E76: 37141000 | F76: 13239000 | G76: 23902000 | H76: 0 | I76: 0 | J76: 0 | K76: Not applicable | L76: 0.35645244
B77: abbotsford-c | C77: 2019 | D77: Parks and Recreation | E77: 79579000 | F77: 54155000 | G77: 25424000 | H77: 111000 | I77: 0 | J77: 0 | K77: In_Progress | L77: 0.68051873
